Workbook

Sheet Navigation
B2: TRELLIS CLIMATE - PRIME COALITION
B4: Climate Tech - Bridge Rounds Research
B5: Phase 1
B8: How to use this model This workbook is structured to move from raw deal-level data to cleaned and standardized data to analytical outputs and charts. The Raw Data tab contains the full set of bridge and extension rounds pulled from source databases. The Sanitized Data tab applies consistent formatting, standardized company names, dates, subsectors, and deal attributes, and is the primary input for all analysis. The Outputs tab aggregates this data into key metrics such as repeat investors, deal size distributions, capital deployed over time, and debt usage. Charts and visuals are generated from the Analytics tab and should not be edited directly. If you plan to update the dataset, start with modifying the Raw Data tab. All downstream tabs should only be updated update regarding the string of rows used as input. The Exclusions & Distinctions tab includes two lists of companies that were reviewed manually to determine inclusion in the dataset. The tabs with the identifier "Setup" are used to avoid embedding complex formulas in the analysis tabs and can be ignored.

Sheet Outputs
B2: KEY METRICS
B5: Deal size (USD MM)
C6: Overall | D6: Renewables | E6: LDES | F6: Hydrogen | G6: CDR | H6: Industrial Decarbonization | I6: Buildings | J6: Mobility | K6: Food&Ag
B7: Minimum | C7: =_xlfn.MINIFS(Cleaned_Data!$J$3:$J$273,Cleaned_Data!$J$3:$J$273, ">0") -> 0.02 | D7: =_xlfn.MINIFS(Cleaned_Data!$J$3:$J$273,Cleaned_Data!$F$3:$F$273, "Renewables", Cleaned_Data!$J$3:$J$273, ">0") -> 0.25 | E7: =_xlfn.MINIFS(Cleaned_Data!$J$3:$J$273,Cleaned_Data!$F$3:$F$273, "LDES", Cleaned_Data!$J$3:$J$273, ">0") -> 0.08 | F7: =_xlfn.MINIFS(Cleaned_Data!$J$3:$J$273,Cleaned_Data!$F$3:$F$273, "Hydrogen", Cleaned_Data!$J$3:$J$273, ">0") -> 0.18 | G7: =_xlfn.MINIFS(Cleaned_Data!$J$3:$J$273,Cleaned_Data!$F$3:$F$273, "CDR", Cleaned_Data!$J$3:$J$273, ">0") -> 0.13 | H7: =_xlfn.MINIFS(Cleaned_Data!$J$3:$J$273,Cleaned_Data!$F$3:$F$273, "Industrial Decarbonization", Cleaned_Data!$J$3:$J$273, ">0") -> 0.1 | I7: =_xlfn.MINIFS(Cleaned_Data!$J$3:$J$273,Cleaned_Data!$F$3:$F$273, "Buildings", Cleaned_Data!$J$3:$J$273, ">0") -> 0.57 | J7: =_xlfn.MINIFS(Cleaned_Data!$J$3:$J$273,Cleaned_Data!$F$3:$F$273, "Mobility", Cleaned_Data!$J$3:$J$273, ">0") -> 0.1 | K7: =_xlfn.MINIFS(Cleaned_Data!$J$3:$J$273,Cleaned_Data!$F$3:$F$273, "Food & Ag", Cleaned_Data!$J$3:$J$273, ">0") -> 0.02
B8: Median | C8: =MEDIAN(_xlfn._xlws.FILTER(Cleaned_Data!$J$3:$J$273,Cleaned_Data!$J$3:$J$273, ">0")) -> 9.89 | D8: {=MEDIAN(_xlfn._xlws.FILTER(Cleaned_Data!$J$3:$J$273,(Cleaned_Data!$F$3:$F$273="Renewables")*(Cleaned_Data!$J$3:$J$273>0)))} -> 13 | E8: {=MEDIAN(_xlfn._xlws.FILTER(Cleaned_Data!$J$3:$J$273,(Cleaned_Data!$F$3:$F$273="LDES")*(Cleaned_Data!$J$3:$J$273>0)))} -> 6.5 | F8: {=MEDIAN(_xlfn._xlws.FILTER(Cleaned_Data!$J$3:$J$273,(Cleaned_Data!$F$3:$F$273="Hydrogen")*(Cleaned_Data!$J$3:$J$273>0)))} -> 12.5 | G8: {=MEDIAN(_xlfn._xlws.FILTER(Cleaned_Data!$J$3:$J$273,(Cleaned_Data!$F$3:$F$273="CDR")*(Cleaned_Data!$J$3:$J$273>0)))} -> 39 | H8: {=MEDIAN(_xlfn._xlws.FILTER(Cleaned_Data!$J$3:$J$273,(Cleaned_Data!$F$3:$F$273="Industrial Decarbonization")*(Cleaned_Data!$J$3:$J$273>0)))} -> 6.7 | I8: {=MEDIAN(_xlfn._xlws.FILTER(Cleaned_Data!$J$3:$J$273,(Cleaned_Data!$F$3:$F$273="Buildings")*(Cleaned_Data!$J$3:$J$273>0)))} -> 7.75 | J8: {=MEDIAN(_xlfn._xlws.FILTER(Cleaned_Data!$J$3:$J$273,(Cleaned_Data!$F$3:$F$273="Mobility")*(Cleaned_Data!$J$3:$J$273>0)))} -> 8.975 | K8: {=MEDIAN(_xlfn._xlws.FILTER(Cleaned_Data!$J$3:$J$273,(Cleaned_Data!$F$3:$F$273="Food & Ag")*(Cleaned_Data!$J$3:$J$273>0)))} -> 8
B9: Average | C9: =AVERAGEIFS(Cleaned_Data!$J$3:$J$273,Cleaned_Data!$J$3:$J$273, ">0") -> 46.603982 | D9: =AVERAGEIFS(Cleaned_Data!$J$3:$J$273,Cleaned_Data!$F$3:$F$273, "Renewables", Cleaned_Data!$J$3:$J$273, ">0") -> 88.747333 | E9: =AVERAGEIFS(Cleaned_Data!$J$3:$J$273,Cleaned_Data!$F$3:$F$273, "LDES", Cleaned_Data!$J$3:$J$273, ">0") -> 19.469 | F9: =AVERAGEIFS(Cleaned_Data!$J$3:$J$273,Cleaned_Data!$F$3:$F$273, "Hydrogen", Cleaned_Data!$J$3:$J$273, ">0") -> 51.111923 | G9: =AVERAGEIFS(Cleaned_Data!$J$3:$J$273,Cleaned_Data!$F$3:$F$273, "CDR", Cleaned_Data!$J$3:$J$273, ">0") -> 51.5025 | H9: =AVERAGEIFS(Cleaned_Data!$J$3:$J$273,Cleaned_Data!$F$3:$F$273, "Industrial Decarbonization", Cleaned_Data!$J$3:$J$273, ">0") -> 26.962093 | I9: =AVERAGEIFS(Cleaned_Data!$J$3:$J$273,Cleaned_Data!$F$3:$F$273, "Buildings", Cleaned_Data!$J$3:$J$273, ">0") -> 12.103333 | J9: =AVERAGEIFS(Cleaned_Data!$J$3:$J$273,Cleaned_Data!$F$3:$F$273, "Mobility", Cleaned_Data!$J$3:$J$273, ">0") -> 81.479 | K9: =AVERAGEIFS(Cleaned_Data!$J$3:$J$273,Cleaned_Data!$F$3:$F$273, "Food & Ag", Cleaned_Data!$J$3:$J$273, ">0") -> 26.019459
B10: Maximum | C10: =_xlfn.MAXIFS(Cleaned_Data!$J$3:$J$273,Cleaned_Data!$J$3:$J$273, ">0") -> 1250 | D10: =_xlfn.MAXIFS(Cleaned_Data!$J$3:$J$273,Cleaned_Data!$F$3:$F$273, "Renewables", Cleaned_Data!$J$3:$J$273, ">0") -> 863 | E10: =_xlfn.MAXIFS(Cleaned_Data!$J$3:$J$273,Cleaned_Data!$F$3:$F$273, "LDES", Cleaned_Data!$J$3:$J$273, ">0") -> 120 | F10: =_xlfn.MAXIFS(Cleaned_Data!$J$3:$J$273,Cleaned_Data!$F$3:$F$273, "Hydrogen", Cleaned_Data!$J$3:$J$273, ">0") -> 650 | G10: =_xlfn.MAXIFS(Cleaned_Data!$J$3:$J$273,Cleaned_Data!$F$3:$F$273, "CDR", Cleaned_Data!$J$3:$J$273, ">0") -> 160 | H10: =_xlfn.MAXIFS(Cleaned_Data!$J$3:$J$273,Cleaned_Data!$F$3:$F$273, "Industrial Decarbonization", Cleaned_Data!$J$3:$J$273, ">0") -> 250 | I10: =_xlfn.MAXIFS(Cleaned_Data!$J$3:$J$273,Cleaned_Data!$F$3:$F$273, "Buildings", Cleaned_Data!$J$3:$J$273, ">0") -> 69.7 | J10: =_xlfn.MAXIFS(Cleaned_Data!$J$3:$J$273,Cleaned_Data!$F$3:$F$273, "Mobility", Cleaned_Data!$J$3:$J$273, ">0") -> 1250 | K10: =_xlfn.MAXIFS(Cleaned_Data!$J$3:$J$273,Cleaned_Data!$F$3:$F$273, "Food & Ag", Cleaned_Data!$J$3:$J$273, ">0") -> 300
B13: Deal Stage Analysis
C14: Overall | D14: Renewables | E14: LDES | F14: Hydrogen | G14: CDR | H14: Industrial Decarbonization | I14: Buildings | J14: Mobility | K14: Food&Ag
B15: Most Common Stage | C15: {=_xlfn.LET(_xlpm.stages, _xlfn._xlws.FILTER(Cleaned_Data!$H$3:$H$273, Cleaned_Data!$H$3:$H$273<>""),INDEX(_xlpm.stages,MODE(MATCH(_xlpm.stages, _xlpm.stages, 0))))} -> Series A | D15: {=_xlfn.LET(_xlpm.stages,_xlfn._xlws.FILTER(Cleaned_Data!$H$3:$H$273,(Cleaned_Data!$F$3:$F$273="Renewables")*(Cleaned_Data!$H$3:$H$273<>"")),INDEX(_xlpm.stages,MODE(MATCH(_xlpm.stages, _xlpm.stages, 0))))} -> Development capital | E15: {=_xlfn.LET(_xlpm.stages,_xlfn._xlws.FILTER(Cleaned_Data!$H$3:$H$273,(Cleaned_Data!$F$3:$F$273="LDES")*(Cleaned_Data!$H$3:$H$273<>"")),INDEX(_xlpm.stages,MODE(MATCH(_xlpm.stages, _xlpm.stages, 0))))} -> Series A | F15: {=_xlfn.LET(_xlpm.stages,_xlfn._xlws.FILTER(Cleaned_Data!$H$3:$H$273,(Cleaned_Data!$F$3:$F$273="Hydrogen")*(Cleaned_Data!$H$3:$H$273<>"")),INDEX(_xlpm.stages,MODE(MATCH(_xlpm.stages, _xlpm.stages, 0))))} -> Development capital | G15: {=_xlfn.LET(_xlpm.stages,_xlfn._xlws.FILTER(Cleaned_Data!$H$3:$H$273,(Cleaned_Data!$F$3:$F$273="CDR")*(Cleaned_Data!$H$3:$H$273<>"")),INDEX(_xlpm.stages,MODE(MATCH(_xlpm.stages, _xlpm.stages, 0))))} -> Development capital | H15: {=_xlfn.LET(_xlpm.stages,_xlfn._xlws.FILTER(Cleaned_Data!$H$3:$H$273,(Cleaned_Data!$F$3:$F$273="Industrial Decarbonization")*(Cleaned_Data!$H$3:$H$273<>"")),INDEX(_xlpm.stages,MODE(MATCH(_xlpm.stages, _xlpm.stages, 0))))} -> Series A | I15: {=_xlfn.LET(_xlpm.stages,_xlfn._xlws.FILTER(Cleaned_Data!$H$3:$H$273,(Cleaned_Data!$F$3:$F$273="Buildings")*(Cleaned_Data!$H$3:$H$273<>"")),INDEX(_xlpm.stages,MODE(MATCH(_xlpm.stages, _xlpm.stages, 0))))} -> Series A | J15: {=_xlfn.LET(_xlpm.stages,_xlfn._xlws.FILTER(Cleaned_Data!$H$3:$H$273,(Cleaned_Data!$F$3:$F$273="Mobility")*(Cleaned_Data!$H$3:$H$273<>"")),INDEX(_xlpm.stages,MODE(MATCH(_xlpm.stages, _xlpm.stages, 0))))} -> Development capital | K15: {=_xlfn.LET(_xlpm.stages,_xlfn._xlws.FILTER(Cleaned_Data!$H$3:$H$273,(Cleaned_Data!$F$3:$F$273="Food & Ag")*(Cleaned_Data!$H$3:$H$273<>"")),INDEX(_xlpm.stages,MODE(MATCH(_xlpm.stages, _xlpm.stages, 0))))} -> Series A
C17: Overall | D17: Seed | E17: Series A | F17: Series B | G17: Development Capital
B18: Total # of rounds | C18: =COUNTIF(Cleaned_Data!$H$3:$H$273, "<>") -> 254 | D18: =COUNTIF(Cleaned_Data!$H$3:$H$273, "Seed") -> 43 | E18: =COUNTIF(Cleaned_Data!$H$3:$H$273, "Series A") -> 81 | F18: =COUNTIF(Cleaned_Data!$H$3:$H$273, "Series B") -> 42 | G18: =COUNTIF(Cleaned_Data!$H$3:$H$273, "Development Capital") -> 80
B19: Median Size | C19: {=MEDIAN(_xlfn._xlws.FILTER(Cleaned_Data!$J$3:$J$273,Cleaned_Data!$J$3:$J$273>0))} -> 9.89 | D19: {=MEDIAN(_xlfn._xlws.FILTER(Cleaned_Data!$J$3:$J$273,(Cleaned_Data!$H$3:$H$273="Seed")*(Cleaned_Data!$J$3:$J$273>0)))} -> 1.805 | E19: {=MEDIAN(_xlfn._xlws.FILTER(Cleaned_Data!$J$3:$J$273,(Cleaned_Data!$H$3:$H$273="Series A")*(Cleaned_Data!$J$3:$J$273>0)))} -> 9.89 | F19: {=MEDIAN(_xlfn._xlws.FILTER(Cleaned_Data!$J$3:$J$273,(Cleaned_Data!$H$3:$H$273="Series B")*(Cleaned_Data!$J$3:$J$273>0)))} -> 18.345 | G19: {=MEDIAN(_xlfn._xlws.FILTER(Cleaned_Data!$J$3:$J$273,(Cleaned_Data!$H$3:$H$273="Development Capital")*(Cleaned_Data!$J$3:$J$273>0)))} -> 30
B22: Time Series Analysis
C23: 2015 | D23: =C23+1 -> 2016 | E23: =D23+1 -> 2017 | F23: =E23+1 -> 2018 | G23: =F23+1 -> 2019 | H23: =G23+1 -> 2020 | I23: =H23+1 -> 2021 | J23: =I23+1 -> 2022 | K23: =J23+1 -> 2023 | ... M23: =L23+1 -> 2025
B24: Total Capital Invested | C24: =SUMIFS( Cleaned_Data!$J$3:$J$273,Cleaned_Data!$G$3:$G$273, ">="&DATE(C$23,1,1), Cleaned_Data!$G$3:$G$273, "<"&DATE(C$23+1,1,1), Cleaned_Data!$J$3:$J$273, ">0") -> 370.54 | D24: =SUMIFS( Cleaned_Data!$J$3:$J$273,Cleaned_Data!$G$3:$G$273, ">="&DATE(D$23,1,1), Cleaned_Data!$G$3:$G$273, "<"&DATE(D$23+1,1,1), Cleaned_Data!$J$3:$J$273, ">0") -> 295.5 | E24: =SUMIFS( Cleaned_Data!$J$3:$J$273,Cleaned_Data!$G$3:$G$273, ">="&DATE(E$23,1,1), Cleaned_Data!$G$3:$G$273, "<"&DATE(E$23+1,1,1), Cleaned_Data!$J$3:$J$273, ">0") -> 44.32 | F24: =SUMIFS( Cleaned_Data!$J$3:$J$273,Cleaned_Data!$G$3:$G$273, ">="&DATE(F$23,1,1), Cleaned_Data!$G$3:$G$273, "<"&DATE(F$23+1,1,1), Cleaned_Data!$J$3:$J$273, ">0") -> 103.31 | G24: =SUMIFS( Cleaned_Data!$J$3:$J$273,Cleaned_Data!$G$3:$G$273, ">="&DATE(G$23,1,1), Cleaned_Data!$G$3:$G$273, "<"&DATE(G$23+1,1,1), Cleaned_Data!$J$3:$J$273, ">0") -> 1631.59 | H24: =SUMIFS( Cleaned_Data!$J$3:$J$273,Cleaned_Data!$G$3:$G$273, ">="&DATE(H$23,1,1), Cleaned_Data!$G$3:$G$273, "<"&DATE(H$23+1,1,1), Cleaned_Data!$J$3:$J$273, ">0") -> 1007.94 | I24: =SUMIFS( Cleaned_Data!$J$3:$J$273,Cleaned_Data!$G$3:$G$273, ">="&DATE(I$23,1,1), Cleaned_Data!$G$3:$G$273, "<"&DATE(I$23+1,1,1), Cleaned_Data!$J$3:$J$273, ">0") -> 475.25 | J24: =SUMIFS( Cleaned_Data!$J$3:$J$273,Cleaned_Data!$G$3:$G$273, ">="&DATE(J$23,1,1), Cleaned_Data!$G$3:$G$273, "<"&DATE(J$23+1,1,1), Cleaned_Data!$J$3:$J$273, ">0") -> 2796.84 | ... M24: =SUMIFS( Cleaned_Data!$J$3:$J$273,Cleaned_Data!$G$3:$G$273, ">="&DATE(M$23,1,1), Cleaned_Data!$G$3:$G$273, "<"&DATE(M$23+1,1,1), Cleaned_Data!$J$3:$J$273, ">0") -> 1905.92
B25: Deal Count | C25: =COUNTIFS(Cleaned_Data!$G$3:$G$273, ">=1/1/2015", Cleaned_Data!$G$3:$G$273, "<1/1/2016") -> 5 | D25: =COUNTIFS(Cleaned_Data!$G$3:$G$273, ">=1/1/2016", Cleaned_Data!$G$3:$G$273, "<1/1/2017") -> 10 | E25: =COUNTIFS(Cleaned_Data!$G$3:$G$273, ">=1/1/2017", Cleaned_Data!$G$3:$G$273, "<1/1/2018") -> 9 | F25: =COUNTIFS(Cleaned_Data!$G$3:$G$273, ">=1/1/2018", Cleaned_Data!$G$3:$G$273, "<1/1/2019") -> 13 | G25: =COUNTIFS(Cleaned_Data!$G$3:$G$273, ">=1/1/2019", Cleaned_Data!$G$3:$G$273, "<1/1/2020") -> 16 | H25: =COUNTIFS(Cleaned_Data!$G$3:$G$273, ">=1/1/2020", Cleaned_Data!$G$3:$G$273, "<1/1/2021") -> 22 | I25: =COUNTIFS(Cleaned_Data!$G$3:$G$273, ">=1/1/2021", Cleaned_Data!$G$3:$G$273, "<1/1/2022") -> 47 | J25: =COUNTIFS(Cleaned_Data!$G$3:$G$273, ">=1/1/2022", Cleaned_Data!$G$3:$G$273, "<1/1/2023") -> 45 | K25: =COUNTIFS(Cleaned_Data!$G$3:$G$273, ">=1/1/2023", Cleaned_Data!$G$3:$G$273, "<1/1/2024") -> 39 | L25: =COUNTIFS(Cleaned_Data!$G$3:$G$273, ">=1/1/2024", Cleaned_Data!$G$3:$G$273, "<1/1/2025") -> 35 | M25: =COUNTIFS(Cleaned_Data!$G$3:$G$273, ">=1/1/2025", Cleaned_Data!$G$3:$G$273, "<1/1/2026") -> 29
B26: Median Deal Size | C26: {=MEDIAN( _xlfn._xlws.FILTER( Cleaned_Data!$J$3:$J$273, (Cleaned_Data!$G$3:$G$273>=DATE(2015,1,1))* (Cleaned_Data!$G$3:$G$273<DATE(2016,1,1))* (Cleaned_Data!$J$3:$J$273>0)))} -> 11 | D26: {=MEDIAN( _xlfn._xlws.FILTER( Cleaned_Data!$J$3:$J$273, (Cleaned_Data!$G$3:$G$273>=DATE(2016,1,1))* (Cleaned_Data!$G$3:$G$273<DATE(2017,1,1))* (Cleaned_Data!$J$3:$J$273>0)))} -> 4.92 | E26: {=MEDIAN( _xlfn._xlws.FILTER( Cleaned_Data!$J$3:$J$273, (Cleaned_Data!$G$3:$G$273>=DATE(2017,1,1))* (Cleaned_Data!$G$3:$G$273<DATE(2018,1,1))* (Cleaned_Data!$J$3:$J$273>0)))} -> 3.92 | F26: {=MEDIAN( _xlfn._xlws.FILTER( Cleaned_Data!$J$3:$J$273, (Cleaned_Data!$G$3:$G$273>=DATE(2018,1,1))* (Cleaned_Data!$G$3:$G$273<DATE(2019,1,1))* (Cleaned_Data!$J$3:$J$273>0)))} -> 5.25 | G26: {=MEDIAN( _xlfn._xlws.FILTER( Cleaned_Data!$J$3:$J$273, (Cleaned_Data!$G$3:$G$273>=DATE(2019,1,1))* (Cleaned_Data!$G$3:$G$273<DATE(2020,1,1))* (Cleaned_Data!$J$3:$J$273>0)))} -> 6.51 | H26: {=MEDIAN( _xlfn._xlws.FILTER( Cleaned_Data!$J$3:$J$273, (Cleaned_Data!$G$3:$G$273>=DATE(2020,1,1))* (Cleaned_Data!$G$3:$G$273<DATE(2021,1,1))* (Cleaned_Data!$J$3:$J$273>0)))} -> 12 | I26: {=MEDIAN( _xlfn._xlws.FILTER( Cleaned_Data!$J$3:$J$273, (Cleaned_Data!$G$3:$G$273>=DATE(2021,1,1))* (Cleaned_Data!$G$3:$G$273<DATE(2022,1,1))* (Cleaned_Data!$J$3:$J$273>0)))} -> 7 | J26: {=MEDIAN( _xlfn._xlws.FILTER( Cleaned_Data!$J$3:$J$273, (Cleaned_Data!$G$3:$G$273>=DATE(2022,1,1))* (Cleaned_Data!$G$3:$G$273<DATE(2023,1,1))* (Cleaned_Data!$J$3:$J$273>0)))} -> 5.125 | K26: {=MEDIAN( _xlfn._xlws.FILTER( Cleaned_Data!$J$3:$J$273, (Cleaned_Data!$G$3:$G$273>=DATE(2023,1,1))* (Cleaned_Data!$G$3:$G$273<DATE(2024,1,1))* (Cleaned_Data!$J$3:$J$273>0)))} -> 12 | L26: {=MEDIAN( _xlfn._xlws.FILTER( Cleaned_Data!$J$3:$J$273, (Cleaned_Data!$G$3:$G$273>=DATE(2024,1,1))* (Cleaned_Data!$G$3:$G$273<DATE(2025,1,1))* (Cleaned_Data!$J$3:$J$273>0)))} -> 15 | M26: {=MEDIAN( _xlfn._xlws.FILTER( Cleaned_Data!$J$3:$J$273, (Cleaned_Data!$G$3:$G$273>=DATE(2025,1,1))* (Cleaned_Data!$G$3:$G$273<DATE(2026,1,1))* (Cleaned_Data!$J$3:$J$273>0)))} -> 25.13
B27: Median Valuation | C27: {=MEDIAN(_xlfn._xlws.FILTER(Cleaned_Data!$K$3:$K$273, (Cleaned_Data!$G$3:$G$273>=DATE(2015,1,1))* (Cleaned_Data!$G$3:$G$273<DATE(2016,1,1))* (Cleaned_Data!$K$3:$K$273>0)))} -> 35.605 | D27: {=MEDIAN( _xlfn._xlws.FILTER( Cleaned_Data!$K$3:$K$273, (Cleaned_Data!$G$3:$G$273>=DATE(2016,1,1))* (Cleaned_Data!$G$3:$G$273<DATE(2017,1,1))* (Cleaned_Data!$K$3:$K$273>0)))} -> 19.45 | E27: {=MEDIAN( _xlfn._xlws.FILTER( Cleaned_Data!$K$3:$K$273, (Cleaned_Data!$G$3:$G$273>=DATE(2017,1,1))* (Cleaned_Data!$G$3:$G$273<DATE(2018,1,1))* (Cleaned_Data!$K$3:$K$273>0)))} -> 19 | F27: {=MEDIAN( _xlfn._xlws.FILTER( Cleaned_Data!$K$3:$K$273, (Cleaned_Data!$G$3:$G$273>=DATE(2018,1,1))* (Cleaned_Data!$G$3:$G$273<DATE(2019,1,1))* (Cleaned_Data!$K$3:$K$273>0)))} -> 30 | G27: {=MEDIAN( _xlfn._xlws.FILTER( Cleaned_Data!$K$3:$K$273, (Cleaned_Data!$G$3:$G$273>=DATE(2019,1,1))* (Cleaned_Data!$G$3:$G$273<DATE(2020,1,1))* (Cleaned_Data!$K$3:$K$273>0)))} -> 21.5 | H27: {=MEDIAN( _xlfn._xlws.FILTER( Cleaned_Data!$K$3:$K$273, (Cleaned_Data!$G$3:$G$273>=DATE(2020,1,1))* (Cleaned_Data!$G$3:$G$273<DATE(2021,1,1))* (Cleaned_Data!$K$3:$K$273>0)))} -> 35.065 | I27: {=MEDIAN( _xlfn._xlws.FILTER( Cleaned_Data!$K$3:$K$273, (Cleaned_Data!$G$3:$G$273>=DATE(2021,1,1))* (Cleaned_Data!$G$3:$G$273<DATE(2022,1,1))* (Cleaned_Data!$K$3:$K$273>0)))} -> 20.95 | J27: {=MEDIAN( _xlfn._xlws.FILTER( Cleaned_Data!$K$3:$K$273, (Cleaned_Data!$G$3:$G$273>=DATE(2022,1,1))* (Cleaned_Data!$G$3:$G$273<DATE(2023,1,1))* (Cleaned_Data!$K$3:$K$273>0)))} -> 38.325 | K27: {=MEDIAN( _xlfn._xlws.FILTER( Cleaned_Data!$K$3:$K$273, (Cleaned_Data!$G$3:$G$273>=DATE(2023,1,1))* (Cleaned_Data!$G$3:$G$273<DATE(2024,1,1))* (Cleaned_Data!$K$3:$K$273>0)))} -> 83 | L27: {=MEDIAN( _xlfn._xlws.FILTER( Cleaned_Data!$K$3:$K$273, (Cleaned_Data!$G$3:$G$273>=DATE(2024,1,1))* (Cleaned_Data!$G$3:$G$273<DATE(2025,1,1))* (Cleaned_Data!$K$3:$K$273>0)))} -> 70.6 | M27: {=MEDIAN( _xlfn._xlws.FILTER( Cleaned_Data!$K$3:$K$273, (Cleaned_Data!$G$3:$G$273>=DATE(2025,1,1))* (Cleaned_Data!$G$3:$G$273<DATE(2026,1,1))* (Cleaned_Data!$K$3:$K$273>0)))} -> 200
B28: Deal Stage | C28: {=_xlfn.LET( _xlpm.stages, _xlfn._xlws.FILTER( Cleaned_Data!$H$3:$H$273, (Cleaned_Data!$G$3:$G$273>=DATE(2015,1,1))* (Cleaned_Data!$G$3:$G$273<DATE(2016,1,1))* (Cleaned_Data!$H$3:$H$273<>"")), INDEX( _xlpm.stages, MODE( MATCH(_xlpm.stages, _xlpm.stages, 0))))} -> Development capital | D28: {=_xlfn.LET( _xlpm.stages, _xlfn._xlws.FILTER( Cleaned_Data!$H$3:$H$273, (Cleaned_Data!$G$3:$G$273>=DATE(2016,1,1))* (Cleaned_Data!$G$3:$G$273<DATE(2017,1,1))* (Cleaned_Data!$H$3:$H$273<>"")), INDEX( _xlpm.stages, MODE( MATCH(_xlpm.stages, _xlpm.stages, 0))))} -> Series A | E28: {=_xlfn.LET( _xlpm.stages, _xlfn._xlws.FILTER( Cleaned_Data!$H$3:$H$273, (Cleaned_Data!$G$3:$G$273>=DATE(2017,1,1))* (Cleaned_Data!$G$3:$G$273<DATE(2018,1,1))* (Cleaned_Data!$H$3:$H$273<>"")), INDEX( _xlpm.stages, MODE( MATCH(_xlpm.stages, _xlpm.stages, 0))))} -> Series A | F28: {=_xlfn.LET( _xlpm.stages, _xlfn._xlws.FILTER( Cleaned_Data!$H$3:$H$273, (Cleaned_Data!$G$3:$G$273>=DATE(2018,1,1))* (Cleaned_Data!$G$3:$G$273<DATE(2019,1,1))* (Cleaned_Data!$H$3:$H$273<>"")), INDEX( _xlpm.stages, MODE( MATCH(_xlpm.stages, _xlpm.stages, 0))))} -> Series A | G28: {=_xlfn.LET( _xlpm.stages, _xlfn._xlws.FILTER( Cleaned_Data!$H$3:$H$273, (Cleaned_Data!$G$3:$G$273>=DATE(2019,1,1))* (Cleaned_Data!$G$3:$G$273<DATE(2020,1,1))* (Cleaned_Data!$H$3:$H$273<>"")), INDEX( _xlpm.stages, MODE( MATCH(_xlpm.stages, _xlpm.stages, 0))))} -> Series A | H28: {=_xlfn.LET( _xlpm.stages, _xlfn._xlws.FILTER( Cleaned_Data!$H$3:$H$273, (Cleaned_Data!$G$3:$G$273>=DATE(2020,1,1))* (Cleaned_Data!$G$3:$G$273<DATE(2021,1,1))* (Cleaned_Data!$H$3:$H$273<>"")), INDEX( _xlpm.stages, MODE( MATCH(_xlpm.stages, _xlpm.stages, 0))))} -> Series A | I28: {=_xlfn.LET( _xlpm.stages, _xlfn._xlws.FILTER( Cleaned_Data!$H$3:$H$273, (Cleaned_Data!$G$3:$G$273>=DATE(2021,1,1))* (Cleaned_Data!$G$3:$G$273<DATE(2022,1,1))* (Cleaned_Data!$H$3:$H$273<>"")), INDEX( _xlpm.stages, MODE( MATCH(_xlpm.stages, _xlpm.stages, 0))))} -> Development capital | J28: {=_xlfn.LET( _xlpm.stages, _xlfn._xlws.FILTER( Cleaned_Data!$H$3:$H$273, (Cleaned_Data!$G$3:$G$273>=DATE(2022,1,1))* (Cleaned_Data!$G$3:$G$273<DATE(2023,1,1))* (Cleaned_Data!$H$3:$H$273<>"")), INDEX( _xlpm.stages, MODE( MATCH(_xlpm.stages, _xlpm.stages, 0))))} -> Seed | K28: {=_xlfn.LET( _xlpm.stages, _xlfn._xlws.FILTER( Cleaned_Data!$H$3:$H$273, (Cleaned_Data!$G$3:$G$273>=DATE(2023,1,1))* (Cleaned_Data!$G$3:$G$273<DATE(2024,1,1))* (Cleaned_Data!$H$3:$H$273<>"")), INDEX( _xlpm.stages, MODE( MATCH(_xlpm.stages, _xlpm.stages, 0))))} -> Development capital | L28: {=_xlfn.LET( _xlpm.stages, _xlfn._xlws.FILTER( Cleaned_Data!$H$3:$H$273, (Cleaned_Data!$G$3:$G$273>=DATE(2024,1,1))* (Cleaned_Data!$G$3:$G$273<DATE(2025,1,1))* (Cleaned_Data!$H$3:$H$273<>"")), INDEX( _xlpm.stages, MODE( MATCH(_xlpm.stages, _xlpm.stages, 0))))} -> Development capital | M28: {=_xlfn.LET( _xlpm.stages, _xlfn._xlws.FILTER( Cleaned_Data!$H$3:$H$273, (Cleaned_Data!$G$3:$G$273>=DATE(2025,1,1))* (Cleaned_Data!$G$3:$G$273<DATE(2026,1,1))* (Cleaned_Data!$H$3:$H$273<>"")), INDEX( _xlpm.stages, MODE( MATCH(_xlpm.stages, _xlpm.stages, 0))))} -> Development capital
B31: Investor Profile Analysis
C32: Overall | D32: Renewables | E32: LDES | F32: Hydrogen | G32: CDR | H32: Industrial Decarbonization | I32: Buildings | J32: Mobility | K32: Food&Ag
B33: Avg Existing Investor Participation (%) | C33: =AVERAGEIFS(Cleaned_Data!$P$3:$P$273,Cleaned_Data!$P$3:$P$273,"<>N/A") -> 0.18731044 | D33: =AVERAGEIFS( Cleaned_Data!$P$3:$P$273,Cleaned_Data!$F$3:$F$273, "Renewables", Cleaned_Data!$P$3:$P$273, "<>N/A") -> 0.11521851 | E33: =AVERAGEIFS( Cleaned_Data!$P$3:$P$273,Cleaned_Data!$F$3:$F$273, "LDES", Cleaned_Data!$P$3:$P$273, "<>N/A") -> 0.22132654 | F33: =AVERAGEIFS( Cleaned_Data!$P$3:$P$273,Cleaned_Data!$F$3:$F$273, "Hydrogen", Cleaned_Data!$P$3:$P$273, "<>N/A") -> 0.16882932 | G33: =AVERAGEIFS( Cleaned_Data!$P$3:$P$273,Cleaned_Data!$F$3:$F$273, "CDR", Cleaned_Data!$P$3:$P$273, "<>N/A") -> 0.20804196 | H33: =AVERAGEIFS( Cleaned_Data!$P$3:$P$273,Cleaned_Data!$F$3:$F$273, "Industrial Decarbonization", Cleaned_Data!$P$3:$P$273, "<>N/A") -> 0.20154326 | I33: =AVERAGEIFS( Cleaned_Data!$P$3:$P$273,Cleaned_Data!$F$3:$F$273, "Buildings", Cleaned_Data!$P$3:$P$273, "<>N/A") -> 0.31555556 | J33: =AVERAGEIFS( Cleaned_Data!$P$3:$P$273,Cleaned_Data!$F$3:$F$273, "Mobility", Cleaned_Data!$P$3:$P$273, "<>N/A") -> 0.10839002 | K33: =AVERAGEIFS( Cleaned_Data!$P$3:$P$273,Cleaned_Data!$F$3:$F$273, "Food & Ag", Cleaned_Data!$P$3:$P$273, "<>N/A") -> 0.24931125
B34: Avg New Investor Participation (%) | C34: =AVERAGEIFS(Cleaned_Data!$R$3:$R$273,Cleaned_Data!$R$3:$R$273,"<>N/A") -> 0.87860528 | D34: =AVERAGEIFS( Cleaned_Data!$R$3:$R$273,Cleaned_Data!$F$3:$F$273, "Renewables", Cleaned_Data!$R$3:$R$273, "<>N/A") -> 0.92494998 | E34: =AVERAGEIFS( Cleaned_Data!$R$3:$R$273,Cleaned_Data!$F$3:$F$273, "LDES", Cleaned_Data!$R$3:$R$273, "<>N/A") -> 0.90662879 | F34: =AVERAGEIFS( Cleaned_Data!$R$3:$R$273,Cleaned_Data!$F$3:$F$273, "Hydrogen", Cleaned_Data!$R$3:$R$273, "<>N/A") -> 0.87441751 | G34: =AVERAGEIFS( Cleaned_Data!$R$3:$R$273,Cleaned_Data!$F$3:$F$273, "CDR", Cleaned_Data!$R$3:$R$273, "<>N/A") -> 0.87941919 | H34: =AVERAGEIFS( Cleaned_Data!$R$3:$R$273,Cleaned_Data!$F$3:$F$273, "Industrial Decarbonization", Cleaned_Data!$R$3:$R$273, "<>N/A") -> 0.87292078 | I34: =AVERAGEIFS( Cleaned_Data!$R$3:$R$273,Cleaned_Data!$F$3:$F$273, "Buildings", Cleaned_Data!$R$3:$R$273, "<>N/A") -> 0.78974359 | J34: =AVERAGEIFS( Cleaned_Data!$R$3:$R$273,Cleaned_Data!$F$3:$F$273, "Mobility", Cleaned_Data!$R$3:$R$273, "<>N/A") -> 0.89160998 | K34: =AVERAGEIFS( Cleaned_Data!$R$3:$R$273,Cleaned_Data!$F$3:$F$273, "Food & Ag", Cleaned_Data!$R$3:$R$273, "<>N/A") -> 0.82865129
B37: # Unique Investors | C37: =COUNTA(_xlfn.UNIQUE(Investor_Analysis_Setup!E4:E1128)) -> 884
B38: Share of deals with existing investor participation | C38: =COUNTIF(Cleaned_Data!$O$3:$O$273, "Y")/COUNTIF(Cleaned_Data!$O$3:$O$273, "<>") -> 0.49077491
B39: Share of deals with new strategic investors | C39: =COUNTIF(Cleaned_Data!S3:S273,"Y")/COUNTIF(Cleaned_Data!S3:S273,"<>") -> 0.11439114
B40: Share of deals with 100% new investors | C40: =COUNTIFS(Cleaned_Data!$R$3:$R$273,"100.0%")/COUNTIF(Cleaned_Data!$R$3:$R$273,"<>") -> 0.52398524
B43: Most commonly participating investors
C44: Breakthrough Energy | D44: Temasek Holdings | E44: SOSV | F44: Collaborative Fund | G44: Safar Partners | H44: Loweracarbon Capital | I44: Climate Capital | J44: Khosla Ventures
B45: Number of Deals | C45: 10 | D45: 9 | E45: 8 | F45: 8 | G45: 7 | H45: 7 | I45: 7 | J45: 6
B47: Most commonly *new* participating investors
C48: Temasek Holdings | D48: Climate Capital | E48: Lowercarbon Capital | F48: Collaborative Fund | G48: E8
B49: Number of Deals | C49: 8 | D49: 7 | E49: 6 | F49: 6 | G49: 5
B52: Other Deal Analysis
B54: Largest deals
B55: Company | C55: Deal Size | D55: Deal Date
B56: {=_xlfn.TAKE(_xlfn._xlws.SORT(_xlfn._xlws.FILTER(CHOOSE({1,2,3},Cleaned_Data!$C$3:$C$273,Cleaned_Data!$J$3:$J$273,Cleaned_Data!$G$3:$G$273),Cleaned_Data!$J$3:$J$273>0),2,-1),5)} -> Faraday Future Intelligent Electric (NAS: FFAI) | C56: 1250 | D56: 43584
B57: Commonwealth Fusion Systems | C57: 863 | D57: 45834
B58: Terrapower | C58: 830 | D58: 44868
B59: Aces Delta | C59: 650 | D59: 44721
B60: California Bioenergy | C60: 500 | D60: 44917
B62: Debt reporting
B63: # of deals that reported debt raise | C63: =COUNTIFS(Cleaned_Data!L3:L273, ">0") -> 21
B64: % of deals that reported debt raise | C64: =COUNTIFS(Cleaned_Data!$L$3:$L$273, ">0")/COUNTIF(Cleaned_Data!$L$3:$L$273, "<>") -> 0.077490775
B65: Median debt share | C65: {=MEDIAN( _xlfn._xlws.FILTER( Cleaned_Data!$L$3:$L$273, Cleaned_Data!$L$3:$L$273>0))} -> 0.485
B66: Average debt share | C66: =AVERAGE(Cleaned_Data!$L$3:$L$273) -> 0.052140642

Sheet Charts
B2: CHARTS

Sheet Cleaned_Data
B2: Deal_ID | C2: Company_Name | D2: State | E2: Year Founded | F2: Sector | G2: Date | H2: Deal Stage | I2: Total Capital Raised to date | J2: Deal_Size | K2: Valuation | L2: % Debt | M2: Investors | N2: # Investors in Round | O2: Existing Investor Participation | P2: Existing Investor % | Q2: New Investor Participation | R2: New Investor % | S2: New Strategic Investor (Y/N) | T2: Philanthropic Capital (Y/N) | U2: Investor Mix
B3: 1 | C3: =IFERROR(_xlfn.XLOOKUP($B3,Raw_Data!$A$3:$A$273,Raw_Data!$B$3:$B$273),"") -> 247Solar | D3: =IFERROR(_xlfn.XLOOKUP($B3,Raw_Data!$A$3:$A$273,Raw_Data!$C$3:$C$273),"") -> Great Falls, VA | E3: =IFERROR(_xlfn.XLOOKUP($B3,Raw_Data!$A$3:$A$273,Raw_Data!$D$3:$D$273),"") -> 2015 | F3: =IFERROR(_xlfn.XLOOKUP($B3,Raw_Data!$A$3:$A$273,Raw_Data!$F$3:$F$273),"") -> Renewables | G3: =IFERROR(_xlfn.XLOOKUP($B3,Raw_Data!$A$3:$A$273,Raw_Data!$J$3:$J$273),"") -> 44895 | H3: Series A | I3: =IFERROR(_xlfn.XLOOKUP($B3,Raw_Data!$A$3:$A$273,Raw_Data!$I$3:$I$273),"") -> 12.5 | J3: =IFERROR(_xlfn.XLOOKUP($B3,Raw_Data!$A$3:$A$273,Raw_Data!$L$3:$L$273),"") -> 3.5 | K3: =IFERROR(_xlfn.XLOOKUP($B3,Raw_Data!$A$3:$A$273,Raw_Data!$M$3:$M$273),"") -> 40 | L3: =IFERROR(_xlfn.XLOOKUP($B3,Raw_Data!$A$3:$A$273,Raw_Data!$Q$3:$Q$273),"") -> 0 | M3: =IFERROR(_xlfn.XLOOKUP($B3,Raw_Data!$A$3:$A$273,Raw_Data!$R$3:$R$273),"") -> Safar Partners | N3: {=IF(M3="",0,COUNTA(_xlfn._xlws.FILTER(_xlfn.TEXTSPLIT(M3,";"), _xlfn.TEXTSPLIT(M3,";")<>"")))} -> 1 | O3: =IF(P3>0,"Y","N") -> N | P3: =IFERROR(_xlfn.XLOOKUP($B3,Raw_Data!$A$3:$A$273,Raw_Data!$V$3:$V$273),"") -> 0 | Q3: =IF(R3>0,"Y","N") -> Y | R3: =IFERROR(_xlfn.XLOOKUP($B3,Raw_Data!$A$3:$A$273,Raw_Data!$Y$3:$Y$273),"") -> 1 | S3: {=_xlfn.LET(_xlpm.s, Raw_Data!W3,_xlpm.strat, _xlfn._xlws.FILTER(REF_Setup!$B$3:$B$40, REF_Setup!$B$3:$B$40<>""),IF(OR(_xlpm.s="",_xlpm.s=0),"Unclassified",IF(SUM(--ISNUMBER(SEARCH(_xlpm.strat, _xlpm.s)))>0, "Y", "N")) )} -> N | T3: {=_xlfn.LET(_xlpm.s,M3,_xlpm.phil, _xlfn._xlws.FILTER(REF_Setup!$D$3:$D$5, REF_Setup!$D$3:$D$5<>""),IF(OR(_xlpm.s="", _xlpm.s=0),"Unclassified",IF(SUM(--ISNUMBER(SEARCH(_xlpm.phil, _xlpm.s)))>0, "Y", "N")))} -> N | U3: {=IF(M3="", "Unclassified", IF(AND(SUMPRODUCT(--ISNUMBER(SEARCH(REF_Setup!$B$3:$B$40,M3)))>0,SUMPRODUCT(--ISNUMBER(SEARCH(REF_Setup!$F$3:$F$15,M3)))>0),"Mixed",IF(SUMPRODUCT(--ISNUMBER(SEARCH(REF_Setup!$B$3:$B$40,M3)))>0,"Strategic Only",IF(SUMPRODUCT(--ISNUMBER(SEARCH(REF_Setup!$F$3:$F$15,M3)))>0,"VC Only","Unclassified"))))} -> VC Only
B4: =B3+1 -> 2 | C4: =IFERROR(_xlfn.XLOOKUP($B4,Raw_Data!$A$3:$A$273,Raw_Data!$B$3:$B$273),"") -> 247Solar | D4: =IFERROR(_xlfn.XLOOKUP($B4,Raw_Data!$A$3:$A$273,Raw_Data!$C$3:$C$273),"") -> Great Falls, VA | E4: =IFERROR(_xlfn.XLOOKUP($B4,Raw_Data!$A$3:$A$273,Raw_Data!$D$3:$D$273),"") -> 2015 | F4: =IFERROR(_xlfn.XLOOKUP($B4,Raw_Data!$A$3:$A$273,Raw_Data!$F$3:$F$273),"") -> Renewables | G4: =IFERROR(_xlfn.XLOOKUP($B4,Raw_Data!$A$3:$A$273,Raw_Data!$J$3:$J$273),"") -> 45657 | H4: Series A | I4: =IFERROR(_xlfn.XLOOKUP($B4,Raw_Data!$A$3:$A$273,Raw_Data!$I$3:$I$273),"") -> 20.5 | J4: =IFERROR(_xlfn.XLOOKUP($B4,Raw_Data!$A$3:$A$273,Raw_Data!$L$3:$L$273),"") -> 8 | K4: =IFERROR(_xlfn.XLOOKUP($B4,Raw_Data!$A$3:$A$273,Raw_Data!$M$3:$M$273),"") -> 0 | L4: =IFERROR(_xlfn.XLOOKUP($B4,Raw_Data!$A$3:$A$273,Raw_Data!$Q$3:$Q$273),"") -> 0 | M4: =IFERROR(_xlfn.XLOOKUP($B4,Raw_Data!$A$3:$A$273,Raw_Data!$R$3:$R$273),"") -> COCONUT GROVE; First Financial Bankshares; M10Lean capital; Mintz | N4: {=IF(M4="",0,COUNTA(_xlfn._xlws.FILTER(_xlfn.TEXTSPLIT(M4,";"), _xlfn.TEXTSPLIT(M4,";")<>"")))} -> 4 | O4: =IF(P4>0,"Y","N") -> N | P4: =IFERROR(_xlfn.XLOOKUP($B4,Raw_Data!$A$3:$A$273,Raw_Data!$V$3:$V$273),"") -> 0 | Q4: =IF(R4>0,"Y","N") -> Y | R4: =IFERROR(_xlfn.XLOOKUP($B4,Raw_Data!$A$3:$A$273,Raw_Data!$Y$3:$Y$273),"") -> 1 | S4: {=_xlfn.LET(_xlpm.s, Raw_Data!W4,_xlpm.strat, _xlfn._xlws.FILTER(REF_Setup!$B$3:$B$40, REF_Setup!$B$3:$B$40<>""),IF(OR(_xlpm.s="",_xlpm.s=0),"Unclassified",IF(SUM(--ISNUMBER(SEARCH(_xlpm.strat, _xlpm.s)))>0, "Y", "N")) )} -> N | T4: {=_xlfn.LET(_xlpm.s,M4,_xlpm.phil, _xlfn._xlws.FILTER(REF_Setup!$D$3:$D$5, REF_Setup!$D$3:$D$5<>""),IF(OR(_xlpm.s="", _xlpm.s=0),"Unclassified",IF(SUM(--ISNUMBER(SEARCH(_xlpm.phil, _xlpm.s)))>0, "Y", "N")))} -> N | U4: {=IF(M4="", "Unclassified", IF(AND(SUMPRODUCT(--ISNUMBER(SEARCH(REF_Setup!$B$3:$B$40,M4)))>0,SUMPRODUCT(--ISNUMBER(SEARCH(REF_Setup!$F$3:$F$15,M4)))>0),"Mixed",IF(SUMPRODUCT(--ISNUMBER(SEARCH(REF_Setup!$B$3:$B$40,M4)))>0,"Strategic Only",IF(SUMPRODUCT(--ISNUMBER(SEARCH(REF_Setup!$F$3:$F$15,M4)))>0,"VC Only","Unclassified"))))} -> VC Only
B5: =B4+1 -> 3 | C5: =IFERROR(_xlfn.XLOOKUP($B5,Raw_Data!$A$3:$A$273,Raw_Data!$B$3:$B$273),"") -> Aanika | D5: =IFERROR(_xlfn.XLOOKUP($B5,Raw_Data!$A$3:$A$273,Raw_Data!$C$3:$C$273),"") -> New York, NY | E5: =IFERROR(_xlfn.XLOOKUP($B5,Raw_Data!$A$3:$A$273,Raw_Data!$D$3:$D$273),"") -> 2018 | F5: =IFERROR(_xlfn.XLOOKUP($B5,Raw_Data!$A$3:$A$273,Raw_Data!$F$3:$F$273),"") -> Food & Ag | G5: =IFERROR(_xlfn.XLOOKUP($B5,Raw_Data!$A$3:$A$273,Raw_Data!$J$3:$J$273),"") -> 43879 | H5: Seed | I5: =IFERROR(_xlfn.XLOOKUP($B5,Raw_Data!$A$3:$A$273,Raw_Data!$I$3:$I$273),"") -> 2.63 | J5: =IFERROR(_xlfn.XLOOKUP($B5,Raw_Data!$A$3:$A$273,Raw_Data!$L$3:$L$273),"") -> 2.5 | K5: =IFERROR(_xlfn.XLOOKUP($B5,Raw_Data!$A$3:$A$273,Raw_Data!$M$3:$M$273),"") -> 7.93 | L5: =IFERROR(_xlfn.XLOOKUP($B5,Raw_Data!$A$3:$A$273,Raw_Data!$Q$3:$Q$273),"") -> 0.028 | M5: =IFERROR(_xlfn.XLOOKUP($B5,Raw_Data!$A$3:$A$273,Raw_Data!$R$3:$R$273),"") -> Alex Chung; Draper Associates; Kabir Misra; RPS Ventures; SOSV | N5: {=IF(M5="",0,COUNTA(_xlfn._xlws.FILTER(_xlfn.TEXTSPLIT(M5,";"), _xlfn.TEXTSPLIT(M5,";")<>"")))} -> 5 | O5: =IF(P5>0,"Y","N") -> N | P5: =IFERROR(_xlfn.XLOOKUP($B5,Raw_Data!$A$3:$A$273,Raw_Data!$V$3:$V$273),"") -> 0 | Q5: =IF(R5>0,"Y","N") -> Y | R5: =IFERROR(_xlfn.XLOOKUP($B5,Raw_Data!$A$3:$A$273,Raw_Data!$Y$3:$Y$273),"") -> 1 | S5: {=_xlfn.LET(_xlpm.s, Raw_Data!W5,_xlpm.strat, _xlfn._xlws.FILTER(REF_Setup!$B$3:$B$40, REF_Setup!$B$3:$B$40<>""),IF(OR(_xlpm.s="",_xlpm.s=0),"Unclassified",IF(SUM(--ISNUMBER(SEARCH(_xlpm.strat, _xlpm.s)))>0, "Y", "N")) )} -> N | T5: {=_xlfn.LET(_xlpm.s,M5,_xlpm.phil, _xlfn._xlws.FILTER(REF_Setup!$D$3:$D$5, REF_Setup!$D$3:$D$5<>""),IF(OR(_xlpm.s="", _xlpm.s=0),"Unclassified",IF(SUM(--ISNUMBER(SEARCH(_xlpm.phil, _xlpm.s)))>0, "Y", "N")))} -> N | U5: {=IF(M5="", "Unclassified", IF(AND(SUMPRODUCT(--ISNUMBER(SEARCH(REF_Setup!$B$3:$B$40,M5)))>0,SUMPRODUCT(--ISNUMBER(SEARCH(REF_Setup!$F$3:$F$15,M5)))>0),"Mixed",IF(SUMPRODUCT(--ISNUMBER(SEARCH(REF_Setup!$B$3:$B$40,M5)))>0,"Strategic Only",IF(SUMPRODUCT(--ISNUMBER(SEARCH(REF_Setup!$F$3:$F$15,M5)))>0,"VC Only","Unclassified"))))} -> VC Only
B6: =B5+1 -> 4 | C6: =IFERROR(_xlfn.XLOOKUP($B6,Raw_Data!$A$3:$A$273,Raw_Data!$B$3:$B$273),"") -> Aces Delta | D6: =IFERROR(_xlfn.XLOOKUP($B6,Raw_Data!$A$3:$A$273,Raw_Data!$C$3:$C$273),"") -> Holladay, UT | E6: =IFERROR(_xlfn.XLOOKUP($B6,Raw_Data!$A$3:$A$273,Raw_Data!$D$3:$D$273),"") -> 2019 | F6: =IFERROR(_xlfn.XLOOKUP($B6,Raw_Data!$A$3:$A$273,Raw_Data!$F$3:$F$273),"") -> Hydrogen | G6: =IFERROR(_xlfn.XLOOKUP($B6,Raw_Data!$A$3:$A$273,Raw_Data!$J$3:$J$273),"") -> 44721 | H6: Development capital | I6: =IFERROR(_xlfn.XLOOKUP($B6,Raw_Data!$A$3:$A$273,Raw_Data!$I$3:$I$273),"") -> 650 | J6: =IFERROR(_xlfn.XLOOKUP($B6,Raw_Data!$A$3:$A$273,Raw_Data!$L$3:$L$273),"") -> 650 | K6: =IFERROR(_xlfn.XLOOKUP($B6,Raw_Data!$A$3:$A$273,Raw_Data!$M$3:$M$273),"") -> 0 | L6: =IFERROR(_xlfn.XLOOKUP($B6,Raw_Data!$A$3:$A$273,Raw_Data!$Q$3:$Q$273),"") -> 0 | M6: =IFERROR(_xlfn.XLOOKUP($B6,Raw_Data!$A$3:$A$273,Raw_Data!$R$3:$R$273),"") -> Alberta Investment Management; GIC Private; Haddington Ventures, Manulife Financial; Onterio Teachers Pension Plan | N6: {=IF(M6="",0,COUNTA(_xlfn._xlws.FILTER(_xlfn.TEXTSPLIT(M6,";"), _xlfn.TEXTSPLIT(M6,";")<>"")))} -> 4 | O6: =IF(P6>0,"Y","N") -> N | P6: =IFERROR(_xlfn.XLOOKUP($B6,Raw_Data!$A$3:$A$273,Raw_Data!$V$3:$V$273),"") -> 0 | Q6: =IF(R6>0,"Y","N") -> Y | R6: =IFERROR(_xlfn.XLOOKUP($B6,Raw_Data!$A$3:$A$273,Raw_Data!$Y$3:$Y$273),"") -> 1 | S6: {=_xlfn.LET(_xlpm.s, Raw_Data!W6,_xlpm.strat, _xlfn._xlws.FILTER(REF_Setup!$B$3:$B$40, REF_Setup!$B$3:$B$40<>""),IF(OR(_xlpm.s="",_xlpm.s=0),"Unclassified",IF(SUM(--ISNUMBER(SEARCH(_xlpm.strat, _xlpm.s)))>0, "Y", "N")) )} -> N | T6: {=_xlfn.LET(_xlpm.s,M6,_xlpm.phil, _xlfn._xlws.FILTER(REF_Setup!$D$3:$D$5, REF_Setup!$D$3:$D$5<>""),IF(OR(_xlpm.s="", _xlpm.s=0),"Unclassified",IF(SUM(--ISNUMBER(SEARCH(_xlpm.phil, _xlpm.s)))>0, "Y", "N")))} -> N | U6: {=IF(M6="", "Unclassified", IF(AND(SUMPRODUCT(--ISNUMBER(SEARCH(REF_Setup!$B$3:$B$40,M6)))>0,SUMPRODUCT(--ISNUMBER(SEARCH(REF_Setup!$F$3:$F$15,M6)))>0),"Mixed",IF(SUMPRODUCT(--ISNUMBER(SEARCH(REF_Setup!$B$3:$B$40,M6)))>0,"Strategic Only",IF(SUMPRODUCT(--ISNUMBER(SEARCH(REF_Setup!$F$3:$F$15,M6)))>0,"VC Only","Unclassified"))))} -> VC Only
B7: =B6+1 -> 5 | C7: =IFERROR(_xlfn.XLOOKUP($B7,Raw_Data!$A$3:$A$273,Raw_Data!$B$3:$B$273),"") -> Addis Energy | D7: =IFERROR(_xlfn.XLOOKUP($B7,Raw_Data!$A$3:$A$273,Raw_Data!$C$3:$C$273),"") -> Somewille, MA | E7: =IFERROR(_xlfn.XLOOKUP($B7,Raw_Data!$A$3:$A$273,Raw_Data!$D$3:$D$273),"") -> 2024 | F7: =IFERROR(_xlfn.XLOOKUP($B7,Raw_Data!$A$3:$A$273,Raw_Data!$F$3:$F$273),"") -> Hydrogen | G7: =IFERROR(_xlfn.XLOOKUP($B7,Raw_Data!$A$3:$A$273,Raw_Data!$J$3:$J$273),"") -> 45978 | I7: =IFERROR(_xlfn.XLOOKUP($B7,Raw_Data!$A$3:$A$273,Raw_Data!$I$3:$I$273),"") -> 17.31 | J7: =IFERROR(_xlfn.XLOOKUP($B7,Raw_Data!$A$3:$A$273,Raw_Data!$L$3:$L$273),"") -> 8.41 | K7: =IFERROR(_xlfn.XLOOKUP($B7,Raw_Data!$A$3:$A$273,Raw_Data!$M$3:$M$273),"") -> 22 | L7: =IFERROR(_xlfn.XLOOKUP($B7,Raw_Data!$A$3:$A$273,Raw_Data!$Q$3:$Q$273),"") -> 0 | M7: =IFERROR(_xlfn.XLOOKUP($B7,Raw_Data!$A$3:$A$273,Raw_Data!$R$3:$R$273),"") -> At One Ventures; Engine Ventures; Pillar VC | N7: {=IF(M7="",0,COUNTA(_xlfn._xlws.FILTER(_xlfn.TEXTSPLIT(M7,";"), _xlfn.TEXTSPLIT(M7,";")<>"")))} -> 3 | O7: =IF(P7>0,"Y","N") -> Y | P7: =IFERROR(_xlfn.XLOOKUP($B7,Raw_Data!$A$3:$A$273,Raw_Data!$V$3:$V$273),"") -> 0.66666667 | Q7: =IF(R7>0,"Y","N") -> Y | R7: =IFERROR(_xlfn.XLOOKUP($B7,Raw_Data!$A$3:$A$273,Raw_Data!$Y$3:$Y$273),"") -> 0.33333333 | S7: {=_xlfn.LET(_xlpm.s, Raw_Data!W7,_xlpm.strat, _xlfn._xlws.FILTER(REF_Setup!$B$3:$B$40, REF_Setup!$B$3:$B$40<>""),IF(OR(_xlpm.s="",_xlpm.s=0),"Unclassified",IF(SUM(--ISNUMBER(SEARCH(_xlpm.strat, _xlpm.s)))>0, "Y", "N")) )} -> N | T7: {=_xlfn.LET(_xlpm.s,M7,_xlpm.phil, _xlfn._xlws.FILTER(REF_Setup!$D$3:$D$5, REF_Setup!$D$3:$D$5<>""),IF(OR(_xlpm.s="", _xlpm.s=0),"Unclassified",IF(SUM(--ISNUMBER(SEARCH(_xlpm.phil, _xlpm.s)))>0, "Y", "N")))} -> N | U7: {=IF(M7="", "Unclassified", IF(AND(SUMPRODUCT(--ISNUMBER(SEARCH(REF_Setup!$B$3:$B$40,M7)))>0,SUMPRODUCT(--ISNUMBER(SEARCH(REF_Setup!$F$3:$F$15,M7)))>0),"Mixed",IF(SUMPRODUCT(--ISNUMBER(SEARCH(REF_Setup!$B$3:$B$40,M7)))>0,"Strategic Only",IF(SUMPRODUCT(--ISNUMBER(SEARCH(REF_Setup!$F$3:$F$15,M7)))>0,"VC Only","Unclassified"))))} -> VC Only
B8: =B7+1 -> 6 | C8: =IFERROR(_xlfn.XLOOKUP($B8,Raw_Data!$A$3:$A$273,Raw_Data!$B$3:$B$273),"") -> Advanced Battery Concepts | D8: =IFERROR(_xlfn.XLOOKUP($B8,Raw_Data!$A$3:$A$273,Raw_Data!$C$3:$C$273),"") -> Clare, MI | E8: =IFERROR(_xlfn.XLOOKUP($B8,Raw_Data!$A$3:$A$273,Raw_Data!$D$3:$D$273),"") -> 2008 | F8: =IFERROR(_xlfn.XLOOKUP($B8,Raw_Data!$A$3:$A$273,Raw_Data!$F$3:$F$273),"") -> LDES | G8: =IFERROR(_xlfn.XLOOKUP($B8,Raw_Data!$A$3:$A$273,Raw_Data!$J$3:$J$273),"") -> 42207 | H8: Series A | I8: =IFERROR(_xlfn.XLOOKUP($B8,Raw_Data!$A$3:$A$273,Raw_Data!$I$3:$I$273),"") -> 8.76 | J8: =IFERROR(_xlfn.XLOOKUP($B8,Raw_Data!$A$3:$A$273,Raw_Data!$L$3:$L$273),"") -> 3.09 | K8: =IFERROR(_xlfn.XLOOKUP($B8,Raw_Data!$A$3:$A$273,Raw_Data!$M$3:$M$273),"") -> 0 | L8: =IFERROR(_xlfn.XLOOKUP($B8,Raw_Data!$A$3:$A$273,Raw_Data!$Q$3:$Q$273),"") -> 0 | M8: =IFERROR(_xlfn.XLOOKUP($B8,Raw_Data!$A$3:$A$273,Raw_Data!$R$3:$R$273),"") -> BlueWater Angels | N8: {=IF(M8="",0,COUNTA(_xlfn._xlws.FILTER(_xlfn.TEXTSPLIT(M8,";"), _xlfn.TEXTSPLIT(M8,";")<>"")))} -> 1 | O8: =IF(P8>0,"Y","N") -> Y | P8: =IFERROR(_xlfn.XLOOKUP($B8,Raw_Data!$A$3:$A$273,Raw_Data!$V$3:$V$273),"") -> 1 | Q8: =IF(R8>0,"Y","N") -> Y | R8: =IFERROR(_xlfn.XLOOKUP($B8,Raw_Data!$A$3:$A$273,Raw_Data!$Y$3:$Y$273),"") -> N/A | S8: {=_xlfn.LET(_xlpm.s, Raw_Data!W8,_xlpm.strat, _xlfn._xlws.FILTER(REF_Setup!$B$3:$B$40, REF_Setup!$B$3:$B$40<>""),IF(OR(_xlpm.s="",_xlpm.s=0),"Unclassified",IF(SUM(--ISNUMBER(SEARCH(_xlpm.strat, _xlpm.s)))>0, "Y", "N")) )} -> Unclassified | T8: {=_xlfn.LET(_xlpm.s,M8,_xlpm.phil, _xlfn._xlws.FILTER(REF_Setup!$D$3:$D$5, REF_Setup!$D$3:$D$5<>""),IF(OR(_xlpm.s="", _xlpm.s=0),"Unclassified",IF(SUM(--ISNUMBER(SEARCH(_xlpm.phil, _xlpm.s)))>0, "Y", "N")))} -> N | U8: {=IF(M8="", "Unclassified", IF(AND(SUMPRODUCT(--ISNUMBER(SEARCH(REF_Setup!$B$3:$B$40,M8)))>0,SUMPRODUCT(--ISNUMBER(SEARCH(REF_Setup!$F$3:$F$15,M8)))>0),"Mixed",IF(SUMPRODUCT(--ISNUMBER(SEARCH(REF_Setup!$B$3:$B$40,M8)))>0,"Strategic Only",IF(SUMPRODUCT(--ISNUMBER(SEARCH(REF_Setup!$F$3:$F$15,M8)))>0,"VC Only","Unclassified"))))} -> Unclassified
B9: =B8+1 -> 7 | C9: =IFERROR(_xlfn.XLOOKUP($B9,Raw_Data!$A$3:$A$273,Raw_Data!$B$3:$B$273),"") -> Advanced Battery Concepts | D9: =IFERROR(_xlfn.XLOOKUP($B9,Raw_Data!$A$3:$A$273,Raw_Data!$C$3:$C$273),"") -> Clare, MI | E9: =IFERROR(_xlfn.XLOOKUP($B9,Raw_Data!$A$3:$A$273,Raw_Data!$D$3:$D$273),"") -> 2008 | F9: =IFERROR(_xlfn.XLOOKUP($B9,Raw_Data!$A$3:$A$273,Raw_Data!$F$3:$F$273),"") -> LDES | G9: =IFERROR(_xlfn.XLOOKUP($B9,Raw_Data!$A$3:$A$273,Raw_Data!$J$3:$J$273),"") -> 42699 | H9: Series A | I9: =IFERROR(_xlfn.XLOOKUP($B9,Raw_Data!$A$3:$A$273,Raw_Data!$I$3:$I$273),"") -> 11.88 | J9: =IFERROR(_xlfn.XLOOKUP($B9,Raw_Data!$A$3:$A$273,Raw_Data!$L$3:$L$273),"") -> 3.12 | K9: =IFERROR(_xlfn.XLOOKUP($B9,Raw_Data!$A$3:$A$273,Raw_Data!$M$3:$M$273),"") -> 0 | L9: =IFERROR(_xlfn.XLOOKUP($B9,Raw_Data!$A$3:$A$273,Raw_Data!$Q$3:$Q$273),"") -> 0 | M9: =IFERROR(_xlfn.XLOOKUP($B9,Raw_Data!$A$3:$A$273,Raw_Data!$R$3:$R$273),"") -> BlueWater Angels; RSVP Ventures | N9: {=IF(M9="",0,COUNTA(_xlfn._xlws.FILTER(_xlfn.TEXTSPLIT(M9,";"), _xlfn.TEXTSPLIT(M9,";")<>"")))} -> 2 | O9: =IF(P9>0,"Y","N") -> Y | P9: =IFERROR(_xlfn.XLOOKUP($B9,Raw_Data!$A$3:$A$273,Raw_Data!$V$3:$V$273),"") -> 0.5 | Q9: =IF(R9>0,"Y","N") -> Y | R9: =IFERROR(_xlfn.XLOOKUP($B9,Raw_Data!$A$3:$A$273,Raw_Data!$Y$3:$Y$273),"") -> 0.5 | S9: {=_xlfn.LET(_xlpm.s, Raw_Data!W9,_xlpm.strat, _xlfn._xlws.FILTER(REF_Setup!$B$3:$B$40, REF_Setup!$B$3:$B$40<>""),IF(OR(_xlpm.s="",_xlpm.s=0),"Unclassified",IF(SUM(--ISNUMBER(SEARCH(_xlpm.strat, _xlpm.s)))>0, "Y", "N")) )} -> N | T9: {=_xlfn.LET(_xlpm.s,M9,_xlpm.phil, _xlfn._xlws.FILTER(REF_Setup!$D$3:$D$5, REF_Setup!$D$3:$D$5<>""),IF(OR(_xlpm.s="", _xlpm.s=0),"Unclassified",IF(SUM(--ISNUMBER(SEARCH(_xlpm.phil, _xlpm.s)))>0, "Y", "N")))} -> N | U9: {=IF(M9="", "Unclassified", IF(AND(SUMPRODUCT(--ISNUMBER(SEARCH(REF_Setup!$B$3:$B$40,M9)))>0,SUMPRODUCT(--ISNUMBER(SEARCH(REF_Setup!$F$3:$F$15,M9)))>0),"Mixed",IF(SUMPRODUCT(--ISNUMBER(SEARCH(REF_Setup!$B$3:$B$40,M9)))>0,"Strategic Only",IF(SUMPRODUCT(--ISNUMBER(SEARCH(REF_Setup!$F$3:$F$15,M9)))>0,"VC Only","Unclassified"))))} -> VC Only
B10: =B9+1 -> 8 | C10: =IFERROR(_xlfn.XLOOKUP($B10,Raw_Data!$A$3:$A$273,Raw_Data!$B$3:$B$273),"") -> Aither Systems | D10: =IFERROR(_xlfn.XLOOKUP($B10,Raw_Data!$A$3:$A$273,Raw_Data!$C$3:$C$273),"") -> Alien, TX | E10: =IFERROR(_xlfn.XLOOKUP($B10,Raw_Data!$A$3:$A$273,Raw_Data!$D$3:$D$273),"") -> 0 | F10: =IFERROR(_xlfn.XLOOKUP($B10,Raw_Data!$A$3:$A$273,Raw_Data!$F$3:$F$273),"") -> LDES | G10: =IFERROR(_xlfn.XLOOKUP($B10,Raw_Data!$A$3:$A$273,Raw_Data!$J$3:$J$273),"") -> 45292 | H10: Development capital | I10: =IFERROR(_xlfn.XLOOKUP($B10,Raw_Data!$A$3:$A$273,Raw_Data!$I$3:$I$273),"") -> 0 | J10: =IFERROR(_xlfn.XLOOKUP($B10,Raw_Data!$A$3:$A$273,Raw_Data!$L$3:$L$273),"") -> 0 | K10: =IFERROR(_xlfn.XLOOKUP($B10,Raw_Data!$A$3:$A$273,Raw_Data!$M$3:$M$273),"") -> 0 | L10: =IFERROR(_xlfn.XLOOKUP($B10,Raw_Data!$A$3:$A$273,Raw_Data!$Q$3:$Q$273),"") -> N/A | M10: =IFERROR(_xlfn.XLOOKUP($B10,Raw_Data!$A$3:$A$273,Raw_Data!$R$3:$R$273),"") -> Encap Investments | N10: {=IF(M10="",0,COUNTA(_xlfn._xlws.FILTER(_xlfn.TEXTSPLIT(M10,";"), _xlfn.TEXTSPLIT(M10,";")<>"")))} -> 1 | O10: =IF(P10>0,"Y","N") -> N | P10: =IFERROR(_xlfn.XLOOKUP($B10,Raw_Data!$A$3:$A$273,Raw_Data!$V$3:$V$273),"") -> 0 | Q10: =IF(R10>0,"Y","N") -> Y | R10: =IFERROR(_xlfn.XLOOKUP($B10,Raw_Data!$A$3:$A$273,Raw_Data!$Y$3:$Y$273),"") -> 1 | S10: {=_xlfn.LET(_xlpm.s, Raw_Data!W10,_xlpm.strat, _xlfn._xlws.FILTER(REF_Setup!$B$3:$B$40, REF_Setup!$B$3:$B$40<>""),IF(OR(_xlpm.s="",_xlpm.s=0),"Unclassified",IF(SUM(--ISNUMBER(SEARCH(_xlpm.strat, _xlpm.s)))>0, "Y", "N")) )} -> N | T10: {=_xlfn.LET(_xlpm.s,M10,_xlpm.phil, _xlfn._xlws.FILTER(REF_Setup!$D$3:$D$5, REF_Setup!$D$3:$D$5<>""),IF(OR(_xlpm.s="", _xlpm.s=0),"Unclassified",IF(SUM(--ISNUMBER(SEARCH(_xlpm.phil, _xlpm.s)))>0, "Y", "N")))} -> N | U10: {=IF(M10="", "Unclassified", IF(AND(SUMPRODUCT(--ISNUMBER(SEARCH(REF_Setup!$B$3:$B$40,M10)))>0,SUMPRODUCT(--ISNUMBER(SEARCH(REF_Setup!$F$3:$F$15,M10)))>0),"Mixed",IF(SUMPRODUCT(--ISNUMBER(SEARCH(REF_Setup!$B$3:$B$40,M10)))>0,"Strategic Only",IF(SUMPRODUCT(--ISNUMBER(SEARCH(REF_Setup!$F$3:$F$15,M10)))>0,"VC Only","Unclassified"))))} -> VC Only
B11: =B10+1 -> 9 | C11: =IFERROR(_xlfn.XLOOKUP($B11,Raw_Data!$A$3:$A$273,Raw_Data!$B$3:$B$273),"") -> Alva Energy (Commercial Services) | D11: =IFERROR(_xlfn.XLOOKUP($B11,Raw_Data!$A$3:$A$273,Raw_Data!$C$3:$C$273),"") -> Cambridge, MA | E11: =IFERROR(_xlfn.XLOOKUP($B11,Raw_Data!$A$3:$A$273,Raw_Data!$D$3:$D$273),"") -> 2023 | F11: =IFERROR(_xlfn.XLOOKUP($B11,Raw_Data!$A$3:$A$273,Raw_Data!$F$3:$F$273),"") -> Renewables | G11: =IFERROR(_xlfn.XLOOKUP($B11,Raw_Data!$A$3:$A$273,Raw_Data!$J$3:$J$273),"") -> 45658 | H11: Development capital | I11: =IFERROR(_xlfn.XLOOKUP($B11,Raw_Data!$A$3:$A$273,Raw_Data!$I$3:$I$273),"") -> 0 | J11: =IFERROR(_xlfn.XLOOKUP($B11,Raw_Data!$A$3:$A$273,Raw_Data!$L$3:$L$273),"") -> 0 | K11: =IFERROR(_xlfn.XLOOKUP($B11,Raw_Data!$A$3:$A$273,Raw_Data!$M$3:$M$273),"") -> 0 | L11: =IFERROR(_xlfn.XLOOKUP($B11,Raw_Data!$A$3:$A$273,Raw_Data!$Q$3:$Q$273),"") -> N/A | M11: =IFERROR(_xlfn.XLOOKUP($B11,Raw_Data!$A$3:$A$273,Raw_Data!$R$3:$R$273),"") -> NGP Energy Capital Management | N11: {=IF(M11="",0,COUNTA(_xlfn._xlws.FILTER(_xlfn.TEXTSPLIT(M11,";"), _xlfn.TEXTSPLIT(M11,";")<>"")))} -> 1 | O11: =IF(P11>0,"Y","N") -> N | P11: =IFERROR(_xlfn.XLOOKUP($B11,Raw_Data!$A$3:$A$273,Raw_Data!$V$3:$V$273),"") -> 0 | Q11: =IF(R11>0,"Y","N") -> Y | R11: =IFERROR(_xlfn.XLOOKUP($B11,Raw_Data!$A$3:$A$273,Raw_Data!$Y$3:$Y$273),"") -> 1 | S11: {=_xlfn.LET(_xlpm.s, Raw_Data!W11,_xlpm.strat, _xlfn._xlws.FILTER(REF_Setup!$B$3:$B$40, REF_Setup!$B$3:$B$40<>""),IF(OR(_xlpm.s="",_xlpm.s=0),"Unclassified",IF(SUM(--ISNUMBER(SEARCH(_xlpm.strat, _xlpm.s)))>0, "Y", "N")) )} -> N | T11: {=_xlfn.LET(_xlpm.s,M11,_xlpm.phil, _xlfn._xlws.FILTER(REF_Setup!$D$3:$D$5, REF_Setup!$D$3:$D$5<>""),IF(OR(_xlpm.s="", _xlpm.s=0),"Unclassified",IF(SUM(--ISNUMBER(SEARCH(_xlpm.phil, _xlpm.s)))>0, "Y", "N")))} -> N | U11: {=IF(M11="", "Unclassified", IF(AND(SUMPRODUCT(--ISNUMBER(SEARCH(REF_Setup!$B$3:$B$40,M11)))>0,SUMPRODUCT(--ISNUMBER(SEARCH(REF_Setup!$F$3:$F$15,M11)))>0),"Mixed",IF(SUMPRODUCT(--ISNUMBER(SEARCH(REF_Setup!$B$3:$B$40,M11)))>0,"Strategic Only",IF(SUMPRODUCT(--ISNUMBER(SEARCH(REF_Setup!$F$3:$F$15,M11)))>0,"VC Only","Unclassified"))))} -> VC Only
B12: =B11+1 -> 10 | C12: =IFERROR(_xlfn.XLOOKUP($B12,Raw_Data!$A$3:$A$273,Raw_Data!$B$3:$B$273),"") -> Amai (Food Products) | D12: =IFERROR(_xlfn.XLOOKUP($B12,Raw_Data!$A$3:$A$273,Raw_Data!$C$3:$C$273),"") -> Vista, CA | E12: =IFERROR(_xlfn.XLOOKUP($B12,Raw_Data!$A$3:$A$273,Raw_Data!$D$3:$D$273),"") -> 2020 | F12: =IFERROR(_xlfn.XLOOKUP($B12,Raw_Data!$A$3:$A$273,Raw_Data!$F$3:$F$273),"") -> Food & Ag | G12: =IFERROR(_xlfn.XLOOKUP($B12,Raw_Data!$A$3:$A$273,Raw_Data!$J$3:$J$273),"") -> 44270 | I12: =IFERROR(_xlfn.XLOOKUP($B12,Raw_Data!$A$3:$A$273,Raw_Data!$I$3:$I$273),"") -> 0.2 | J12: =IFERROR(_xlfn.XLOOKUP($B12,Raw_Data!$A$3:$A$273,Raw_Data!$L$3:$L$273),"") -> 0 | K12: =IFERROR(_xlfn.XLOOKUP($B12,Raw_Data!$A$3:$A$273,Raw_Data!$M$3:$M$273),"") -> 0 | L12: =IFERROR(_xlfn.XLOOKUP($B12,Raw_Data!$A$3:$A$273,Raw_Data!$Q$3:$Q$273),"") -> N/A | M12: =IFERROR(_xlfn.XLOOKUP($B12,Raw_Data!$A$3:$A$273,Raw_Data!$R$3:$R$273),"") -> Chartered Investment Managers | N12: {=IF(M12="",0,COUNTA(_xlfn._xlws.FILTER(_xlfn.TEXTSPLIT(M12,";"), _xlfn.TEXTSPLIT(M12,";")<>"")))} -> 1 | O12: =IF(P12>0,"Y","N") -> N | P12: =IFERROR(_xlfn.XLOOKUP($B12,Raw_Data!$A$3:$A$273,Raw_Data!$V$3:$V$273),"") -> 0 | Q12: =IF(R12>0,"Y","N") -> Y | R12: =IFERROR(_xlfn.XLOOKUP($B12,Raw_Data!$A$3:$A$273,Raw_Data!$Y$3:$Y$273),"") -> 1 | S12: {=_xlfn.LET(_xlpm.s, Raw_Data!W12,_xlpm.strat, _xlfn._xlws.FILTER(REF_Setup!$B$3:$B$40, REF_Setup!$B$3:$B$40<>""),IF(OR(_xlpm.s="",_xlpm.s=0),"Unclassified",IF(SUM(--ISNUMBER(SEARCH(_xlpm.strat, _xlpm.s)))>0, "Y", "N")) )} -> N | T12: {=_xlfn.LET(_xlpm.s,M12,_xlpm.phil, _xlfn._xlws.FILTER(REF_Setup!$D$3:$D$5, REF_Setup!$D$3:$D$5<>""),IF(OR(_xlpm.s="", _xlpm.s=0),"Unclassified",IF(SUM(--ISNUMBER(SEARCH(_xlpm.phil, _xlpm.s)))>0, "Y", "N")))} -> N | U12: {=IF(M12="", "Unclassified", IF(AND(SUMPRODUCT(--ISNUMBER(SEARCH(REF_Setup!$B$3:$B$40,M12)))>0,SUMPRODUCT(--ISNUMBER(SEARCH(REF_Setup!$F$3:$F$15,M12)))>0),"Mixed",IF(SUMPRODUCT(--ISNUMBER(SEARCH(REF_Setup!$B$3:$B$40,M12)))>0,"Strategic Only",IF(SUMPRODUCT(--ISNUMBER(SEARCH(REF_Setup!$F$3:$F$15,M12)))>0,"VC Only","Unclassified"))))} -> VC Only
B13: =B12+1 -> 11 | C13: =IFERROR(_xlfn.XLOOKUP($B13,Raw_Data!$A$3:$A$273,Raw_Data!$B$3:$B$273),"") -> Amber Kinetics | D13: =IFERROR(_xlfn.XLOOKUP($B13,Raw_Data!$A$3:$A$273,Raw_Data!$C$3:$C$273),"") -> Union City, CA | E13: =IFERROR(_xlfn.XLOOKUP($B13,Raw_Data!$A$3:$A$273,Raw_Data!$D$3:$D$273),"") -> 2009 | F13: =IFERROR(_xlfn.XLOOKUP($B13,Raw_Data!$A$3:$A$273,Raw_Data!$F$3:$F$273),"") -> LDES | G13: =IFERROR(_xlfn.XLOOKUP($B13,Raw_Data!$A$3:$A$273,Raw_Data!$J$3:$J$273),"") -> 45474 | H13: Development capital | I13: =IFERROR(_xlfn.XLOOKUP($B13,Raw_Data!$A$3:$A$273,Raw_Data!$I$3:$I$273),"") -> 46.98 | J13: =IFERROR(_xlfn.XLOOKUP($B13,Raw_Data!$A$3:$A$273,Raw_Data!$L$3:$L$273),"") -> 0 | K13: =IFERROR(_xlfn.XLOOKUP($B13,Raw_Data!$A$3:$A$273,Raw_Data!$M$3:$M$273),"") -> 0 | L13: =IFERROR(_xlfn.XLOOKUP($B13,Raw_Data!$A$3:$A$273,Raw_Data!$Q$3:$Q$273),"") -> N/A | M13: =IFERROR(_xlfn.XLOOKUP($B13,Raw_Data!$A$3:$A$273,Raw_Data!$R$3:$R$273),"") -> Innova Capital Partners | N13: {=IF(M13="",0,COUNTA(_xlfn._xlws.FILTER(_xlfn.TEXTSPLIT(M13,";"), _xlfn.TEXTSPLIT(M13,";")<>"")))} -> 1 | O13: =IF(P13>0,"Y","N") -> N | P13: =IFERROR(_xlfn.XLOOKUP($B13,Raw_Data!$A$3:$A$273,Raw_Data!$V$3:$V$273),"") -> 0 | Q13: =IF(R13>0,"Y","N") -> Y | R13: =IFERROR(_xlfn.XLOOKUP($B13,Raw_Data!$A$3:$A$273,Raw_Data!$Y$3:$Y$273),"") -> 1 | S13: {=_xlfn.LET(_xlpm.s, Raw_Data!W13,_xlpm.strat, _xlfn._xlws.FILTER(REF_Setup!$B$3:$B$40, REF_Setup!$B$3:$B$40<>""),IF(OR(_xlpm.s="",_xlpm.s=0),"Unclassified",IF(SUM(--ISNUMBER(SEARCH(_xlpm.strat, _xlpm.s)))>0, "Y", "N")) )} -> N | T13: {=_xlfn.LET(_xlpm.s,M13,_xlpm.phil, _xlfn._xlws.FILTER(REF_Setup!$D$3:$D$5, REF_Setup!$D$3:$D$5<>""),IF(OR(_xlpm.s="", _xlpm.s=0),"Unclassified",IF(SUM(--ISNUMBER(SEARCH(_xlpm.phil, _xlpm.s)))>0, "Y", "N")))} -> N | U13: {=IF(M13="", "Unclassified", IF(AND(SUMPRODUCT(--ISNUMBER(SEARCH(REF_Setup!$B$3:$B$40,M13)))>0,SUMPRODUCT(--ISNUMBER(SEARCH(REF_Setup!$F$3:$F$15,M13)))>0),"Mixed",IF(SUMPRODUCT(--ISNUMBER(SEARCH(REF_Setup!$B$3:$B$40,M13)))>0,"Strategic Only",IF(SUMPRODUCT(--ISNUMBER(SEARCH(REF_Setup!$F$3:$F$15,M13)))>0,"VC Only","Unclassified"))))} -> VC Only
B14: =B13+1 -> 12 | C14: =IFERROR(_xlfn.XLOOKUP($B14,Raw_Data!$A$3:$A$273,Raw_Data!$B$3:$B$273),"") -> Amogy | D14: =IFERROR(_xlfn.XLOOKUP($B14,Raw_Data!$A$3:$A$273,Raw_Data!$C$3:$C$273),"") -> New York, NY | E14: =IFERROR(_xlfn.XLOOKUP($B14,Raw_Data!$A$3:$A$273,Raw_Data!$D$3:$D$273),"") -> 2020 | F14: =IFERROR(_xlfn.XLOOKUP($B14,Raw_Data!$A$3:$A$273,Raw_Data!$F$3:$F$273),"") -> Hydrogen | G14: =IFERROR(_xlfn.XLOOKUP($B14,Raw_Data!$A$3:$A$273,Raw_Data!$J$3:$J$273),"") -> 45002 | H14: Series B | I14: =IFERROR(_xlfn.XLOOKUP($B14,Raw_Data!$A$3:$A$273,Raw_Data!$I$3:$I$273),"") -> 207.94 | J14: =IFERROR(_xlfn.XLOOKUP($B14,Raw_Data!$A$3:$A$273,Raw_Data!$L$3:$L$273),"") -> 139 | K14: =IFERROR(_xlfn.XLOOKUP($B14,Raw_Data!$A$3:$A$273,Raw_Data!$M$3:$M$273),"") -> 589 | L14: =IFERROR(_xlfn.XLOOKUP($B14,Raw_Data!$A$3:$A$273,Raw_Data!$Q$3:$Q$273),"") -> 0 | M14: =IFERROR(_xlfn.XLOOKUP($B14,Raw_Data!$A$3:$A$273,Raw_Data!$R$3:$R$273),"") -> AP Ventures; Aramco Ventures; DCVC; Guernsey Holdings; Korea Zinc; Mitsui & Company; MOL PLUS; SK Innovation; Temasek Holdings; Yanmar Holdings; Zeon Ventures | N14: {=IF(M14="",0,COUNTA(_xlfn._xlws.FILTER(_xlfn.TEXTSPLIT(M14,";"), _xlfn.TEXTSPLIT(M14,";")<>"")))} -> 11 | O14: =IF(P14>0,"Y","N") -> Y | P14: =IFERROR(_xlfn.XLOOKUP($B14,Raw_Data!$A$3:$A$273,Raw_Data!$V$3:$V$273),"") -> 0.36363636 | Q14: =IF(R14>0,"Y","N") -> Y | R14: =IFERROR(_xlfn.XLOOKUP($B14,Raw_Data!$A$3:$A$273,Raw_Data!$Y$3:$Y$273),"") -> 0.63636364 | S14: {=_xlfn.LET(_xlpm.s, Raw_Data!W14,_xlpm.strat, _xlfn._xlws.FILTER(REF_Setup!$B$3:$B$40, REF_Setup!$B$3:$B$40<>""),IF(OR(_xlpm.s="",_xlpm.s=0),"Unclassified",IF(SUM(--ISNUMBER(SEARCH(_xlpm.strat, _xlpm.s)))>0, "Y", "N")) )} -> N | T14: {=_xlfn.LET(_xlpm.s,M14,_xlpm.phil, _xlfn._xlws.FILTER(REF_Setup!$D$3:$D$5, REF_Setup!$D$3:$D$5<>""),IF(OR(_xlpm.s="", _xlpm.s=0),"Unclassified",IF(SUM(--ISNUMBER(SEARCH(_xlpm.phil, _xlpm.s)))>0, "Y", "N")))} -> N | U14: {=IF(M14="", "Unclassified", IF(AND(SUMPRODUCT(--ISNUMBER(SEARCH(REF_Setup!$B$3:$B$40,M14)))>0,SUMPRODUCT(--ISNUMBER(SEARCH(REF_Setup!$F$3:$F$15,M14)))>0),"Mixed",IF(SUMPRODUCT(--ISNUMBER(SEARCH(REF_Setup!$B$3:$B$40,M14)))>0,"Strategic Only",IF(SUMPRODUCT(--ISNUMBER(SEARCH(REF_Setup!$F$3:$F$15,M14)))>0,"VC Only","Unclassified"))))} -> Mixed
B15: =B14+1 -> 13 | C15: =IFERROR(_xlfn.XLOOKUP($B15,Raw_Data!$A$3:$A$273,Raw_Data!$B$3:$B$273),"") -> Amogy | D15: =IFERROR(_xlfn.XLOOKUP($B15,Raw_Data!$A$3:$A$273,Raw_Data!$C$3:$C$273),"") -> New York, NY | E15: =IFERROR(_xlfn.XLOOKUP($B15,Raw_Data!$A$3:$A$273,Raw_Data!$D$3:$D$273),"") -> 2020 | F15: =IFERROR(_xlfn.XLOOKUP($B15,Raw_Data!$A$3:$A$273,Raw_Data!$F$3:$F$273),"") -> Hydrogen | G15: =IFERROR(_xlfn.XLOOKUP($B15,Raw_Data!$A$3:$A$273,Raw_Data!$J$3:$J$273),"") -> 45853 | H15: Series B | I15: =IFERROR(_xlfn.XLOOKUP($B15,Raw_Data!$A$3:$A$273,Raw_Data!$I$3:$I$273),"") -> 314.16 | J15: =IFERROR(_xlfn.XLOOKUP($B15,Raw_Data!$A$3:$A$273,Raw_Data!$L$3:$L$273),"") -> 95 | K15: =IFERROR(_xlfn.XLOOKUP($B15,Raw_Data!$A$3:$A$273,Raw_Data!$M$3:$M$273),"") -> 700 | L15: =IFERROR(_xlfn.XLOOKUP($B15,Raw_Data!$A$3:$A$273,Raw_Data!$Q$3:$Q$273),"") -> 0.47473684 | M15: =IFERROR(_xlfn.XLOOKUP($B15,Raw_Data!$A$3:$A$273,Raw_Data!$R$3:$R$273),"") -> AFW Partners; AP Ventures; Aramco Ventures; BHP Ventures; KDB Investment; SV Investment; MOL PLUS; Yanmar Holdings; Samsung Heavy Industries; BHP Ventures; MOL Switch; JB Investment (Private Equity); GS Engineering & Construction; Xplor Investment; GS Futures; Marunouchi Innovation Partners; Pathway Capital Management; Seoul Investment Partners; AFW Partners; AP Ventures; Odyssey Ventures (London); BonAngels Venture Partners; Quantum Ventures Korea; Kibo Invest; Temasek Holdings; Hanwha Investment & Securities Company; Gorilla Private Equity | N15: {=IF(M15="",0,COUNTA(_xlfn._xlws.FILTER(_xlfn.TEXTSPLIT(M15,";"), _xlfn.TEXTSPLIT(M15,";")<>"")))} -> 27 | O15: =IF(P15>0,"Y","N") -> Y | P15: =IFERROR(_xlfn.XLOOKUP($B15,Raw_Data!$A$3:$A$273,Raw_Data!$V$3:$V$273),"") -> 0.14814815 | Q15: =IF(R15>0,"Y","N") -> Y | R15: =IFERROR(_xlfn.XLOOKUP($B15,Raw_Data!$A$3:$A$273,Raw_Data!$Y$3:$Y$273),"") -> 0.85185185 | S15: {=_xlfn.LET(_xlpm.s, Raw_Data!W15,_xlpm.strat, _xlfn._xlws.FILTER(REF_Setup!$B$3:$B$40, REF_Setup!$B$3:$B$40<>""),IF(OR(_xlpm.s="",_xlpm.s=0),"Unclassified",IF(SUM(--ISNUMBER(SEARCH(_xlpm.strat, _xlpm.s)))>0, "Y", "N")) )} -> Y | T15: {=_xlfn.LET(_xlpm.s,M15,_xlpm.phil, _xlfn._xlws.FILTER(REF_Setup!$D$3:$D$5, REF_Setup!$D$3:$D$5<>""),IF(OR(_xlpm.s="", _xlpm.s=0),"Unclassified",IF(SUM(--ISNUMBER(SEARCH(_xlpm.phil, _xlpm.s)))>0, "Y", "N")))} -> N | U15: {=IF(M15="", "Unclassified", IF(AND(SUMPRODUCT(--ISNUMBER(SEARCH(REF_Setup!$B$3:$B$40,M15)))>0,SUMPRODUCT(--ISNUMBER(SEARCH(REF_Setup!$F$3:$F$15,M15)))>0),"Mixed",IF(SUMPRODUCT(--ISNUMBER(SEARCH(REF_Setup!$B$3:$B$40,M15)))>0,"Strategic Only",IF(SUMPRODUCT(--ISNUMBER(SEARCH(REF_Setup!$F$3:$F$15,M15)))>0,"VC Only","Unclassified"))))} -> Mixed
B16: =B15+1 -> 14 | C16: =IFERROR(_xlfn.XLOOKUP($B16,Raw_Data!$A$3:$A$273,Raw_Data!$B$3:$B$273),"") -> Ampcera | D16: =IFERROR(_xlfn.XLOOKUP($B16,Raw_Data!$A$3:$A$273,Raw_Data!$C$3:$C$273),"") -> San Jose, CA | E16: =IFERROR(_xlfn.XLOOKUP($B16,Raw_Data!$A$3:$A$273,Raw_Data!$D$3:$D$273),"") -> 2017 | F16: =IFERROR(_xlfn.XLOOKUP($B16,Raw_Data!$A$3:$A$273,Raw_Data!$F$3:$F$273),"") -> LDES | G16: =IFERROR(_xlfn.XLOOKUP($B16,Raw_Data!$A$3:$A$273,Raw_Data!$J$3:$J$273),"") -> 43220 | H16: Seed | I16: =IFERROR(_xlfn.XLOOKUP($B16,Raw_Data!$A$3:$A$273,Raw_Data!$I$3:$I$273),"") -> 1 | J16: =IFERROR(_xlfn.XLOOKUP($B16,Raw_Data!$A$3:$A$273,Raw_Data!$L$3:$L$273),"") -> 1 | K16: =IFERROR(_xlfn.XLOOKUP($B16,Raw_Data!$A$3:$A$273,Raw_Data!$M$3:$M$273),"") -> 10 | L16: =IFERROR(_xlfn.XLOOKUP($B16,Raw_Data!$A$3:$A$273,Raw_Data!$Q$3:$Q$273),"") -> 0 | N16: {=IF(M16="",0,COUNTA(_xlfn._xlws.FILTER(_xlfn.TEXTSPLIT(M16,";"), _xlfn.TEXTSPLIT(M16,";")<>"")))} -> 0 | O16: =IF(P16>0,"Y","N") -> Y | P16: =IFERROR(_xlfn.XLOOKUP($B16,Raw_Data!$A$3:$A$273,Raw_Data!$V$3:$V$273),"") -> N/A | Q16: =IF(R16>0,"Y","N") -> Y | R16: =IFERROR(_xlfn.XLOOKUP($B16,Raw_Data!$A$3:$A$273,Raw_Data!$Y$3:$Y$273),"") -> N/A | S16: {=_xlfn.LET(_xlpm.s, Raw_Data!W16,_xlpm.strat, _xlfn._xlws.FILTER(REF_Setup!$B$3:$B$40, REF_Setup!$B$3:$B$40<>""),IF(OR(_xlpm.s="",_xlpm.s=0),"Unclassified",IF(SUM(--ISNUMBER(SEARCH(_xlpm.strat, _xlpm.s)))>0, "Y", "N")) )} -> Unclassified | T16: {=_xlfn.LET(_xlpm.s,M16,_xlpm.phil, _xlfn._xlws.FILTER(REF_Setup!$D$3:$D$5, REF_Setup!$D$3:$D$5<>""),IF(OR(_xlpm.s="", _xlpm.s=0),"Unclassified",IF(SUM(--ISNUMBER(SEARCH(_xlpm.phil, _xlpm.s)))>0, "Y", "N")))} -> Unclassified | U16: {=IF(M16="", "Unclassified", IF(AND(SUMPRODUCT(--ISNUMBER(SEARCH(REF_Setup!$B$3:$B$40,M16)))>0,SUMPRODUCT(--ISNUMBER(SEARCH(REF_Setup!$F$3:$F$15,M16)))>0),"Mixed",IF(SUMPRODUCT(--ISNUMBER(SEARCH(REF_Setup!$B$3:$B$40,M16)))>0,"Strategic Only",IF(SUMPRODUCT(--ISNUMBER(SEARCH(REF_Setup!$F$3:$F$15,M16)))>0,"VC Only","Unclassified"))))} -> Unclassified
B17: =B16+1 -> 15 | C17: =IFERROR(_xlfn.XLOOKUP($B17,Raw_Data!$A$3:$A$273,Raw_Data!$B$3:$B$273),"") -> Anesi | D17: =IFERROR(_xlfn.XLOOKUP($B17,Raw_Data!$A$3:$A$273,Raw_Data!$C$3:$C$273),"") -> TN | E17: =IFERROR(_xlfn.XLOOKUP($B17,Raw_Data!$A$3:$A$273,Raw_Data!$D$3:$D$273),"") -> 2010 | F17: =IFERROR(_xlfn.XLOOKUP($B17,Raw_Data!$A$3:$A$273,Raw_Data!$F$3:$F$273),"") -> Buildings | G17: =IFERROR(_xlfn.XLOOKUP($B17,Raw_Data!$A$3:$A$273,Raw_Data!$J$3:$J$273),"") -> 44358 | H17: Series A | I17: =IFERROR(_xlfn.XLOOKUP($B17,Raw_Data!$A$3:$A$273,Raw_Data!$I$3:$I$273),"") -> 3.3 | J17: =IFERROR(_xlfn.XLOOKUP($B17,Raw_Data!$A$3:$A$273,Raw_Data!$L$3:$L$273),"") -> 3.3 | K17: =IFERROR(_xlfn.XLOOKUP($B17,Raw_Data!$A$3:$A$273,Raw_Data!$M$3:$M$273),"") -> 10 | L17: =IFERROR(_xlfn.XLOOKUP($B17,Raw_Data!$A$3:$A$273,Raw_Data!$Q$3:$Q$273),"") -> 0.24242424 | M17: =IFERROR(_xlfn.XLOOKUP($B17,Raw_Data!$A$3:$A$273,Raw_Data!$R$3:$R$273),"") -> Enbridge | N17: {=IF(M17="",0,COUNTA(_xlfn._xlws.FILTER(_xlfn.TEXTSPLIT(M17,";"), _xlfn.TEXTSPLIT(M17,";")<>"")))} -> 1 | O17: =IF(P17>0,"Y","N") -> N | P17: =IFERROR(_xlfn.XLOOKUP($B17,Raw_Data!$A$3:$A$273,Raw_Data!$V$3:$V$273),"") -> 0 | Q17: =IF(R17>0,"Y","N") -> Y | R17: =IFERROR(_xlfn.XLOOKUP($B17,Raw_Data!$A$3:$A$273,Raw_Data!$Y$3:$Y$273),"") -> 1 | S17: {=_xlfn.LET(_xlpm.s, Raw_Data!W17,_xlpm.strat, _xlfn._xlws.FILTER(REF_Setup!$B$3:$B$40, REF_Setup!$B$3:$B$40<>""),IF(OR(_xlpm.s="",_xlpm.s=0),"Unclassified",IF(SUM(--ISNUMBER(SEARCH(_xlpm.strat, _xlpm.s)))>0, "Y", "N")) )} -> N | T17: {=_xlfn.LET(_xlpm.s,M17,_xlpm.phil, _xlfn._xlws.FILTER(REF_Setup!$D$3:$D$5, REF_Setup!$D$3:$D$5<>""),IF(OR(_xlpm.s="", _xlpm.s=0),"Unclassified",IF(SUM(--ISNUMBER(SEARCH(_xlpm.phil, _xlpm.s)))>0, "Y", "N")))} -> N | U17: {=IF(M17="", "Unclassified", IF(AND(SUMPRODUCT(--ISNUMBER(SEARCH(REF_Setup!$B$3:$B$40,M17)))>0,SUMPRODUCT(--ISNUMBER(SEARCH(REF_Setup!$F$3:$F$15,M17)))>0),"Mixed",IF(SUMPRODUCT(--ISNUMBER(SEARCH(REF_Setup!$B$3:$B$40,M17)))>0,"Strategic Only",IF(SUMPRODUCT(--ISNUMBER(SEARCH(REF_Setup!$F$3:$F$15,M17)))>0,"VC Only","Unclassified"))))} -> Unclassified
B18: =B17+1 -> 16 | C18: =IFERROR(_xlfn.XLOOKUP($B18,Raw_Data!$A$3:$A$273,Raw_Data!$B$3:$B$273),"") -> Anesi | D18: =IFERROR(_xlfn.XLOOKUP($B18,Raw_Data!$A$3:$A$273,Raw_Data!$C$3:$C$273),"") -> TN | E18: =IFERROR(_xlfn.XLOOKUP($B18,Raw_Data!$A$3:$A$273,Raw_Data!$D$3:$D$273),"") -> 2010 | F18: =IFERROR(_xlfn.XLOOKUP($B18,Raw_Data!$A$3:$A$273,Raw_Data!$F$3:$F$273),"") -> Buildings | G18: =IFERROR(_xlfn.XLOOKUP($B18,Raw_Data!$A$3:$A$273,Raw_Data!$J$3:$J$273),"") -> 44869 | H18: Series A | I18: =IFERROR(_xlfn.XLOOKUP($B18,Raw_Data!$A$3:$A$273,Raw_Data!$I$3:$I$273),"") -> 20.8 | J18: =IFERROR(_xlfn.XLOOKUP($B18,Raw_Data!$A$3:$A$273,Raw_Data!$L$3:$L$273),"") -> 17.5 | K18: =IFERROR(_xlfn.XLOOKUP($B18,Raw_Data!$A$3:$A$273,Raw_Data!$M$3:$M$273),"") -> 36.5 | L18: =IFERROR(_xlfn.XLOOKUP($B18,Raw_Data!$A$3:$A$273,Raw_Data!$Q$3:$Q$273),"") -> 0 | M18: =IFERROR(_xlfn.XLOOKUP($B18,Raw_Data!$A$3:$A$273,Raw_Data!$R$3:$R$273),"") -> Energy Impact Partners | N18: {=IF(M18="",0,COUNTA(_xlfn._xlws.FILTER(_xlfn.TEXTSPLIT(M18,";"), _xlfn.TEXTSPLIT(M18,";")<>"")))} -> 1 | O18: =IF(P18>0,"Y","N") -> N | P18: =IFERROR(_xlfn.XLOOKUP($B18,Raw_Data!$A$3:$A$273,Raw_Data!$V$3:$V$273),"") -> 0 | Q18: =IF(R18>0,"Y","N") -> Y | R18: =IFERROR(_xlfn.XLOOKUP($B18,Raw_Data!$A$3:$A$273,Raw_Data!$Y$3:$Y$273),"") -> 1 | S18: {=_xlfn.LET(_xlpm.s, Raw_Data!W18,_xlpm.strat, _xlfn._xlws.FILTER(REF_Setup!$B$3:$B$40, REF_Setup!$B$3:$B$40<>""),IF(OR(_xlpm.s="",_xlpm.s=0),"Unclassified",IF(SUM(--ISNUMBER(SEARCH(_xlpm.strat, _xlpm.s)))>0, "Y", "N")) )} -> N | T18: {=_xlfn.LET(_xlpm.s,M18,_xlpm.phil, _xlfn._xlws.FILTER(REF_Setup!$D$3:$D$5, REF_Setup!$D$3:$D$5<>""),IF(OR(_xlpm.s="", _xlpm.s=0),"Unclassified",IF(SUM(--ISNUMBER(SEARCH(_xlpm.phil, _xlpm.s)))>0, "Y", "N")))} -> N | U18: {=IF(M18="", "Unclassified", IF(AND(SUMPRODUCT(--ISNUMBER(SEARCH(REF_Setup!$B$3:$B$40,M18)))>0,SUMPRODUCT(--ISNUMBER(SEARCH(REF_Setup!$F$3:$F$15,M18)))>0),"Mixed",IF(SUMPRODUCT(--ISNUMBER(SEARCH(REF_Setup!$B$3:$B$40,M18)))>0,"Strategic Only",IF(SUMPRODUCT(--ISNUMBER(SEARCH(REF_Setup!$F$3:$F$15,M18)))>0,"VC Only","Unclassified"))))} -> VC Only
B19: =B18+1 -> 17 | C19: =IFERROR(_xlfn.XLOOKUP($B19,Raw_Data!$A$3:$A$273,Raw_Data!$B$3:$B$273),"") -> Anthro Energy | D19: =IFERROR(_xlfn.XLOOKUP($B19,Raw_Data!$A$3:$A$273,Raw_Data!$C$3:$C$273),"") -> Alameda, CA | E19: =IFERROR(_xlfn.XLOOKUP($B19,Raw_Data!$A$3:$A$273,Raw_Data!$D$3:$D$273),"") -> 2020 | F19: =IFERROR(_xlfn.XLOOKUP($B19,Raw_Data!$A$3:$A$273,Raw_Data!$F$3:$F$273),"") -> LDES | G19: =IFERROR(_xlfn.XLOOKUP($B19,Raw_Data!$A$3:$A$273,Raw_Data!$J$3:$J$273),"") -> 44197 | H19: Seed | I19: =IFERROR(_xlfn.XLOOKUP($B19,Raw_Data!$A$3:$A$273,Raw_Data!$I$3:$I$273),"") -> 0.53 | J19: =IFERROR(_xlfn.XLOOKUP($B19,Raw_Data!$A$3:$A$273,Raw_Data!$L$3:$L$273),"") -> 0.53 | K19: =IFERROR(_xlfn.XLOOKUP($B19,Raw_Data!$A$3:$A$273,Raw_Data!$M$3:$M$273),"") -> 2 | L19: =IFERROR(_xlfn.XLOOKUP($B19,Raw_Data!$A$3:$A$273,Raw_Data!$Q$3:$Q$273),"") -> 0 | M19: =IFERROR(_xlfn.XLOOKUP($B19,Raw_Data!$A$3:$A$273,Raw_Data!$R$3:$R$273),"") -> Black Mountain Ventures; Cameron Drummond; Dorm Room Fund | N19: {=IF(M19="",0,COUNTA(_xlfn._xlws.FILTER(_xlfn.TEXTSPLIT(M19,";"), _xlfn.TEXTSPLIT(M19,";")<>"")))} -> 3 | O19: =IF(P19>0,"Y","N") -> N | P19: =IFERROR(_xlfn.XLOOKUP($B19,Raw_Data!$A$3:$A$273,Raw_Data!$V$3:$V$273),"") -> 0 | Q19: =IF(R19>0,"Y","N") -> Y | R19: =IFERROR(_xlfn.XLOOKUP($B19,Raw_Data!$A$3:$A$273,Raw_Data!$Y$3:$Y$273),"") -> 1 | S19: {=_xlfn.LET(_xlpm.s, Raw_Data!W19,_xlpm.strat, _xlfn._xlws.FILTER(REF_Setup!$B$3:$B$40, REF_Setup!$B$3:$B$40<>""),IF(OR(_xlpm.s="",_xlpm.s=0),"Unclassified",IF(SUM(--ISNUMBER(SEARCH(_xlpm.strat, _xlpm.s)))>0, "Y", "N")) )} -> N | T19: {=_xlfn.LET(_xlpm.s,M19,_xlpm.phil, _xlfn._xlws.FILTER(REF_Setup!$D$3:$D$5, REF_Setup!$D$3:$D$5<>""),IF(OR(_xlpm.s="", _xlpm.s=0),"Unclassified",IF(SUM(--ISNUMBER(SEARCH(_xlpm.phil, _xlpm.s)))>0, "Y", "N")))} -> N | U19: {=IF(M19="", "Unclassified", IF(AND(SUMPRODUCT(--ISNUMBER(SEARCH(REF_Setup!$B$3:$B$40,M19)))>0,SUMPRODUCT(--ISNUMBER(SEARCH(REF_Setup!$F$3:$F$15,M19)))>0),"Mixed",IF(SUMPRODUCT(--ISNUMBER(SEARCH(REF_Setup!$B$3:$B$40,M19)))>0,"Strategic Only",IF(SUMPRODUCT(--ISNUMBER(SEARCH(REF_Setup!$F$3:$F$15,M19)))>0,"VC Only","Unclassified"))))} -> VC Only
B20: =B19+1 -> 18 | C20: =IFERROR(_xlfn.XLOOKUP($B20,Raw_Data!$A$3:$A$273,Raw_Data!$B$3:$B$273),"") -> Antora Energy | D20: =IFERROR(_xlfn.XLOOKUP($B20,Raw_Data!$A$3:$A$273,Raw_Data!$C$3:$C$273),"") -> Sunnyuale, CA | E20: =IFERROR(_xlfn.XLOOKUP($B20,Raw_Data!$A$3:$A$273,Raw_Data!$D$3:$D$273),"") -> 2017 | F20: =IFERROR(_xlfn.XLOOKUP($B20,Raw_Data!$A$3:$A$273,Raw_Data!$F$3:$F$273),"") -> LDES | G20: =IFERROR(_xlfn.XLOOKUP($B20,Raw_Data!$A$3:$A$273,Raw_Data!$J$3:$J$273),"") -> 44834 | H20: Series B | I20: =IFERROR(_xlfn.XLOOKUP($B20,Raw_Data!$A$3:$A$273,Raw_Data!$I$3:$I$273),"") -> 87.4 | J20: =IFERROR(_xlfn.XLOOKUP($B20,Raw_Data!$A$3:$A$273,Raw_Data!$L$3:$L$273),"") -> 30 | K20: =IFERROR(_xlfn.XLOOKUP($B20,Raw_Data!$A$3:$A$273,Raw_Data!$M$3:$M$273),"") -> 190.4 | L20: =IFERROR(_xlfn.XLOOKUP($B20,Raw_Data!$A$3:$A$273,Raw_Data!$Q$3:$Q$273),"") -> 0.32 | M20: =IFERROR(_xlfn.XLOOKUP($B20,Raw_Data!$A$3:$A$273,Raw_Data!$R$3:$R$273),"") -> CalSEED; Keybridge Venture Partners; Overture Climate VC; Reaction Global; StartX | N20: {=IF(M20="",0,COUNTA(_xlfn._xlws.FILTER(_xlfn.TEXTSPLIT(M20,";"), _xlfn.TEXTSPLIT(M20,";")<>"")))} -> 5 | O20: =IF(P20>0,"Y","N") -> Y | P20: =IFERROR(_xlfn.XLOOKUP($B20,Raw_Data!$A$3:$A$273,Raw_Data!$V$3:$V$273),"") -> 0.2 | Q20: =IF(R20>0,"Y","N") -> Y | R20: =IFERROR(_xlfn.XLOOKUP($B20,Raw_Data!$A$3:$A$273,Raw_Data!$Y$3:$Y$273),"") -> 0.8 | S20: {=_xlfn.LET(_xlpm.s, Raw_Data!W20,_xlpm.strat, _xlfn._xlws.FILTER(REF_Setup!$B$3:$B$40, REF_Setup!$B$3:$B$40<>""),IF(OR(_xlpm.s="",_xlpm.s=0),"Unclassified",IF(SUM(--ISNUMBER(SEARCH(_xlpm.strat, _xlpm.s)))>0, "Y", "N")) )} -> N | T20: {=_xlfn.LET(_xlpm.s,M20,_xlpm.phil, _xlfn._xlws.FILTER(REF_Setup!$D$3:$D$5, REF_Setup!$D$3:$D$5<>""),IF(OR(_xlpm.s="", _xlpm.s=0),"Unclassified",IF(SUM(--ISNUMBER(SEARCH(_xlpm.phil, _xlpm.s)))>0, "Y", "N")))} -> N | U20: {=IF(M20="", "Unclassified", IF(AND(SUMPRODUCT(--ISNUMBER(SEARCH(REF_Setup!$B$3:$B$40,M20)))>0,SUMPRODUCT(--ISNUMBER(SEARCH(REF_Setup!$F$3:$F$15,M20)))>0),"Mixed",IF(SUMPRODUCT(--ISNUMBER(SEARCH(REF_Setup!$B$3:$B$40,M20)))>0,"Strategic Only",IF(SUMPRODUCT(--ISNUMBER(SEARCH(REF_Setup!$F$3:$F$15,M20)))>0,"VC Only","Unclassified"))))} -> VC Only
B21: =B20+1 -> 19 | C21: =IFERROR(_xlfn.XLOOKUP($B21,Raw_Data!$A$3:$A$273,Raw_Data!$B$3:$B$273),"") -> AtmosZero | D21: =IFERROR(_xlfn.XLOOKUP($B21,Raw_Data!$A$3:$A$273,Raw_Data!$C$3:$C$273),"") -> Fort Collins, CO | E21: =IFERROR(_xlfn.XLOOKUP($B21,Raw_Data!$A$3:$A$273,Raw_Data!$D$3:$D$273),"") -> 2021 | F21: =IFERROR(_xlfn.XLOOKUP($B21,Raw_Data!$A$3:$A$273,Raw_Data!$F$3:$F$273),"") -> Industrial Decarbonization | G21: =IFERROR(_xlfn.XLOOKUP($B21,Raw_Data!$A$3:$A$273,Raw_Data!$J$3:$J$273),"") -> 44897 | H21: Series A | I21: =IFERROR(_xlfn.XLOOKUP($B21,Raw_Data!$A$3:$A$273,Raw_Data!$I$3:$I$273),"") -> 7.5 | J21: =IFERROR(_xlfn.XLOOKUP($B21,Raw_Data!$A$3:$A$273,Raw_Data!$L$3:$L$273),"") -> 3.5 | K21: =IFERROR(_xlfn.XLOOKUP($B21,Raw_Data!$A$3:$A$273,Raw_Data!$M$3:$M$273),"") -> 20 | L21: =IFERROR(_xlfn.XLOOKUP($B21,Raw_Data!$A$3:$A$273,Raw_Data!$Q$3:$Q$273),"") -> 0 | M21: =IFERROR(_xlfn.XLOOKUP($B21,Raw_Data!$A$3:$A$273,Raw_Data!$R$3:$R$273),"") -> AENU; Energy Impact Partners | N21: {=IF(M21="",0,COUNTA(_xlfn._xlws.FILTER(_xlfn.TEXTSPLIT(M21,";"), _xlfn.TEXTSPLIT(M21,";")<>"")))} -> 2 | O21: =IF(P21>0,"Y","N") -> Y | P21: =IFERROR(_xlfn.XLOOKUP($B21,Raw_Data!$A$3:$A$273,Raw_Data!$V$3:$V$273),"") -> 0.5 | Q21: =IF(R21>0,"Y","N") -> Y | R21: =IFERROR(_xlfn.XLOOKUP($B21,Raw_Data!$A$3:$A$273,Raw_Data!$Y$3:$Y$273),"") -> 0.5 | S21: {=_xlfn.LET(_xlpm.s, Raw_Data!W21,_xlpm.strat, _xlfn._xlws.FILTER(REF_Setup!$B$3:$B$40, REF_Setup!$B$3:$B$40<>""),IF(OR(_xlpm.s="",_xlpm.s=0),"Unclassified",IF(SUM(--ISNUMBER(SEARCH(_xlpm.strat, _xlpm.s)))>0, "Y", "N")) )} -> N | T21: {=_xlfn.LET(_xlpm.s,M21,_xlpm.phil, _xlfn._xlws.FILTER(REF_Setup!$D$3:$D$5, REF_Setup!$D$3:$D$5<>""),IF(OR(_xlpm.s="", _xlpm.s=0),"Unclassified",IF(SUM(--ISNUMBER(SEARCH(_xlpm.phil, _xlpm.s)))>0, "Y", "N")))} -> N | U21: {=IF(M21="", "Unclassified", IF(AND(SUMPRODUCT(--ISNUMBER(SEARCH(REF_Setup!$B$3:$B$40,M21)))>0,SUMPRODUCT(--ISNUMBER(SEARCH(REF_Setup!$F$3:$F$15,M21)))>0),"Mixed",IF(SUMPRODUCT(--ISNUMBER(SEARCH(REF_Setup!$B$3:$B$40,M21)))>0,"Strategic Only",IF(SUMPRODUCT(--ISNUMBER(SEARCH(REF_Setup!$F$3:$F$15,M21)))>0,"VC Only","Unclassified"))))} -> VC Only
B22: =B21+1 -> 20 | C22: =IFERROR(_xlfn.XLOOKUP($B22,Raw_Data!$A$3:$A$273,Raw_Data!$B$3:$B$273),"") -> Aymium | D22: =IFERROR(_xlfn.XLOOKUP($B22,Raw_Data!$A$3:$A$273,Raw_Data!$C$3:$C$273),"") -> Gwinn, MI | E22: =IFERROR(_xlfn.XLOOKUP($B22,Raw_Data!$A$3:$A$273,Raw_Data!$D$3:$D$273),"") -> 2012 | F22: =IFERROR(_xlfn.XLOOKUP($B22,Raw_Data!$A$3:$A$273,Raw_Data!$F$3:$F$273),"") -> Industrial Decarbonization | G22: =IFERROR(_xlfn.XLOOKUP($B22,Raw_Data!$A$3:$A$273,Raw_Data!$J$3:$J$273),"") -> 44621 | H22: Development capital | I22: =IFERROR(_xlfn.XLOOKUP($B22,Raw_Data!$A$3:$A$273,Raw_Data!$I$3:$I$273),"") -> 0 | J22: =IFERROR(_xlfn.XLOOKUP($B22,Raw_Data!$A$3:$A$273,Raw_Data!$L$3:$L$273),"") -> 0 | K22: =IFERROR(_xlfn.XLOOKUP($B22,Raw_Data!$A$3:$A$273,Raw_Data!$M$3:$M$273),"") -> 0 | L22: =IFERROR(_xlfn.XLOOKUP($B22,Raw_Data!$A$3:$A$273,Raw_Data!$Q$3:$Q$273),"") -> N/A | M22: =IFERROR(_xlfn.XLOOKUP($B22,Raw_Data!$A$3:$A$273,Raw_Data!$R$3:$R$273),"") -> Nippon Steel Trading; Rio Tinto; Sandton Capital Partners; Steel Dynamics | N22: {=IF(M22="",0,COUNTA(_xlfn._xlws.FILTER(_xlfn.TEXTSPLIT(M22,";"), _xlfn.TEXTSPLIT(M22,";")<>"")))} -> 4 | O22: =IF(P22>0,"Y","N") -> N | P22: =IFERROR(_xlfn.XLOOKUP($B22,Raw_Data!$A$3:$A$273,Raw_Data!$V$3:$V$273),"") -> 0 | Q22: =IF(R22>0,"Y","N") -> Y | R22: =IFERROR(_xlfn.XLOOKUP($B22,Raw_Data!$A$3:$A$273,Raw_Data!$Y$3:$Y$273),"") -> 1 | S22: {=_xlfn.LET(_xlpm.s, Raw_Data!W22,_xlpm.strat, _xlfn._xlws.FILTER(REF_Setup!$B$3:$B$40, REF_Setup!$B$3:$B$40<>""),IF(OR(_xlpm.s="",_xlpm.s=0),"Unclassified",IF(SUM(--ISNUMBER(SEARCH(_xlpm.strat, _xlpm.s)))>0, "Y", "N")) )} -> Y | T22: {=_xlfn.LET(_xlpm.s,M22,_xlpm.phil, _xlfn._xlws.FILTER(REF_Setup!$D$3:$D$5, REF_Setup!$D$3:$D$5<>""),IF(OR(_xlpm.s="", _xlpm.s=0),"Unclassified",IF(SUM(--ISNUMBER(SEARCH(_xlpm.phil, _xlpm.s)))>0, "Y", "N")))} -> N | U22: {=IF(M22="", "Unclassified", IF(AND(SUMPRODUCT(--ISNUMBER(SEARCH(REF_Setup!$B$3:$B$40,M22)))>0,SUMPRODUCT(--ISNUMBER(SEARCH(REF_Setup!$F$3:$F$15,M22)))>0),"Mixed",IF(SUMPRODUCT(--ISNUMBER(SEARCH(REF_Setup!$B$3:$B$40,M22)))>0,"Strategic Only",IF(SUMPRODUCT(--ISNUMBER(SEARCH(REF_Setup!$F$3:$F$15,M22)))>0,"VC Only","Unclassified"))))} -> Mixed
B23: =B22+1 -> 21 | C23: =IFERROR(_xlfn.XLOOKUP($B23,Raw_Data!$A$3:$A$273,Raw_Data!$B$3:$B$273),"") -> Baja Carports | D23: =IFERROR(_xlfn.XLOOKUP($B23,Raw_Data!$A$3:$A$273,Raw_Data!$C$3:$C$273),"") -> Martinez, CA | E23: =IFERROR(_xlfn.XLOOKUP($B23,Raw_Data!$A$3:$A$273,Raw_Data!$D$3:$D$273),"") -> 1981 | F23: =IFERROR(_xlfn.XLOOKUP($B23,Raw_Data!$A$3:$A$273,Raw_Data!$F$3:$F$273),"") -> Renewables | G23: =IFERROR(_xlfn.XLOOKUP($B23,Raw_Data!$A$3:$A$273,Raw_Data!$J$3:$J$273),"") -> 45566 | H23: Development capital | I23: =IFERROR(_xlfn.XLOOKUP($B23,Raw_Data!$A$3:$A$273,Raw_Data!$I$3:$I$273),"") -> 0 | J23: =IFERROR(_xlfn.XLOOKUP($B23,Raw_Data!$A$3:$A$273,Raw_Data!$L$3:$L$273),"") -> 0 | K23: =IFERROR(_xlfn.XLOOKUP($B23,Raw_Data!$A$3:$A$273,Raw_Data!$M$3:$M$273),"") -> 0 | L23: =IFERROR(_xlfn.XLOOKUP($B23,Raw_Data!$A$3:$A$273,Raw_Data!$Q$3:$Q$273),"") -> N/A | M23: =IFERROR(_xlfn.XLOOKUP($B23,Raw_Data!$A$3:$A$273,Raw_Data!$R$3:$R$273),"") -> Compass Group Equity Partners | N23: {=IF(M23="",0,COUNTA(_xlfn._xlws.FILTER(_xlfn.TEXTSPLIT(M23,";"), _xlfn.TEXTSPLIT(M23,";")<>"")))} -> 1 | O23: =IF(P23>0,"Y","N") -> N | P23: =IFERROR(_xlfn.XLOOKUP($B23,Raw_Data!$A$3:$A$273,Raw_Data!$V$3:$V$273),"") -> 0 | Q23: =IF(R23>0,"Y","N") -> Y | R23: =IFERROR(_xlfn.XLOOKUP($B23,Raw_Data!$A$3:$A$273,Raw_Data!$Y$3:$Y$273),"") -> 1 | S23: {=_xlfn.LET(_xlpm.s, Raw_Data!W23,_xlpm.strat, _xlfn._xlws.FILTER(REF_Setup!$B$3:$B$40, REF_Setup!$B$3:$B$40<>""),IF(OR(_xlpm.s="",_xlpm.s=0),"Unclassified",IF(SUM(--ISNUMBER(SEARCH(_xlpm.strat, _xlpm.s)))>0, "Y", "N")) )} -> N | T23: {=_xlfn.LET(_xlpm.s,M23,_xlpm.phil, _xlfn._xlws.FILTER(REF_Setup!$D$3:$D$5, REF_Setup!$D$3:$D$5<>""),IF(OR(_xlpm.s="", _xlpm.s=0),"Unclassified",IF(SUM(--ISNUMBER(SEARCH(_xlpm.phil, _xlpm.s)))>0, "Y", "N")))} -> N | U23: {=IF(M23="", "Unclassified", IF(AND(SUMPRODUCT(--ISNUMBER(SEARCH(REF_Setup!$B$3:$B$40,M23)))>0,SUMPRODUCT(--ISNUMBER(SEARCH(REF_Setup!$F$3:$F$15,M23)))>0),"Mixed",IF(SUMPRODUCT(--ISNUMBER(SEARCH(REF_Setup!$B$3:$B$40,M23)))>0,"Strategic Only",IF(SUMPRODUCT(--ISNUMBER(SEARCH(REF_Setup!$F$3:$F$15,M23)))>0,"VC Only","Unclassified"))))} -> VC Only
B24: =B23+1 -> 22 | C24: =IFERROR(_xlfn.XLOOKUP($B24,Raw_Data!$A$3:$A$273,Raw_Data!$B$3:$B$273),"") -> BayoTech | D24: =IFERROR(_xlfn.XLOOKUP($B24,Raw_Data!$A$3:$A$273,Raw_Data!$C$3:$C$273),"") -> Houston, TX | E24: =IFERROR(_xlfn.XLOOKUP($B24,Raw_Data!$A$3:$A$273,Raw_Data!$D$3:$D$273),"") -> 2015 | F24: =IFERROR(_xlfn.XLOOKUP($B24,Raw_Data!$A$3:$A$273,Raw_Data!$F$3:$F$273),"") -> Hydrogen | G24: =IFERROR(_xlfn.XLOOKUP($B24,Raw_Data!$A$3:$A$273,Raw_Data!$J$3:$J$273),"") -> 44189 | H24: Development capital | I24: =IFERROR(_xlfn.XLOOKUP($B24,Raw_Data!$A$3:$A$273,Raw_Data!$I$3:$I$273),"") -> 173.7 | J24: =IFERROR(_xlfn.XLOOKUP($B24,Raw_Data!$A$3:$A$273,Raw_Data!$L$3:$L$273),"") -> 157 | K24: =IFERROR(_xlfn.XLOOKUP($B24,Raw_Data!$A$3:$A$273,Raw_Data!$M$3:$M$273),"") -> 0 | L24: =IFERROR(_xlfn.XLOOKUP($B24,Raw_Data!$A$3:$A$273,Raw_Data!$Q$3:$Q$273),"") -> 0 | M24: =IFERROR(_xlfn.XLOOKUP($B24,Raw_Data!$A$3:$A$273,Raw_Data!$R$3:$R$273),"") -> Cottonwood Technology Fund+S32; Fortistar; Newlight Partners; Sun Mountain Capital | N24: {=IF(M24="",0,COUNTA(_xlfn._xlws.FILTER(_xlfn.TEXTSPLIT(M24,";"), _xlfn.TEXTSPLIT(M24,";")<>"")))} -> 4 | O24: =IF(P24>0,"Y","N") -> Y | P24: =IFERROR(_xlfn.XLOOKUP($B24,Raw_Data!$A$3:$A$273,Raw_Data!$V$3:$V$273),"") -> 0.5 | Q24: =IF(R24>0,"Y","N") -> Y | R24: =IFERROR(_xlfn.XLOOKUP($B24,Raw_Data!$A$3:$A$273,Raw_Data!$Y$3:$Y$273),"") -> 0.75 | S24: {=_xlfn.LET(_xlpm.s, Raw_Data!W24,_xlpm.strat, _xlfn._xlws.FILTER(REF_Setup!$B$3:$B$40, REF_Setup!$B$3:$B$40<>""),IF(OR(_xlpm.s="",_xlpm.s=0),"Unclassified",IF(SUM(--ISNUMBER(SEARCH(_xlpm.strat, _xlpm.s)))>0, "Y", "N")) )} -> N | T24: {=_xlfn.LET(_xlpm.s,M24,_xlpm.phil, _xlfn._xlws.FILTER(REF_Setup!$D$3:$D$5, REF_Setup!$D$3:$D$5<>""),IF(OR(_xlpm.s="", _xlpm.s=0),"Unclassified",IF(SUM(--ISNUMBER(SEARCH(_xlpm.phil, _xlpm.s)))>0, "Y", "N")))} -> N | U24: {=IF(M24="", "Unclassified", IF(AND(SUMPRODUCT(--ISNUMBER(SEARCH(REF_Setup!$B$3:$B$40,M24)))>0,SUMPRODUCT(--ISNUMBER(SEARCH(REF_Setup!$F$3:$F$15,M24)))>0),"Mixed",IF(SUMPRODUCT(--ISNUMBER(SEARCH(REF_Setup!$B$3:$B$40,M24)))>0,"Strategic Only",IF(SUMPRODUCT(--ISNUMBER(SEARCH(REF_Setup!$F$3:$F$15,M24)))>0,"VC Only","Unclassified"))))} -> VC Only
B25: =B24+1 -> 23 | C25: =IFERROR(_xlfn.XLOOKUP($B25,Raw_Data!$A$3:$A$273,Raw_Data!$B$3:$B$273),"") -> BayoTech | D25: =IFERROR(_xlfn.XLOOKUP($B25,Raw_Data!$A$3:$A$273,Raw_Data!$C$3:$C$273),"") -> Houston, TX | E25: =IFERROR(_xlfn.XLOOKUP($B25,Raw_Data!$A$3:$A$273,Raw_Data!$D$3:$D$273),"") -> 2015 | F25: =IFERROR(_xlfn.XLOOKUP($B25,Raw_Data!$A$3:$A$273,Raw_Data!$F$3:$F$273),"") -> Hydrogen | G25: =IFERROR(_xlfn.XLOOKUP($B25,Raw_Data!$A$3:$A$273,Raw_Data!$J$3:$J$273),"") -> 44204 | H25: Development capital | I25: =IFERROR(_xlfn.XLOOKUP($B25,Raw_Data!$A$3:$A$273,Raw_Data!$I$3:$I$273),"") -> 183.7 | J25: =IFERROR(_xlfn.XLOOKUP($B25,Raw_Data!$A$3:$A$273,Raw_Data!$L$3:$L$273),"") -> 10 | K25: =IFERROR(_xlfn.XLOOKUP($B25,Raw_Data!$A$3:$A$273,Raw_Data!$M$3:$M$273),"") -> 0 | L25: =IFERROR(_xlfn.XLOOKUP($B25,Raw_Data!$A$3:$A$273,Raw_Data!$Q$3:$Q$273),"") -> 0 | N25: {=IF(M25="",0,COUNTA(_xlfn._xlws.FILTER(_xlfn.TEXTSPLIT(M25,";"), _xlfn.TEXTSPLIT(M25,";")<>"")))} -> 0 | O25: =IF(P25>0,"Y","N") -> Y | P25: =IFERROR(_xlfn.XLOOKUP($B25,Raw_Data!$A$3:$A$273,Raw_Data!$V$3:$V$273),"") -> N/A | Q25: =IF(R25>0,"Y","N") -> Y | R25: =IFERROR(_xlfn.XLOOKUP($B25,Raw_Data!$A$3:$A$273,Raw_Data!$Y$3:$Y$273),"") -> N/A | S25: {=_xlfn.LET(_xlpm.s, Raw_Data!W25,_xlpm.strat, _xlfn._xlws.FILTER(REF_Setup!$B$3:$B$40, REF_Setup!$B$3:$B$40<>""),IF(OR(_xlpm.s="",_xlpm.s=0),"Unclassified",IF(SUM(--ISNUMBER(SEARCH(_xlpm.strat, _xlpm.s)))>0, "Y", "N")) )} -> Unclassified | T25: {=_xlfn.LET(_xlpm.s,M25,_xlpm.phil, _xlfn._xlws.FILTER(REF_Setup!$D$3:$D$5, REF_Setup!$D$3:$D$5<>""),IF(OR(_xlpm.s="", _xlpm.s=0),"Unclassified",IF(SUM(--ISNUMBER(SEARCH(_xlpm.phil, _xlpm.s)))>0, "Y", "N")))} -> Unclassified | U25: {=IF(M25="", "Unclassified", IF(AND(SUMPRODUCT(--ISNUMBER(SEARCH(REF_Setup!$B$3:$B$40,M25)))>0,SUMPRODUCT(--ISNUMBER(SEARCH(REF_Setup!$F$3:$F$15,M25)))>0),"Mixed",IF(SUMPRODUCT(--ISNUMBER(SEARCH(REF_Setup!$B$3:$B$40,M25)))>0,"Strategic Only",IF(SUMPRODUCT(--ISNUMBER(SEARCH(REF_Setup!$F$3:$F$15,M25)))>0,"VC Only","Unclassified"))))} -> Unclassified
B26: =B25+1 -> 24 | C26: =IFERROR(_xlfn.XLOOKUP($B26,Raw_Data!$A$3:$A$273,Raw_Data!$B$3:$B$273),"") -> BayoTech | D26: =IFERROR(_xlfn.XLOOKUP($B26,Raw_Data!$A$3:$A$273,Raw_Data!$C$3:$C$273),"") -> Houston, TX | E26: =IFERROR(_xlfn.XLOOKUP($B26,Raw_Data!$A$3:$A$273,Raw_Data!$D$3:$D$273),"") -> 2015 | F26: =IFERROR(_xlfn.XLOOKUP($B26,Raw_Data!$A$3:$A$273,Raw_Data!$F$3:$F$273),"") -> Hydrogen | G26: =IFERROR(_xlfn.XLOOKUP($B26,Raw_Data!$A$3:$A$273,Raw_Data!$J$3:$J$273),"") -> 44390 | H26: Development capital | I26: =IFERROR(_xlfn.XLOOKUP($B26,Raw_Data!$A$3:$A$273,Raw_Data!$I$3:$I$273),"") -> 213.7 | J26: =IFERROR(_xlfn.XLOOKUP($B26,Raw_Data!$A$3:$A$273,Raw_Data!$L$3:$L$273),"") -> 30 | K26: =IFERROR(_xlfn.XLOOKUP($B26,Raw_Data!$A$3:$A$273,Raw_Data!$M$3:$M$273),"") -> 0 | L26: =IFERROR(_xlfn.XLOOKUP($B26,Raw_Data!$A$3:$A$273,Raw_Data!$Q$3:$Q$273),"") -> 0 | N26: {=IF(M26="",0,COUNTA(_xlfn._xlws.FILTER(_xlfn.TEXTSPLIT(M26,";"), _xlfn.TEXTSPLIT(M26,";")<>"")))} -> 0 | O26: =IF(P26>0,"Y","N") -> Y | P26: =IFERROR(_xlfn.XLOOKUP($B26,Raw_Data!$A$3:$A$273,Raw_Data!$V$3:$V$273),"") -> N/A | Q26: =IF(R26>0,"Y","N") -> Y | R26: =IFERROR(_xlfn.XLOOKUP($B26,Raw_Data!$A$3:$A$273,Raw_Data!$Y$3:$Y$273),"") -> N/A | S26: {=_xlfn.LET(_xlpm.s, Raw_Data!W26,_xlpm.strat, _xlfn._xlws.FILTER(REF_Setup!$B$3:$B$40, REF_Setup!$B$3:$B$40<>""),IF(OR(_xlpm.s="",_xlpm.s=0),"Unclassified",IF(SUM(--ISNUMBER(SEARCH(_xlpm.strat, _xlpm.s)))>0, "Y", "N")) )} -> Unclassified | T26: {=_xlfn.LET(_xlpm.s,M26,_xlpm.phil, _xlfn._xlws.FILTER(REF_Setup!$D$3:$D$5, REF_Setup!$D$3:$D$5<>""),IF(OR(_xlpm.s="", _xlpm.s=0),"Unclassified",IF(SUM(--ISNUMBER(SEARCH(_xlpm.phil, _xlpm.s)))>0, "Y", "N")))} -> Unclassified | U26: {=IF(M26="", "Unclassified", IF(AND(SUMPRODUCT(--ISNUMBER(SEARCH(REF_Setup!$B$3:$B$40,M26)))>0,SUMPRODUCT(--ISNUMBER(SEARCH(REF_Setup!$F$3:$F$15,M26)))>0),"Mixed",IF(SUMPRODUCT(--ISNUMBER(SEARCH(REF_Setup!$B$3:$B$40,M26)))>0,"Strategic Only",IF(SUMPRODUCT(--ISNUMBER(SEARCH(REF_Setup!$F$3:$F$15,M26)))>0,"VC Only","Unclassified"))))} -> Unclassified
B27: =B26+1 -> 25 | C27: =IFERROR(_xlfn.XLOOKUP($B27,Raw_Data!$A$3:$A$273,Raw_Data!$B$3:$B$273),"") -> Biomason | D27: =IFERROR(_xlfn.XLOOKUP($B27,Raw_Data!$A$3:$A$273,Raw_Data!$C$3:$C$273),"") -> Durham, NC | E27: =IFERROR(_xlfn.XLOOKUP($B27,Raw_Data!$A$3:$A$273,Raw_Data!$D$3:$D$273),"") -> 2012 | F27: =IFERROR(_xlfn.XLOOKUP($B27,Raw_Data!$A$3:$A$273,Raw_Data!$F$3:$F$273),"") -> Industrial Decarbonization | G27: =IFERROR(_xlfn.XLOOKUP($B27,Raw_Data!$A$3:$A$273,Raw_Data!$J$3:$J$273),"") -> 45645 | H27: Series B | I27: =IFERROR(_xlfn.XLOOKUP($B27,Raw_Data!$A$3:$A$273,Raw_Data!$I$3:$I$273),"") -> 132.88 | J27: =IFERROR(_xlfn.XLOOKUP($B27,Raw_Data!$A$3:$A$273,Raw_Data!$L$3:$L$273),"") -> 16.7 | K27: =IFERROR(_xlfn.XLOOKUP($B27,Raw_Data!$A$3:$A$273,Raw_Data!$M$3:$M$273),"") -> 186.67 | L27: =IFERROR(_xlfn.XLOOKUP($B27,Raw_Data!$A$3:$A$273,Raw_Data!$Q$3:$Q$273),"") -> 0 | M27: =IFERROR(_xlfn.XLOOKUP($B27,Raw_Data!$A$3:$A$273,Raw_Data!$R$3:$R$273),"") -> 2150; Celesta Capital; Noel Ventures; Novo Holdings | N27: {=IF(M27="",0,COUNTA(_xlfn._xlws.FILTER(_xlfn.TEXTSPLIT(M27,";"), _xlfn.TEXTSPLIT(M27,";")<>"")))} -> 4 | O27: =IF(P27>0,"Y","N") -> Y | P27: =IFERROR(_xlfn.XLOOKUP($B27,Raw_Data!$A$3:$A$273,Raw_Data!$V$3:$V$273),"") -> 1 | Q27: =IF(R27>0,"Y","N") -> Y | R27: =IFERROR(_xlfn.XLOOKUP($B27,Raw_Data!$A$3:$A$273,Raw_Data!$Y$3:$Y$273),"") -> 0.25 | S27: {=_xlfn.LET(_xlpm.s, Raw_Data!W27,_xlpm.strat, _xlfn._xlws.FILTER(REF_Setup!$B$3:$B$40, REF_Setup!$B$3:$B$40<>""),IF(OR(_xlpm.s="",_xlpm.s=0),"Unclassified",IF(SUM(--ISNUMBER(SEARCH(_xlpm.strat, _xlpm.s)))>0, "Y", "N")) )} -> N | T27: {=_xlfn.LET(_xlpm.s,M27,_xlpm.phil, _xlfn._xlws.FILTER(REF_Setup!$D$3:$D$5, REF_Setup!$D$3:$D$5<>""),IF(OR(_xlpm.s="", _xlpm.s=0),"Unclassified",IF(SUM(--ISNUMBER(SEARCH(_xlpm.phil, _xlpm.s)))>0, "Y", "N")))} -> N | U27: {=IF(M27="", "Unclassified", IF(AND(SUMPRODUCT(--ISNUMBER(SEARCH(REF_Setup!$B$3:$B$40,M27)))>0,SUMPRODUCT(--ISNUMBER(SEARCH(REF_Setup!$F$3:$F$15,M27)))>0),"Mixed",IF(SUMPRODUCT(--ISNUMBER(SEARCH(REF_Setup!$B$3:$B$40,M27)))>0,"Strategic Only",IF(SUMPRODUCT(--ISNUMBER(SEARCH(REF_Setup!$F$3:$F$15,M27)))>0,"VC Only","Unclassified"))))} -> VC Only
B28: =B27+1 -> 26 | C28: =IFERROR(_xlfn.XLOOKUP($B28,Raw_Data!$A$3:$A$273,Raw_Data!$B$3:$B$273),"") -> Blue Frontier | D28: =IFERROR(_xlfn.XLOOKUP($B28,Raw_Data!$A$3:$A$273,Raw_Data!$C$3:$C$273),"") -> Boca Raton, FL | E28: =IFERROR(_xlfn.XLOOKUP($B28,Raw_Data!$A$3:$A$273,Raw_Data!$D$3:$D$273),"") -> 2017 | F28: =IFERROR(_xlfn.XLOOKUP($B28,Raw_Data!$A$3:$A$273,Raw_Data!$F$3:$F$273),"") -> Buildings | G28: =IFERROR(_xlfn.XLOOKUP($B28,Raw_Data!$A$3:$A$273,Raw_Data!$J$3:$J$273),"") -> 45429 | H28: Series A | I28: =IFERROR(_xlfn.XLOOKUP($B28,Raw_Data!$A$3:$A$273,Raw_Data!$I$3:$I$273),"") -> 47.66 | J28: =IFERROR(_xlfn.XLOOKUP($B28,Raw_Data!$A$3:$A$273,Raw_Data!$L$3:$L$273),"") -> 25.56 | K28: =IFERROR(_xlfn.XLOOKUP($B28,Raw_Data!$A$3:$A$273,Raw_Data!$M$3:$M$273),"") -> 111.18 | L28: =IFERROR(_xlfn.XLOOKUP($B28,Raw_Data!$A$3:$A$273,Raw_Data!$Q$3:$Q$273),"") -> 0 | M28: =IFERROR(_xlfn.XLOOKUP($B28,Raw_Data!$A$3:$A$273,Raw_Data!$R$3:$R$273),"") -> 2150; Breakthrough Energy; Florida Opportunity Fund; Tech Square Ventures; Volo Earth Ventures | N28: {=IF(M28="",0,COUNTA(_xlfn._xlws.FILTER(_xlfn.TEXTSPLIT(M28,";"), _xlfn.TEXTSPLIT(M28,";")<>"")))} -> 5 | O28: =IF(P28>0,"Y","N") -> Y | P28: =IFERROR(_xlfn.XLOOKUP($B28,Raw_Data!$A$3:$A$273,Raw_Data!$V$3:$V$273),"") -> 0.6 | Q28: =IF(R28>0,"Y","N") -> Y | R28: =IFERROR(_xlfn.XLOOKUP($B28,Raw_Data!$A$3:$A$273,Raw_Data!$Y$3:$Y$273),"") -> 0.4 | S28: {=_xlfn.LET(_xlpm.s, Raw_Data!W28,_xlpm.strat, _xlfn._xlws.FILTER(REF_Setup!$B$3:$B$40, REF_Setup!$B$3:$B$40<>""),IF(OR(_xlpm.s="",_xlpm.s=0),"Unclassified",IF(SUM(--ISNUMBER(SEARCH(_xlpm.strat, _xlpm.s)))>0, "Y", "N")) )} -> N | T28: {=_xlfn.LET(_xlpm.s,M28,_xlpm.phil, _xlfn._xlws.FILTER(REF_Setup!$D$3:$D$5, REF_Setup!$D$3:$D$5<>""),IF(OR(_xlpm.s="", _xlpm.s=0),"Unclassified",IF(SUM(--ISNUMBER(SEARCH(_xlpm.phil, _xlpm.s)))>0, "Y", "N")))} -> N | U28: {=IF(M28="", "Unclassified", IF(AND(SUMPRODUCT(--ISNUMBER(SEARCH(REF_Setup!$B$3:$B$40,M28)))>0,SUMPRODUCT(--ISNUMBER(SEARCH(REF_Setup!$F$3:$F$15,M28)))>0),"Mixed",IF(SUMPRODUCT(--ISNUMBER(SEARCH(REF_Setup!$B$3:$B$40,M28)))>0,"Strategic Only",IF(SUMPRODUCT(--ISNUMBER(SEARCH(REF_Setup!$F$3:$F$15,M28)))>0,"VC Only","Unclassified"))))} -> VC Only
B29: =B28+1 -> 27 | C29: =IFERROR(_xlfn.XLOOKUP($B29,Raw_Data!$A$3:$A$273,Raw_Data!$B$3:$B$273),"") -> Brightmark | D29: =IFERROR(_xlfn.XLOOKUP($B29,Raw_Data!$A$3:$A$273,Raw_Data!$C$3:$C$273),"") -> San Francisco, CA | E29: =IFERROR(_xlfn.XLOOKUP($B29,Raw_Data!$A$3:$A$273,Raw_Data!$D$3:$D$273),"") -> 2016 | F29: =IFERROR(_xlfn.XLOOKUP($B29,Raw_Data!$A$3:$A$273,Raw_Data!$F$3:$F$273),"") -> Industrial Decarbonization | G29: =IFERROR(_xlfn.XLOOKUP($B29,Raw_Data!$A$3:$A$273,Raw_Data!$J$3:$J$273),"") -> 42680 | H29: Development capital | I29: =IFERROR(_xlfn.XLOOKUP($B29,Raw_Data!$A$3:$A$273,Raw_Data!$I$3:$I$273),"") -> 250 | J29: =IFERROR(_xlfn.XLOOKUP($B29,Raw_Data!$A$3:$A$273,Raw_Data!$L$3:$L$273),"") -> 250 | K29: =IFERROR(_xlfn.XLOOKUP($B29,Raw_Data!$A$3:$A$273,Raw_Data!$M$3:$M$273),"") -> 0 | L29: =IFERROR(_xlfn.XLOOKUP($B29,Raw_Data!$A$3:$A$273,Raw_Data!$Q$3:$Q$273),"") -> 0 | M29: =IFERROR(_xlfn.XLOOKUP($B29,Raw_Data!$A$3:$A$273,Raw_Data!$R$3:$R$273),"") -> Jackson Investment Group | N29: {=IF(M29="",0,COUNTA(_xlfn._xlws.FILTER(_xlfn.TEXTSPLIT(M29,";"), _xlfn.TEXTSPLIT(M29,";")<>"")))} -> 1 | O29: =IF(P29>0,"Y","N") -> N | P29: =IFERROR(_xlfn.XLOOKUP($B29,Raw_Data!$A$3:$A$273,Raw_Data!$V$3:$V$273),"") -> 0 | Q29: =IF(R29>0,"Y","N") -> Y | R29: =IFERROR(_xlfn.XLOOKUP($B29,Raw_Data!$A$3:$A$273,Raw_Data!$Y$3:$Y$273),"") -> 1 | S29: {=_xlfn.LET(_xlpm.s, Raw_Data!W29,_xlpm.strat, _xlfn._xlws.FILTER(REF_Setup!$B$3:$B$40, REF_Setup!$B$3:$B$40<>""),IF(OR(_xlpm.s="",_xlpm.s=0),"Unclassified",IF(SUM(--ISNUMBER(SEARCH(_xlpm.strat, _xlpm.s)))>0, "Y", "N")) )} -> N | T29: {=_xlfn.LET(_xlpm.s,M29,_xlpm.phil, _xlfn._xlws.FILTER(REF_Setup!$D$3:$D$5, REF_Setup!$D$3:$D$5<>""),IF(OR(_xlpm.s="", _xlpm.s=0),"Unclassified",IF(SUM(--ISNUMBER(SEARCH(_xlpm.phil, _xlpm.s)))>0, "Y", "N")))} -> N | U29: {=IF(M29="", "Unclassified", IF(AND(SUMPRODUCT(--ISNUMBER(SEARCH(REF_Setup!$B$3:$B$40,M29)))>0,SUMPRODUCT(--ISNUMBER(SEARCH(REF_Setup!$F$3:$F$15,M29)))>0),"Mixed",IF(SUMPRODUCT(--ISNUMBER(SEARCH(REF_Setup!$B$3:$B$40,M29)))>0,"Strategic Only",IF(SUMPRODUCT(--ISNUMBER(SEARCH(REF_Setup!$F$3:$F$15,M29)))>0,"VC Only","Unclassified"))))} -> VC Only
B30: =B29+1 -> 28 | C30: =IFERROR(_xlfn.XLOOKUP($B30,Raw_Data!$A$3:$A$273,Raw_Data!$B$3:$B$273),"") -> C-Power | D30: =IFERROR(_xlfn.XLOOKUP($B30,Raw_Data!$A$3:$A$273,Raw_Data!$C$3:$C$273),"") -> Charlottesville, VA | E30: =IFERROR(_xlfn.XLOOKUP($B30,Raw_Data!$A$3:$A$273,Raw_Data!$D$3:$D$273),"") -> 2005 | F30: =IFERROR(_xlfn.XLOOKUP($B30,Raw_Data!$A$3:$A$273,Raw_Data!$F$3:$F$273),"") -> Renewables | G30: =IFERROR(_xlfn.XLOOKUP($B30,Raw_Data!$A$3:$A$273,Raw_Data!$J$3:$J$273),"") -> 44666 | H30: Series B | I30: =IFERROR(_xlfn.XLOOKUP($B30,Raw_Data!$A$3:$A$273,Raw_Data!$I$3:$I$273),"") -> 13.7 | J30: =IFERROR(_xlfn.XLOOKUP($B30,Raw_Data!$A$3:$A$273,Raw_Data!$L$3:$L$273),"") -> 3.5 | K30: =IFERROR(_xlfn.XLOOKUP($B30,Raw_Data!$A$3:$A$273,Raw_Data!$M$3:$M$273),"") -> 48 | L30: =IFERROR(_xlfn.XLOOKUP($B30,Raw_Data!$A$3:$A$273,Raw_Data!$Q$3:$Q$273),"") -> 0 | N30: {=IF(M30="",0,COUNTA(_xlfn._xlws.FILTER(_xlfn.TEXTSPLIT(M30,";"), _xlfn.TEXTSPLIT(M30,";")<>"")))} -> 0 | O30: =IF(P30>0,"Y","N") -> Y | P30: =IFERROR(_xlfn.XLOOKUP($B30,Raw_Data!$A$3:$A$273,Raw_Data!$V$3:$V$273),"") -> N/A | Q30: =IF(R30>0,"Y","N") -> Y | R30: =IFERROR(_xlfn.XLOOKUP($B30,Raw_Data!$A$3:$A$273,Raw_Data!$Y$3:$Y$273),"") -> N/A | S30: {=_xlfn.LET(_xlpm.s, Raw_Data!W30,_xlpm.strat, _xlfn._xlws.FILTER(REF_Setup!$B$3:$B$40, REF_Setup!$B$3:$B$40<>""),IF(OR(_xlpm.s="",_xlpm.s=0),"Unclassified",IF(SUM(--ISNUMBER(SEARCH(_xlpm.strat, _xlpm.s)))>0, "Y", "N")) )} -> Unclassified | T30: {=_xlfn.LET(_xlpm.s,M30,_xlpm.phil, _xlfn._xlws.FILTER(REF_Setup!$D$3:$D$5, REF_Setup!$D$3:$D$5<>""),IF(OR(_xlpm.s="", _xlpm.s=0),"Unclassified",IF(SUM(--ISNUMBER(SEARCH(_xlpm.phil, _xlpm.s)))>0, "Y", "N")))} -> Unclassified | U30: {=IF(M30="", "Unclassified", IF(AND(SUMPRODUCT(--ISNUMBER(SEARCH(REF_Setup!$B$3:$B$40,M30)))>0,SUMPRODUCT(--ISNUMBER(SEARCH(REF_Setup!$F$3:$F$15,M30)))>0),"Mixed",IF(SUMPRODUCT(--ISNUMBER(SEARCH(REF_Setup!$B$3:$B$40,M30)))>0,"Strategic Only",IF(SUMPRODUCT(--ISNUMBER(SEARCH(REF_Setup!$F$3:$F$15,M30)))>0,"VC Only","Unclassified"))))} -> Unclassified
B31: =B30+1 -> 29 | C31: =IFERROR(_xlfn.XLOOKUP($B31,Raw_Data!$A$3:$A$273,Raw_Data!$B$3:$B$273),"") -> Cadenza Innovation | D31: =IFERROR(_xlfn.XLOOKUP($B31,Raw_Data!$A$3:$A$273,Raw_Data!$C$3:$C$273),"") -> Danbury, CT | E31: =IFERROR(_xlfn.XLOOKUP($B31,Raw_Data!$A$3:$A$273,Raw_Data!$D$3:$D$273),"") -> 2012 | F31: =IFERROR(_xlfn.XLOOKUP($B31,Raw_Data!$A$3:$A$273,Raw_Data!$F$3:$F$273),"") -> LDES | G31: =IFERROR(_xlfn.XLOOKUP($B31,Raw_Data!$A$3:$A$273,Raw_Data!$J$3:$J$273),"") -> 43661 | H31: Series A | I31: =IFERROR(_xlfn.XLOOKUP($B31,Raw_Data!$A$3:$A$273,Raw_Data!$I$3:$I$273),"") -> 31.74 | J31: =IFERROR(_xlfn.XLOOKUP($B31,Raw_Data!$A$3:$A$273,Raw_Data!$L$3:$L$273),"") -> 9 | K31: =IFERROR(_xlfn.XLOOKUP($B31,Raw_Data!$A$3:$A$273,Raw_Data!$M$3:$M$273),"") -> 118 | L31: =IFERROR(_xlfn.XLOOKUP($B31,Raw_Data!$A$3:$A$273,Raw_Data!$Q$3:$Q$273),"") -> 0 | M31: =IFERROR(_xlfn.XLOOKUP($B31,Raw_Data!$A$3:$A$273,Raw_Data!$R$3:$R$273),"") -> Connecticut Innovations; Daniel Hagedorn | N31: {=IF(M31="",0,COUNTA(_xlfn._xlws.FILTER(_xlfn.TEXTSPLIT(M31,";"), _xlfn.TEXTSPLIT(M31,";")<>"")))} -> 2 | O31: =IF(P31>0,"Y","N") -> Y | P31: =IFERROR(_xlfn.XLOOKUP($B31,Raw_Data!$A$3:$A$273,Raw_Data!$V$3:$V$273),"") -> 1 | Q31: =IF(R31>0,"Y","N") -> Y | R31: =IFERROR(_xlfn.XLOOKUP($B31,Raw_Data!$A$3:$A$273,Raw_Data!$Y$3:$Y$273),"") -> N/A | S31: {=_xlfn.LET(_xlpm.s, Raw_Data!W31,_xlpm.strat, _xlfn._xlws.FILTER(REF_Setup!$B$3:$B$40, REF_Setup!$B$3:$B$40<>""),IF(OR(_xlpm.s="",_xlpm.s=0),"Unclassified",IF(SUM(--ISNUMBER(SEARCH(_xlpm.strat, _xlpm.s)))>0, "Y", "N")) )} -> Unclassified | T31: {=_xlfn.LET(_xlpm.s,M31,_xlpm.phil, _xlfn._xlws.FILTER(REF_Setup!$D$3:$D$5, REF_Setup!$D$3:$D$5<>""),IF(OR(_xlpm.s="", _xlpm.s=0),"Unclassified",IF(SUM(--ISNUMBER(SEARCH(_xlpm.phil, _xlpm.s)))>0, "Y", "N")))} -> N | U31: {=IF(M31="", "Unclassified", IF(AND(SUMPRODUCT(--ISNUMBER(SEARCH(REF_Setup!$B$3:$B$40,M31)))>0,SUMPRODUCT(--ISNUMBER(SEARCH(REF_Setup!$F$3:$F$15,M31)))>0),"Mixed",IF(SUMPRODUCT(--ISNUMBER(SEARCH(REF_Setup!$B$3:$B$40,M31)))>0,"Strategic Only",IF(SUMPRODUCT(--ISNUMBER(SEARCH(REF_Setup!$F$3:$F$15,M31)))>0,"VC Only","Unclassified"))))} -> Unclassified
B32: =B31+1 -> 30 | C32: =IFERROR(_xlfn.XLOOKUP($B32,Raw_Data!$A$3:$A$273,Raw_Data!$B$3:$B$273),"") -> Caelux | D32: =IFERROR(_xlfn.XLOOKUP($B32,Raw_Data!$A$3:$A$273,Raw_Data!$C$3:$C$273),"") -> Baldwin Park, CA | E32: =IFERROR(_xlfn.XLOOKUP($B32,Raw_Data!$A$3:$A$273,Raw_Data!$D$3:$D$273),"") -> 2014 | F32: =IFERROR(_xlfn.XLOOKUP($B32,Raw_Data!$A$3:$A$273,Raw_Data!$F$3:$F$273),"") -> Renewables | G32: =IFERROR(_xlfn.XLOOKUP($B32,Raw_Data!$A$3:$A$273,Raw_Data!$J$3:$J$273),"") -> 44741 | H32: Series A | I32: =IFERROR(_xlfn.XLOOKUP($B32,Raw_Data!$A$3:$A$273,Raw_Data!$I$3:$I$273),"") -> 18.1 | J32: =IFERROR(_xlfn.XLOOKUP($B32,Raw_Data!$A$3:$A$273,Raw_Data!$L$3:$L$273),"") -> 12 | K32: =IFERROR(_xlfn.XLOOKUP($B32,Raw_Data!$A$3:$A$273,Raw_Data!$M$3:$M$273),"") -> 60 | L32: =IFERROR(_xlfn.XLOOKUP($B32,Raw_Data!$A$3:$A$273,Raw_Data!$Q$3:$Q$273),"") -> 0 | M32: =IFERROR(_xlfn.XLOOKUP($B32,Raw_Data!$A$3:$A$273,Raw_Data!$R$3:$R$273),"") -> Reliance Industries | N32: {=IF(M32="",0,COUNTA(_xlfn._xlws.FILTER(_xlfn.TEXTSPLIT(M32,";"), _xlfn.TEXTSPLIT(M32,";")<>"")))} -> 1 | O32: =IF(P32>0,"Y","N") -> N | P32: =IFERROR(_xlfn.XLOOKUP($B32,Raw_Data!$A$3:$A$273,Raw_Data!$V$3:$V$273),"") -> 0 | Q32: =IF(R32>0,"Y","N") -> Y | R32: =IFERROR(_xlfn.XLOOKUP($B32,Raw_Data!$A$3:$A$273,Raw_Data!$Y$3:$Y$273),"") -> 1 | S32: {=_xlfn.LET(_xlpm.s, Raw_Data!W32,_xlpm.strat, _xlfn._xlws.FILTER(REF_Setup!$B$3:$B$40, REF_Setup!$B$3:$B$40<>""),IF(OR(_xlpm.s="",_xlpm.s=0),"Unclassified",IF(SUM(--ISNUMBER(SEARCH(_xlpm.strat, _xlpm.s)))>0, "Y", "N")) )} -> N | T32: {=_xlfn.LET(_xlpm.s,M32,_xlpm.phil, _xlfn._xlws.FILTER(REF_Setup!$D$3:$D$5, REF_Setup!$D$3:$D$5<>""),IF(OR(_xlpm.s="", _xlpm.s=0),"Unclassified",IF(SUM(--ISNUMBER(SEARCH(_xlpm.phil, _xlpm.s)))>0, "Y", "N")))} -> N | U32: {=IF(M32="", "Unclassified", IF(AND(SUMPRODUCT(--ISNUMBER(SEARCH(REF_Setup!$B$3:$B$40,M32)))>0,SUMPRODUCT(--ISNUMBER(SEARCH(REF_Setup!$F$3:$F$15,M32)))>0),"Mixed",IF(SUMPRODUCT(--ISNUMBER(SEARCH(REF_Setup!$B$3:$B$40,M32)))>0,"Strategic Only",IF(SUMPRODUCT(--ISNUMBER(SEARCH(REF_Setup!$F$3:$F$15,M32)))>0,"VC Only","Unclassified"))))} -> Unclassified
B33: =B32+1 -> 31 | C33: =IFERROR(_xlfn.XLOOKUP($B33,Raw_Data!$A$3:$A$273,Raw_Data!$B$3:$B$273),"") -> Caelux | D33: =IFERROR(_xlfn.XLOOKUP($B33,Raw_Data!$A$3:$A$273,Raw_Data!$C$3:$C$273),"") -> Baldwin Park, CA | E33: =IFERROR(_xlfn.XLOOKUP($B33,Raw_Data!$A$3:$A$273,Raw_Data!$D$3:$D$273),"") -> 2014 | F33: =IFERROR(_xlfn.XLOOKUP($B33,Raw_Data!$A$3:$A$273,Raw_Data!$F$3:$F$273),"") -> Renewables | G33: =IFERROR(_xlfn.XLOOKUP($B33,Raw_Data!$A$3:$A$273,Raw_Data!$J$3:$J$273),"") -> 44833 | H33: Series A | I33: =IFERROR(_xlfn.XLOOKUP($B33,Raw_Data!$A$3:$A$273,Raw_Data!$I$3:$I$273),"") -> 32.1 | J33: =IFERROR(_xlfn.XLOOKUP($B33,Raw_Data!$A$3:$A$273,Raw_Data!$L$3:$L$273),"") -> 14 | K33: =IFERROR(_xlfn.XLOOKUP($B33,Raw_Data!$A$3:$A$273,Raw_Data!$M$3:$M$273),"") -> 60 | L33: =IFERROR(_xlfn.XLOOKUP($B33,Raw_Data!$A$3:$A$273,Raw_Data!$Q$3:$Q$273),"") -> 0 | M33: =IFERROR(_xlfn.XLOOKUP($B33,Raw_Data!$A$3:$A$273,Raw_Data!$R$3:$R$273),"") -> Khosla Ventures | N33: {=IF(M33="",0,COUNTA(_xlfn._xlws.FILTER(_xlfn.TEXTSPLIT(M33,";"), _xlfn.TEXTSPLIT(M33,";")<>"")))} -> 1 | O33: =IF(P33>0,"Y","N") -> Y | P33: =IFERROR(_xlfn.XLOOKUP($B33,Raw_Data!$A$3:$A$273,Raw_Data!$V$3:$V$273),"") -> 1 | Q33: =IF(R33>0,"Y","N") -> Y | R33: =IFERROR(_xlfn.XLOOKUP($B33,Raw_Data!$A$3:$A$273,Raw_Data!$Y$3:$Y$273),"") -> N/A | S33: {=_xlfn.LET(_xlpm.s, Raw_Data!W33,_xlpm.strat, _xlfn._xlws.FILTER(REF_Setup!$B$3:$B$40, REF_Setup!$B$3:$B$40<>""),IF(OR(_xlpm.s="",_xlpm.s=0),"Unclassified",IF(SUM(--ISNUMBER(SEARCH(_xlpm.strat, _xlpm.s)))>0, "Y", "N")) )} -> Unclassified | T33: {=_xlfn.LET(_xlpm.s,M33,_xlpm.phil, _xlfn._xlws.FILTER(REF_Setup!$D$3:$D$5, REF_Setup!$D$3:$D$5<>""),IF(OR(_xlpm.s="", _xlpm.s=0),"Unclassified",IF(SUM(--ISNUMBER(SEARCH(_xlpm.phil, _xlpm.s)))>0, "Y", "N")))} -> N | U33: {=IF(M33="", "Unclassified", IF(AND(SUMPRODUCT(--ISNUMBER(SEARCH(REF_Setup!$B$3:$B$40,M33)))>0,SUMPRODUCT(--ISNUMBER(SEARCH(REF_Setup!$F$3:$F$15,M33)))>0),"Mixed",IF(SUMPRODUCT(--ISNUMBER(SEARCH(REF_Setup!$B$3:$B$40,M33)))>0,"Strategic Only",IF(SUMPRODUCT(--ISNUMBER(SEARCH(REF_Setup!$F$3:$F$15,M33)))>0,"VC Only","Unclassified"))))} -> VC Only
B34: =B33+1 -> 32 | C34: =IFERROR(_xlfn.XLOOKUP($B34,Raw_Data!$A$3:$A$273,Raw_Data!$B$3:$B$273),"") -> Caelux | D34: =IFERROR(_xlfn.XLOOKUP($B34,Raw_Data!$A$3:$A$273,Raw_Data!$C$3:$C$273),"") -> Baldwin Park, CA | E34: =IFERROR(_xlfn.XLOOKUP($B34,Raw_Data!$A$3:$A$273,Raw_Data!$D$3:$D$273),"") -> 2014 | F34: =IFERROR(_xlfn.XLOOKUP($B34,Raw_Data!$A$3:$A$273,Raw_Data!$F$3:$F$273),"") -> Renewables | G34: =IFERROR(_xlfn.XLOOKUP($B34,Raw_Data!$A$3:$A$273,Raw_Data!$J$3:$J$273),"") -> 45141 | H34: Series A | I34: =IFERROR(_xlfn.XLOOKUP($B34,Raw_Data!$A$3:$A$273,Raw_Data!$I$3:$I$273),"") -> 44.1 | J34: =IFERROR(_xlfn.XLOOKUP($B34,Raw_Data!$A$3:$A$273,Raw_Data!$L$3:$L$273),"") -> 12 | K34: =IFERROR(_xlfn.XLOOKUP($B34,Raw_Data!$A$3:$A$273,Raw_Data!$M$3:$M$273),"") -> 95 | L34: =IFERROR(_xlfn.XLOOKUP($B34,Raw_Data!$A$3:$A$273,Raw_Data!$Q$3:$Q$273),"") -> 0 | M34: =IFERROR(_xlfn.XLOOKUP($B34,Raw_Data!$A$3:$A$273,Raw_Data!$R$3:$R$273),"") -> 31 Ventures; F-Prime Capital; Global Brain; Khosla Ventures; Mitsui Fudosan; NextEra Energy; Reliance Industries; Temasek Holdins | N34: {=IF(M34="",0,COUNTA(_xlfn._xlws.FILTER(_xlfn.TEXTSPLIT(M34,";"), _xlfn.TEXTSPLIT(M34,";")<>"")))} -> 8 | O34: =IF(P34>0,"Y","N") -> Y | P34: =IFERROR(_xlfn.XLOOKUP($B34,Raw_Data!$A$3:$A$273,Raw_Data!$V$3:$V$273),"") -> 0.25 | Q34: =IF(R34>0,"Y","N") -> Y | R34: =IFERROR(_xlfn.XLOOKUP($B34,Raw_Data!$A$3:$A$273,Raw_Data!$Y$3:$Y$273),"") -> 0.75 | S34: {=_xlfn.LET(_xlpm.s, Raw_Data!W34,_xlpm.strat, _xlfn._xlws.FILTER(REF_Setup!$B$3:$B$40, REF_Setup!$B$3:$B$40<>""),IF(OR(_xlpm.s="",_xlpm.s=0),"Unclassified",IF(SUM(--ISNUMBER(SEARCH(_xlpm.strat, _xlpm.s)))>0, "Y", "N")) )} -> Y | T34: {=_xlfn.LET(_xlpm.s,M34,_xlpm.phil, _xlfn._xlws.FILTER(REF_Setup!$D$3:$D$5, REF_Setup!$D$3:$D$5<>""),IF(OR(_xlpm.s="", _xlpm.s=0),"Unclassified",IF(SUM(--ISNUMBER(SEARCH(_xlpm.phil, _xlpm.s)))>0, "Y", "N")))} -> N | U34: {=IF(M34="", "Unclassified", IF(AND(SUMPRODUCT(--ISNUMBER(SEARCH(REF_Setup!$B$3:$B$40,M34)))>0,SUMPRODUCT(--ISNUMBER(SEARCH(REF_Setup!$F$3:$F$15,M34)))>0),"Mixed",IF(SUMPRODUCT(--ISNUMBER(SEARCH(REF_Setup!$B$3:$B$40,M34)))>0,"Strategic Only",IF(SUMPRODUCT(--ISNUMBER(SEARCH(REF_Setup!$F$3:$F$15,M34)))>0,"VC Only","Unclassified"))))} -> Mixed
B35: =B34+1 -> 33 | C35: =IFERROR(_xlfn.XLOOKUP($B35,Raw_Data!$A$3:$A$273,Raw_Data!$B$3:$B$273),"") -> Calicat | D35: =IFERROR(_xlfn.XLOOKUP($B35,Raw_Data!$A$3:$A$273,Raw_Data!$C$3:$C$273),"") -> Chatsworth, CA | E35: =IFERROR(_xlfn.XLOOKUP($B35,Raw_Data!$A$3:$A$273,Raw_Data!$D$3:$D$273),"") -> 2021 | F35: =IFERROR(_xlfn.XLOOKUP($B35,Raw_Data!$A$3:$A$273,Raw_Data!$F$3:$F$273),"") -> Hydrogen | G35: =IFERROR(_xlfn.XLOOKUP($B35,Raw_Data!$A$3:$A$273,Raw_Data!$J$3:$J$273),"") -> 45474 | H35: Series A | I35: =IFERROR(_xlfn.XLOOKUP($B35,Raw_Data!$A$3:$A$273,Raw_Data!$I$3:$I$273),"") -> 14 | J35: =IFERROR(_xlfn.XLOOKUP($B35,Raw_Data!$A$3:$A$273,Raw_Data!$L$3:$L$273),"") -> 3 | K35: =IFERROR(_xlfn.XLOOKUP($B35,Raw_Data!$A$3:$A$273,Raw_Data!$M$3:$M$273),"") -> 0 | L35: =IFERROR(_xlfn.XLOOKUP($B35,Raw_Data!$A$3:$A$273,Raw_Data!$Q$3:$Q$273),"") -> 0 | M35: =IFERROR(_xlfn.XLOOKUP($B35,Raw_Data!$A$3:$A$273,Raw_Data!$R$3:$R$273),"") -> Acario Innovation; Dolby Family Ventures; Freeflow Ventures; Hess; Jericho Energy Ventures; MOL Switch; Motus Ventures; Tokyo Gas; TSV Capital; Volo Earth Ventures | N35: {=IF(M35="",0,COUNTA(_xlfn._xlws.FILTER(_xlfn.TEXTSPLIT(M35,";"), _xlfn.TEXTSPLIT(M35,";")<>"")))} -> 10 | O35: =IF(P35>0,"Y","N") -> Y | P35: =IFERROR(_xlfn.XLOOKUP($B35,Raw_Data!$A$3:$A$273,Raw_Data!$V$3:$V$273),"") -> 0.7 | Q35: =IF(R35>0,"Y","N") -> Y | R35: =IFERROR(_xlfn.XLOOKUP($B35,Raw_Data!$A$3:$A$273,Raw_Data!$Y$3:$Y$273),"") -> 0.3 | S35: {=_xlfn.LET(_xlpm.s, Raw_Data!W35,_xlpm.strat, _xlfn._xlws.FILTER(REF_Setup!$B$3:$B$40, REF_Setup!$B$3:$B$40<>""),IF(OR(_xlpm.s="",_xlpm.s=0),"Unclassified",IF(SUM(--ISNUMBER(SEARCH(_xlpm.strat, _xlpm.s)))>0, "Y", "N")) )} -> N | T35: {=_xlfn.LET(_xlpm.s,M35,_xlpm.phil, _xlfn._xlws.FILTER(REF_Setup!$D$3:$D$5, REF_Setup!$D$3:$D$5<>""),IF(OR(_xlpm.s="", _xlpm.s=0),"Unclassified",IF(SUM(--ISNUMBER(SEARCH(_xlpm.phil, _xlpm.s)))>0, "Y", "N")))} -> N | U35: {=IF(M35="", "Unclassified", IF(AND(SUMPRODUCT(--ISNUMBER(SEARCH(REF_Setup!$B$3:$B$40,M35)))>0,SUMPRODUCT(--ISNUMBER(SEARCH(REF_Setup!$F$3:$F$15,M35)))>0),"Mixed",IF(SUMPRODUCT(--ISNUMBER(SEARCH(REF_Setup!$B$3:$B$40,M35)))>0,"Strategic Only",IF(SUMPRODUCT(--ISNUMBER(SEARCH(REF_Setup!$F$3:$F$15,M35)))>0,"VC Only","Unclassified"))))} -> VC Only
B36: =B35+1 -> 34 | C36: =IFERROR(_xlfn.XLOOKUP($B36,Raw_Data!$A$3:$A$273,Raw_Data!$B$3:$B$273),"") -> California Bioenergy | D36: =IFERROR(_xlfn.XLOOKUP($B36,Raw_Data!$A$3:$A$273,Raw_Data!$C$3:$C$273),"") -> Visalia, CA | E36: =IFERROR(_xlfn.XLOOKUP($B36,Raw_Data!$A$3:$A$273,Raw_Data!$D$3:$D$273),"") -> 2006 | F36: =IFERROR(_xlfn.XLOOKUP($B36,Raw_Data!$A$3:$A$273,Raw_Data!$F$3:$F$273),"") -> Renewables | G36: =IFERROR(_xlfn.XLOOKUP($B36,Raw_Data!$A$3:$A$273,Raw_Data!$J$3:$J$273),"") -> 44917 | H36: Development capital | I36: =IFERROR(_xlfn.XLOOKUP($B36,Raw_Data!$A$3:$A$273,Raw_Data!$I$3:$I$273),"") -> 506 | J36: =IFERROR(_xlfn.XLOOKUP($B36,Raw_Data!$A$3:$A$273,Raw_Data!$L$3:$L$273),"") -> 500 | K36: =IFERROR(_xlfn.XLOOKUP($B36,Raw_Data!$A$3:$A$273,Raw_Data!$M$3:$M$273),"") -> 0 | L36: =IFERROR(_xlfn.XLOOKUP($B36,Raw_Data!$A$3:$A$273,Raw_Data!$Q$3:$Q$273),"") -> 0 | M36: =IFERROR(_xlfn.XLOOKUP($B36,Raw_Data!$A$3:$A$273,Raw_Data!$R$3:$R$273),"") -> Brookfield Corporation | N36: {=IF(M36="",0,COUNTA(_xlfn._xlws.FILTER(_xlfn.TEXTSPLIT(M36,";"), _xlfn.TEXTSPLIT(M36,";")<>"")))} -> 1 | O36: =IF(P36>0,"Y","N") -> N | P36: =IFERROR(_xlfn.XLOOKUP($B36,Raw_Data!$A$3:$A$273,Raw_Data!$V$3:$V$273),"") -> 0 | Q36: =IF(R36>0,"Y","N") -> Y | R36: =IFERROR(_xlfn.XLOOKUP($B36,Raw_Data!$A$3:$A$273,Raw_Data!$Y$3:$Y$273),"") -> 1 | S36: {=_xlfn.LET(_xlpm.s, Raw_Data!W36,_xlpm.strat, _xlfn._xlws.FILTER(REF_Setup!$B$3:$B$40, REF_Setup!$B$3:$B$40<>""),IF(OR(_xlpm.s="",_xlpm.s=0),"Unclassified",IF(SUM(--ISNUMBER(SEARCH(_xlpm.strat, _xlpm.s)))>0, "Y", "N")) )} -> N | T36: {=_xlfn.LET(_xlpm.s,M36,_xlpm.phil, _xlfn._xlws.FILTER(REF_Setup!$D$3:$D$5, REF_Setup!$D$3:$D$5<>""),IF(OR(_xlpm.s="", _xlpm.s=0),"Unclassified",IF(SUM(--ISNUMBER(SEARCH(_xlpm.phil, _xlpm.s)))>0, "Y", "N")))} -> N | U36: {=IF(M36="", "Unclassified", IF(AND(SUMPRODUCT(--ISNUMBER(SEARCH(REF_Setup!$B$3:$B$40,M36)))>0,SUMPRODUCT(--ISNUMBER(SEARCH(REF_Setup!$F$3:$F$15,M36)))>0),"Mixed",IF(SUMPRODUCT(--ISNUMBER(SEARCH(REF_Setup!$B$3:$B$40,M36)))>0,"Strategic Only",IF(SUMPRODUCT(--ISNUMBER(SEARCH(REF_Setup!$F$3:$F$15,M36)))>0,"VC Only","Unclassified"))))} -> Unclassified
B37: =B36+1 -> 35 | C37: =IFERROR(_xlfn.XLOOKUP($B37,Raw_Data!$A$3:$A$273,Raw_Data!$B$3:$B$273),"") -> California Bioenergy | D37: =IFERROR(_xlfn.XLOOKUP($B37,Raw_Data!$A$3:$A$273,Raw_Data!$C$3:$C$273),"") -> Visalia, CA | E37: =IFERROR(_xlfn.XLOOKUP($B37,Raw_Data!$A$3:$A$273,Raw_Data!$D$3:$D$273),"") -> 2006 | F37: =IFERROR(_xlfn.XLOOKUP($B37,Raw_Data!$A$3:$A$273,Raw_Data!$F$3:$F$273),"") -> Renewables | G37: =IFERROR(_xlfn.XLOOKUP($B37,Raw_Data!$A$3:$A$273,Raw_Data!$J$3:$J$273),"") -> 45536 | H37: Development capital | I37: =IFERROR(_xlfn.XLOOKUP($B37,Raw_Data!$A$3:$A$273,Raw_Data!$I$3:$I$273),"") -> 506 | J37: =IFERROR(_xlfn.XLOOKUP($B37,Raw_Data!$A$3:$A$273,Raw_Data!$L$3:$L$273),"") -> 0 | K37: =IFERROR(_xlfn.XLOOKUP($B37,Raw_Data!$A$3:$A$273,Raw_Data!$M$3:$M$273),"") -> 0 | L37: =IFERROR(_xlfn.XLOOKUP($B37,Raw_Data!$A$3:$A$273,Raw_Data!$Q$3:$Q$273),"") -> N/A | M37: =IFERROR(_xlfn.XLOOKUP($B37,Raw_Data!$A$3:$A$273,Raw_Data!$R$3:$R$273),"") -> Broadscale Group | N37: {=IF(M37="",0,COUNTA(_xlfn._xlws.FILTER(_xlfn.TEXTSPLIT(M37,";"), _xlfn.TEXTSPLIT(M37,";")<>"")))} -> 1 | O37: =IF(P37>0,"Y","N") -> N | P37: =IFERROR(_xlfn.XLOOKUP($B37,Raw_Data!$A$3:$A$273,Raw_Data!$V$3:$V$273),"") -> 0 | Q37: =IF(R37>0,"Y","N") -> Y | R37: =IFERROR(_xlfn.XLOOKUP($B37,Raw_Data!$A$3:$A$273,Raw_Data!$Y$3:$Y$273),"") -> 1 | S37: {=_xlfn.LET(_xlpm.s, Raw_Data!W37,_xlpm.strat, _xlfn._xlws.FILTER(REF_Setup!$B$3:$B$40, REF_Setup!$B$3:$B$40<>""),IF(OR(_xlpm.s="",_xlpm.s=0),"Unclassified",IF(SUM(--ISNUMBER(SEARCH(_xlpm.strat, _xlpm.s)))>0, "Y", "N")) )} -> N | T37: {=_xlfn.LET(_xlpm.s,M37,_xlpm.phil, _xlfn._xlws.FILTER(REF_Setup!$D$3:$D$5, REF_Setup!$D$3:$D$5<>""),IF(OR(_xlpm.s="", _xlpm.s=0),"Unclassified",IF(SUM(--ISNUMBER(SEARCH(_xlpm.phil, _xlpm.s)))>0, "Y", "N")))} -> N | U37: {=IF(M37="", "Unclassified", IF(AND(SUMPRODUCT(--ISNUMBER(SEARCH(REF_Setup!$B$3:$B$40,M37)))>0,SUMPRODUCT(--ISNUMBER(SEARCH(REF_Setup!$F$3:$F$15,M37)))>0),"Mixed",IF(SUMPRODUCT(--ISNUMBER(SEARCH(REF_Setup!$B$3:$B$40,M37)))>0,"Strategic Only",IF(SUMPRODUCT(--ISNUMBER(SEARCH(REF_Setup!$F$3:$F$15,M37)))>0,"VC Only","Unclassified"))))} -> VC Only
B38: =B37+1 -> 36 | C38: =IFERROR(_xlfn.XLOOKUP($B38,Raw_Data!$A$3:$A$273,Raw_Data!$B$3:$B$273),"") -> Cambrian Innovation | D38: =IFERROR(_xlfn.XLOOKUP($B38,Raw_Data!$A$3:$A$273,Raw_Data!$C$3:$C$273),"") -> Wa tertown MA | E38: =IFERROR(_xlfn.XLOOKUP($B38,Raw_Data!$A$3:$A$273,Raw_Data!$D$3:$D$273),"") -> 2006 | F38: =IFERROR(_xlfn.XLOOKUP($B38,Raw_Data!$A$3:$A$273,Raw_Data!$F$3:$F$273),"") -> Industrial Decarbonization | G38: =IFERROR(_xlfn.XLOOKUP($B38,Raw_Data!$A$3:$A$273,Raw_Data!$J$3:$J$273),"") -> 42548 | H38: Series A | I38: =IFERROR(_xlfn.XLOOKUP($B38,Raw_Data!$A$3:$A$273,Raw_Data!$I$3:$I$273),"") -> 10.59 | J38: =IFERROR(_xlfn.XLOOKUP($B38,Raw_Data!$A$3:$A$273,Raw_Data!$L$3:$L$273),"") -> 6.7 | K38: =IFERROR(_xlfn.XLOOKUP($B38,Raw_Data!$A$3:$A$273,Raw_Data!$M$3:$M$273),"") -> 19.7 | L38: =IFERROR(_xlfn.XLOOKUP($B38,Raw_Data!$A$3:$A$273,Raw_Data!$Q$3:$Q$273),"") -> 0.74626866 | M38: =IFERROR(_xlfn.XLOOKUP($B38,Raw_Data!$A$3:$A$273,Raw_Data!$R$3:$R$273),"") -> Rijn Capital | N38: {=IF(M38="",0,COUNTA(_xlfn._xlws.FILTER(_xlfn.TEXTSPLIT(M38,";"), _xlfn.TEXTSPLIT(M38,";")<>"")))} -> 1 | O38: =IF(P38>0,"Y","N") -> N | P38: =IFERROR(_xlfn.XLOOKUP($B38,Raw_Data!$A$3:$A$273,Raw_Data!$V$3:$V$273),"") -> 0 | Q38: =IF(R38>0,"Y","N") -> Y | R38: =IFERROR(_xlfn.XLOOKUP($B38,Raw_Data!$A$3:$A$273,Raw_Data!$Y$3:$Y$273),"") -> 1 | S38: {=_xlfn.LET(_xlpm.s, Raw_Data!W38,_xlpm.strat, _xlfn._xlws.FILTER(REF_Setup!$B$3:$B$40, REF_Setup!$B$3:$B$40<>""),IF(OR(_xlpm.s="",_xlpm.s=0),"Unclassified",IF(SUM(--ISNUMBER(SEARCH(_xlpm.strat, _xlpm.s)))>0, "Y", "N")) )} -> N | T38: {=_xlfn.LET(_xlpm.s,M38,_xlpm.phil, _xlfn._xlws.FILTER(REF_Setup!$D$3:$D$5, REF_Setup!$D$3:$D$5<>""),IF(OR(_xlpm.s="", _xlpm.s=0),"Unclassified",IF(SUM(--ISNUMBER(SEARCH(_xlpm.phil, _xlpm.s)))>0, "Y", "N")))} -> N | U38: {=IF(M38="", "Unclassified", IF(AND(SUMPRODUCT(--ISNUMBER(SEARCH(REF_Setup!$B$3:$B$40,M38)))>0,SUMPRODUCT(--ISNUMBER(SEARCH(REF_Setup!$F$3:$F$15,M38)))>0),"Mixed",IF(SUMPRODUCT(--ISNUMBER(SEARCH(REF_Setup!$B$3:$B$40,M38)))>0,"Strategic Only",IF(SUMPRODUCT(--ISNUMBER(SEARCH(REF_Setup!$F$3:$F$15,M38)))>0,"VC Only","Unclassified"))))} -> VC Only
B39: =B38+1 -> 37 | C39: =IFERROR(_xlfn.XLOOKUP($B39,Raw_Data!$A$3:$A$273,Raw_Data!$B$3:$B$273),"") -> Cambrian Innovation | D39: =IFERROR(_xlfn.XLOOKUP($B39,Raw_Data!$A$3:$A$273,Raw_Data!$C$3:$C$273),"") -> Wa tertown MA | E39: =IFERROR(_xlfn.XLOOKUP($B39,Raw_Data!$A$3:$A$273,Raw_Data!$D$3:$D$273),"") -> 2006 | F39: =IFERROR(_xlfn.XLOOKUP($B39,Raw_Data!$A$3:$A$273,Raw_Data!$F$3:$F$273),"") -> Industrial Decarbonization | G39: =IFERROR(_xlfn.XLOOKUP($B39,Raw_Data!$A$3:$A$273,Raw_Data!$J$3:$J$273),"") -> 43753 | H39: Series B | I39: =IFERROR(_xlfn.XLOOKUP($B39,Raw_Data!$A$3:$A$273,Raw_Data!$I$3:$I$273),"") -> 25.78 | J39: =IFERROR(_xlfn.XLOOKUP($B39,Raw_Data!$A$3:$A$273,Raw_Data!$L$3:$L$273),"") -> 3 | K39: =IFERROR(_xlfn.XLOOKUP($B39,Raw_Data!$A$3:$A$273,Raw_Data!$M$3:$M$273),"") -> 53 | L39: =IFERROR(_xlfn.XLOOKUP($B39,Raw_Data!$A$3:$A$273,Raw_Data!$Q$3:$Q$273),"") -> 0 | M39: =IFERROR(_xlfn.XLOOKUP($B39,Raw_Data!$A$3:$A$273,Raw_Data!$R$3:$R$273),"") -> Spring Lane Capital | N39: {=IF(M39="",0,COUNTA(_xlfn._xlws.FILTER(_xlfn.TEXTSPLIT(M39,";"), _xlfn.TEXTSPLIT(M39,";")<>"")))} -> 1 | O39: =IF(P39>0,"Y","N") -> Y | P39: =IFERROR(_xlfn.XLOOKUP($B39,Raw_Data!$A$3:$A$273,Raw_Data!$V$3:$V$273),"") -> 1 | Q39: =IF(R39>0,"Y","N") -> Y | R39: =IFERROR(_xlfn.XLOOKUP($B39,Raw_Data!$A$3:$A$273,Raw_Data!$Y$3:$Y$273),"") -> 1 | S39: {=_xlfn.LET(_xlpm.s, Raw_Data!W39,_xlpm.strat, _xlfn._xlws.FILTER(REF_Setup!$B$3:$B$40, REF_Setup!$B$3:$B$40<>""),IF(OR(_xlpm.s="",_xlpm.s=0),"Unclassified",IF(SUM(--ISNUMBER(SEARCH(_xlpm.strat, _xlpm.s)))>0, "Y", "N")) )} -> N | T39: {=_xlfn.LET(_xlpm.s,M39,_xlpm.phil, _xlfn._xlws.FILTER(REF_Setup!$D$3:$D$5, REF_Setup!$D$3:$D$5<>""),IF(OR(_xlpm.s="", _xlpm.s=0),"Unclassified",IF(SUM(--ISNUMBER(SEARCH(_xlpm.phil, _xlpm.s)))>0, "Y", "N")))} -> N | U39: {=IF(M39="", "Unclassified", IF(AND(SUMPRODUCT(--ISNUMBER(SEARCH(REF_Setup!$B$3:$B$40,M39)))>0,SUMPRODUCT(--ISNUMBER(SEARCH(REF_Setup!$F$3:$F$15,M39)))>0),"Mixed",IF(SUMPRODUCT(--ISNUMBER(SEARCH(REF_Setup!$B$3:$B$40,M39)))>0,"Strategic Only",IF(SUMPRODUCT(--ISNUMBER(SEARCH(REF_Setup!$F$3:$F$15,M39)))>0,"VC Only","Unclassified"))))} -> VC Only
B40: =B39+1 -> 38 | C40: =IFERROR(_xlfn.XLOOKUP($B40,Raw_Data!$A$3:$A$273,Raw_Data!$B$3:$B$273),"") -> Capacitech Energy | D40: =IFERROR(_xlfn.XLOOKUP($B40,Raw_Data!$A$3:$A$273,Raw_Data!$C$3:$C$273),"") -> Orlando, FL | E40: =IFERROR(_xlfn.XLOOKUP($B40,Raw_Data!$A$3:$A$273,Raw_Data!$D$3:$D$273),"") -> 0 | F40: =IFERROR(_xlfn.XLOOKUP($B40,Raw_Data!$A$3:$A$273,Raw_Data!$F$3:$F$273),"") -> LDES | G40: =IFERROR(_xlfn.XLOOKUP($B40,Raw_Data!$A$3:$A$273,Raw_Data!$J$3:$J$273),"") -> 43895 | H40: Series A | I40: =IFERROR(_xlfn.XLOOKUP($B40,Raw_Data!$A$3:$A$273,Raw_Data!$I$3:$I$273),"") -> 1.12 | J40: =IFERROR(_xlfn.XLOOKUP($B40,Raw_Data!$A$3:$A$273,Raw_Data!$L$3:$L$273),"") -> 1 | K40: =IFERROR(_xlfn.XLOOKUP($B40,Raw_Data!$A$3:$A$273,Raw_Data!$M$3:$M$273),"") -> 4 | L40: =IFERROR(_xlfn.XLOOKUP($B40,Raw_Data!$A$3:$A$273,Raw_Data!$Q$3:$Q$273),"") -> 0 | M40: =IFERROR(_xlfn.XLOOKUP($B40,Raw_Data!$A$3:$A$273,Raw_Data!$R$3:$R$273),"") -> Beresford Ventures; Flobas Ventures; Icebook Investments; New World Angels; Westlake Ventures | N40: {=IF(M40="",0,COUNTA(_xlfn._xlws.FILTER(_xlfn.TEXTSPLIT(M40,";"), _xlfn.TEXTSPLIT(M40,";")<>"")))} -> 5 | O40: =IF(P40>0,"Y","N") -> N | P40: =IFERROR(_xlfn.XLOOKUP($B40,Raw_Data!$A$3:$A$273,Raw_Data!$V$3:$V$273),"") -> 0 | Q40: =IF(R40>0,"Y","N") -> Y | R40: =IFERROR(_xlfn.XLOOKUP($B40,Raw_Data!$A$3:$A$273,Raw_Data!$Y$3:$Y$273),"") -> 1 | S40: {=_xlfn.LET(_xlpm.s, Raw_Data!W40,_xlpm.strat, _xlfn._xlws.FILTER(REF_Setup!$B$3:$B$40, REF_Setup!$B$3:$B$40<>""),IF(OR(_xlpm.s="",_xlpm.s=0),"Unclassified",IF(SUM(--ISNUMBER(SEARCH(_xlpm.strat, _xlpm.s)))>0, "Y", "N")) )} -> N | T40: {=_xlfn.LET(_xlpm.s,M40,_xlpm.phil, _xlfn._xlws.FILTER(REF_Setup!$D$3:$D$5, REF_Setup!$D$3:$D$5<>""),IF(OR(_xlpm.s="", _xlpm.s=0),"Unclassified",IF(SUM(--ISNUMBER(SEARCH(_xlpm.phil, _xlpm.s)))>0, "Y", "N")))} -> N | U40: {=IF(M40="", "Unclassified", IF(AND(SUMPRODUCT(--ISNUMBER(SEARCH(REF_Setup!$B$3:$B$40,M40)))>0,SUMPRODUCT(--ISNUMBER(SEARCH(REF_Setup!$F$3:$F$15,M40)))>0),"Mixed",IF(SUMPRODUCT(--ISNUMBER(SEARCH(REF_Setup!$B$3:$B$40,M40)))>0,"Strategic Only",IF(SUMPRODUCT(--ISNUMBER(SEARCH(REF_Setup!$F$3:$F$15,M40)))>0,"VC Only","Unclassified"))))} -> VC Only
B41: =B40+1 -> 39 | C41: =IFERROR(_xlfn.XLOOKUP($B41,Raw_Data!$A$3:$A$273,Raw_Data!$B$3:$B$273),"") -> Capacitech Energy | D41: =IFERROR(_xlfn.XLOOKUP($B41,Raw_Data!$A$3:$A$273,Raw_Data!$C$3:$C$273),"") -> Orlando, FL | E41: =IFERROR(_xlfn.XLOOKUP($B41,Raw_Data!$A$3:$A$273,Raw_Data!$D$3:$D$273),"") -> 0 | F41: =IFERROR(_xlfn.XLOOKUP($B41,Raw_Data!$A$3:$A$273,Raw_Data!$F$3:$F$273),"") -> LDES | G41: =IFERROR(_xlfn.XLOOKUP($B41,Raw_Data!$A$3:$A$273,Raw_Data!$J$3:$J$273),"") -> 43565 | H41: Series A | I41: =IFERROR(_xlfn.XLOOKUP($B41,Raw_Data!$A$3:$A$273,Raw_Data!$I$3:$I$273),"") -> 0.12 | J41: =IFERROR(_xlfn.XLOOKUP($B41,Raw_Data!$A$3:$A$273,Raw_Data!$L$3:$L$273),"") -> 0.08 | K41: =IFERROR(_xlfn.XLOOKUP($B41,Raw_Data!$A$3:$A$273,Raw_Data!$M$3:$M$273),"") -> 1.5 | L41: =IFERROR(_xlfn.XLOOKUP($B41,Raw_Data!$A$3:$A$273,Raw_Data!$Q$3:$Q$273),"") -> 0 | M41: =IFERROR(_xlfn.XLOOKUP($B41,Raw_Data!$A$3:$A$273,Raw_Data!$R$3:$R$273),"") -> Icebook Investments; Varnadore Financial | N41: {=IF(M41="",0,COUNTA(_xlfn._xlws.FILTER(_xlfn.TEXTSPLIT(M41,";"), _xlfn.TEXTSPLIT(M41,";")<>"")))} -> 2 | O41: =IF(P41>0,"Y","N") -> N | P41: =IFERROR(_xlfn.XLOOKUP($B41,Raw_Data!$A$3:$A$273,Raw_Data!$V$3:$V$273),"") -> 0 | Q41: =IF(R41>0,"Y","N") -> Y | R41: =IFERROR(_xlfn.XLOOKUP($B41,Raw_Data!$A$3:$A$273,Raw_Data!$Y$3:$Y$273),"") -> 1 | S41: {=_xlfn.LET(_xlpm.s, Raw_Data!W41,_xlpm.strat, _xlfn._xlws.FILTER(REF_Setup!$B$3:$B$40, REF_Setup!$B$3:$B$40<>""),IF(OR(_xlpm.s="",_xlpm.s=0),"Unclassified",IF(SUM(--ISNUMBER(SEARCH(_xlpm.strat, _xlpm.s)))>0, "Y", "N")) )} -> N | T41: {=_xlfn.LET(_xlpm.s,M41,_xlpm.phil, _xlfn._xlws.FILTER(REF_Setup!$D$3:$D$5, REF_Setup!$D$3:$D$5<>""),IF(OR(_xlpm.s="", _xlpm.s=0),"Unclassified",IF(SUM(--ISNUMBER(SEARCH(_xlpm.phil, _xlpm.s)))>0, "Y", "N")))} -> N | U41: {=IF(M41="", "Unclassified", IF(AND(SUMPRODUCT(--ISNUMBER(SEARCH(REF_Setup!$B$3:$B$40,M41)))>0,SUMPRODUCT(--ISNUMBER(SEARCH(REF_Setup!$F$3:$F$15,M41)))>0),"Mixed",IF(SUMPRODUCT(--ISNUMBER(SEARCH(REF_Setup!$B$3:$B$40,M41)))>0,"Strategic Only",IF(SUMPRODUCT(--ISNUMBER(SEARCH(REF_Setup!$F$3:$F$15,M41)))>0,"VC Only","Unclassified"))))} -> Unclassified
B42: =B41+1 -> 40 | C42: =IFERROR(_xlfn.XLOOKUP($B42,Raw_Data!$A$3:$A$273,Raw_Data!$B$3:$B$273),"") -> Charm Industrial | D42: =IFERROR(_xlfn.XLOOKUP($B42,Raw_Data!$A$3:$A$273,Raw_Data!$C$3:$C$273),"") -> San Francisco, CA | E42: =IFERROR(_xlfn.XLOOKUP($B42,Raw_Data!$A$3:$A$273,Raw_Data!$D$3:$D$273),"") -> 2018 | F42: =IFERROR(_xlfn.XLOOKUP($B42,Raw_Data!$A$3:$A$273,Raw_Data!$F$3:$F$273),"") -> CDR | G42: =IFERROR(_xlfn.XLOOKUP($B42,Raw_Data!$A$3:$A$273,Raw_Data!$J$3:$J$273),"") -> 43594 | H42: Seed | I42: =IFERROR(_xlfn.XLOOKUP($B42,Raw_Data!$A$3:$A$273,Raw_Data!$I$3:$I$273),"") -> 3.5 | J42: =IFERROR(_xlfn.XLOOKUP($B42,Raw_Data!$A$3:$A$273,Raw_Data!$L$3:$L$273),"") -> 3.5 | K42: =IFERROR(_xlfn.XLOOKUP($B42,Raw_Data!$A$3:$A$273,Raw_Data!$M$3:$M$273),"") -> 21.5 | L42: =IFERROR(_xlfn.XLOOKUP($B42,Raw_Data!$A$3:$A$273,Raw_Data!$Q$3:$Q$273),"") -> 0 | M42: =IFERROR(_xlfn.XLOOKUP($B42,Raw_Data!$A$3:$A$273,Raw_Data!$R$3:$R$273),"") -> David Ulevitch; Incite Ventures; James Tamplin; Lowercarbon Capital; Nat Friedman; Peter Reinhardt; Stripe; Thomas Mvlnerney; Valor Equity Partners | N42: {=IF(M42="",0,COUNTA(_xlfn._xlws.FILTER(_xlfn.TEXTSPLIT(M42,";"), _xlfn.TEXTSPLIT(M42,";")<>"")))} -> 9 | O42: =IF(P42>0,"Y","N") -> N | P42: =IFERROR(_xlfn.XLOOKUP($B42,Raw_Data!$A$3:$A$273,Raw_Data!$V$3:$V$273),"") -> 0 | Q42: =IF(R42>0,"Y","N") -> Y | R42: =IFERROR(_xlfn.XLOOKUP($B42,Raw_Data!$A$3:$A$273,Raw_Data!$Y$3:$Y$273),"") -> 1 | S42: {=_xlfn.LET(_xlpm.s, Raw_Data!W42,_xlpm.strat, _xlfn._xlws.FILTER(REF_Setup!$B$3:$B$40, REF_Setup!$B$3:$B$40<>""),IF(OR(_xlpm.s="",_xlpm.s=0),"Unclassified",IF(SUM(--ISNUMBER(SEARCH(_xlpm.strat, _xlpm.s)))>0, "Y", "N")) )} -> N | T42: {=_xlfn.LET(_xlpm.s,M42,_xlpm.phil, _xlfn._xlws.FILTER(REF_Setup!$D$3:$D$5, REF_Setup!$D$3:$D$5<>""),IF(OR(_xlpm.s="", _xlpm.s=0),"Unclassified",IF(SUM(--ISNUMBER(SEARCH(_xlpm.phil, _xlpm.s)))>0, "Y", "N")))} -> N | U42: {=IF(M42="", "Unclassified", IF(AND(SUMPRODUCT(--ISNUMBER(SEARCH(REF_Setup!$B$3:$B$40,M42)))>0,SUMPRODUCT(--ISNUMBER(SEARCH(REF_Setup!$F$3:$F$15,M42)))>0),"Mixed",IF(SUMPRODUCT(--ISNUMBER(SEARCH(REF_Setup!$B$3:$B$40,M42)))>0,"Strategic Only",IF(SUMPRODUCT(--ISNUMBER(SEARCH(REF_Setup!$F$3:$F$15,M42)))>0,"VC Only","Unclassified"))))} -> VC Only
... B49: =B48+1 -> 47 | C49: =IFERROR(_xlfn.XLOOKUP($B49,Raw_Data!$A$3:$A$273,Raw_Data!$B$3:$B$273),"") -> Clean Hydrogen Technologies | D49: =IFERROR(_xlfn.XLOOKUP($B49,Raw_Data!$A$3:$A$273,Raw_Data!$C$3:$C$273),"") -> New York, NY | E49: =IFERROR(_xlfn.XLOOKUP($B49,Raw_Data!$A$3:$A$273,Raw_Data!$D$3:$D$273),"") -> 2021 | F49: =IFERROR(_xlfn.XLOOKUP($B49,Raw_Data!$A$3:$A$273,Raw_Data!$F$3:$F$273),"") -> Hydrogen | G49: =IFERROR(_xlfn.XLOOKUP($B49,Raw_Data!$A$3:$A$273,Raw_Data!$J$3:$J$273),"") -> 44531 | H49: Development capital | I49: =IFERROR(_xlfn.XLOOKUP($B49,Raw_Data!$A$3:$A$273,Raw_Data!$I$3:$I$273),"") -> 0.68 | J49: =IFERROR(_xlfn.XLOOKUP($B49,Raw_Data!$A$3:$A$273,Raw_Data!$L$3:$L$273),"") -> 0.68 | K49: =IFERROR(_xlfn.XLOOKUP($B49,Raw_Data!$A$3:$A$273,Raw_Data!$M$3:$M$273),"") -> 4.18 | L49: =IFERROR(_xlfn.XLOOKUP($B49,Raw_Data!$A$3:$A$273,Raw_Data!$Q$3:$Q$273),"") -> 0 | M49: =IFERROR(_xlfn.XLOOKUP($B49,Raw_Data!$A$3:$A$273,Raw_Data!$R$3:$R$273),"") -> BPH Energy | N49: {=IF(M49="",0,COUNTA(_xlfn._xlws.FILTER(_xlfn.TEXTSPLIT(M49,";"), _xlfn.TEXTSPLIT(M49,";")<>"")))} -> 1 | O49: =IF(P49>0,"Y","N") -> N | P49: =IFERROR(_xlfn.XLOOKUP($B49,Raw_Data!$A$3:$A$273,Raw_Data!$V$3:$V$273),"") -> 0 | Q49: =IF(R49>0,"Y","N") -> Y | R49: =IFERROR(_xlfn.XLOOKUP($B49,Raw_Data!$A$3:$A$273,Raw_Data!$Y$3:$Y$273),"") -> 1 | S49: {=_xlfn.LET(_xlpm.s, Raw_Data!W49,_xlpm.strat, _xlfn._xlws.FILTER(REF_Setup!$B$3:$B$40, REF_Setup!$B$3:$B$40<>""),IF(OR(_xlpm.s="",_xlpm.s=0),"Unclassified",IF(SUM(--ISNUMBER(SEARCH(_xlpm.strat, _xlpm.s)))>0, "Y", "N")) )} -> N | T49: {=_xlfn.LET(_xlpm.s,M49,_xlpm.phil, _xlfn._xlws.FILTER(REF_Setup!$D$3:$D$5, REF_Setup!$D$3:$D$5<>""),IF(OR(_xlpm.s="", _xlpm.s=0),"Unclassified",IF(SUM(--ISNUMBER(SEARCH(_xlpm.phil, _xlpm.s)))>0, "Y", "N")))} -> N | U49: {=IF(M49="", "Unclassified", IF(AND(SUMPRODUCT(--ISNUMBER(SEARCH(REF_Setup!$B$3:$B$40,M49)))>0,SUMPRODUCT(--ISNUMBER(SEARCH(REF_Setup!$F$3:$F$15,M49)))>0),"Mixed",IF(SUMPRODUCT(--ISNUMBER(SEARCH(REF_Setup!$B$3:$B$40,M49)))>0,"Strategic Only",IF(SUMPRODUCT(--ISNUMBER(SEARCH(REF_Setup!$F$3:$F$15,M49)))>0,"VC Only","Unclassified"))))} -> Unclassified
B50: =B49+1 -> 48 | C50: =IFERROR(_xlfn.XLOOKUP($B50,Raw_Data!$A$3:$A$273,Raw_Data!$B$3:$B$273),"") -> Clean Hydrogen Technologies | D50: =IFERROR(_xlfn.XLOOKUP($B50,Raw_Data!$A$3:$A$273,Raw_Data!$C$3:$C$273),"") -> New York, NY | E50: =IFERROR(_xlfn.XLOOKUP($B50,Raw_Data!$A$3:$A$273,Raw_Data!$D$3:$D$273),"") -> 2021 | F50: =IFERROR(_xlfn.XLOOKUP($B50,Raw_Data!$A$3:$A$273,Raw_Data!$F$3:$F$273),"") -> Hydrogen | G50: =IFERROR(_xlfn.XLOOKUP($B50,Raw_Data!$A$3:$A$273,Raw_Data!$J$3:$J$273),"") -> 45596 | H50: Development capital | I50: =IFERROR(_xlfn.XLOOKUP($B50,Raw_Data!$A$3:$A$273,Raw_Data!$I$3:$I$273),"") -> 16.88 | J50: =IFERROR(_xlfn.XLOOKUP($B50,Raw_Data!$A$3:$A$273,Raw_Data!$L$3:$L$273),"") -> 16.2 | K50: =IFERROR(_xlfn.XLOOKUP($B50,Raw_Data!$A$3:$A$273,Raw_Data!$M$3:$M$273),"") -> 38.88 | L50: =IFERROR(_xlfn.XLOOKUP($B50,Raw_Data!$A$3:$A$273,Raw_Data!$Q$3:$Q$273),"") -> 0.6 | N50: {=IF(M50="",0,COUNTA(_xlfn._xlws.FILTER(_xlfn.TEXTSPLIT(M50,";"), _xlfn.TEXTSPLIT(M50,";")<>"")))} -> 0 | O50: =IF(P50>0,"Y","N") -> Y | P50: =IFERROR(_xlfn.XLOOKUP($B50,Raw_Data!$A$3:$A$273,Raw_Data!$V$3:$V$273),"") -> N/A | Q50: =IF(R50>0,"Y","N") -> Y | R50: =IFERROR(_xlfn.XLOOKUP($B50,Raw_Data!$A$3:$A$273,Raw_Data!$Y$3:$Y$273),"") -> N/A | S50: {=_xlfn.LET(_xlpm.s, Raw_Data!W50,_xlpm.strat, _xlfn._xlws.FILTER(REF_Setup!$B$3:$B$40, REF_Setup!$B$3:$B$40<>""),IF(OR(_xlpm.s="",_xlpm.s=0),"Unclassified",IF(SUM(--ISNUMBER(SEARCH(_xlpm.strat, _xlpm.s)))>0, "Y", "N")) )} -> Unclassified | T50: {=_xlfn.LET(_xlpm.s,M50,_xlpm.phil, _xlfn._xlws.FILTER(REF_Setup!$D$3:$D$5, REF_Setup!$D$3:$D$5<>""),IF(OR(_xlpm.s="", _xlpm.s=0),"Unclassified",IF(SUM(--ISNUMBER(SEARCH(_xlpm.phil, _xlpm.s)))>0, "Y", "N")))} -> Unclassified | U50: {=IF(M50="", "Unclassified", IF(AND(SUMPRODUCT(--ISNUMBER(SEARCH(REF_Setup!$B$3:$B$40,M50)))>0,SUMPRODUCT(--ISNUMBER(SEARCH(REF_Setup!$F$3:$F$15,M50)))>0),"Mixed",IF(SUMPRODUCT(--ISNUMBER(SEARCH(REF_Setup!$B$3:$B$40,M50)))>0,"Strategic Only",IF(SUMPRODUCT(--ISNUMBER(SEARCH(REF_Setup!$F$3:$F$15,M50)))>0,"VC Only","Unclassified"))))} -> Unclassified
B51: =B50+1 -> 49 | C51: =IFERROR(_xlfn.XLOOKUP($B51,Raw_Data!$A$3:$A$273,Raw_Data!$B$3:$B$273),"") -> Clean Fiber | D51: =IFERROR(_xlfn.XLOOKUP($B51,Raw_Data!$A$3:$A$273,Raw_Data!$C$3:$C$273),"") -> Blasdell, NY | E51: =IFERROR(_xlfn.XLOOKUP($B51,Raw_Data!$A$3:$A$273,Raw_Data!$D$3:$D$273),"") -> 2013 | F51: =IFERROR(_xlfn.XLOOKUP($B51,Raw_Data!$A$3:$A$273,Raw_Data!$F$3:$F$273),"") -> Buildings | G51: =IFERROR(_xlfn.XLOOKUP($B51,Raw_Data!$A$3:$A$273,Raw_Data!$J$3:$J$273),"") -> 45047 | H51: Series A | I51: =IFERROR(_xlfn.XLOOKUP($B51,Raw_Data!$A$3:$A$273,Raw_Data!$I$3:$I$273),"") -> 62.28 | J51: =IFERROR(_xlfn.XLOOKUP($B51,Raw_Data!$A$3:$A$273,Raw_Data!$L$3:$L$273),"") -> 6.7 | K51: =IFERROR(_xlfn.XLOOKUP($B51,Raw_Data!$A$3:$A$273,Raw_Data!$M$3:$M$273),"") -> 33 | L51: =IFERROR(_xlfn.XLOOKUP($B51,Raw_Data!$A$3:$A$273,Raw_Data!$Q$3:$Q$273),"") -> 0 | M51: =IFERROR(_xlfn.XLOOKUP($B51,Raw_Data!$A$3:$A$273,Raw_Data!$R$3:$R$273),"") -> WNY Impact Investment Fund | N51: {=IF(M51="",0,COUNTA(_xlfn._xlws.FILTER(_xlfn.TEXTSPLIT(M51,";"), _xlfn.TEXTSPLIT(M51,";")<>"")))} -> 1 | O51: =IF(P51>0,"Y","N") -> Y | P51: =IFERROR(_xlfn.XLOOKUP($B51,Raw_Data!$A$3:$A$273,Raw_Data!$V$3:$V$273),"") -> 1 | Q51: =IF(R51>0,"Y","N") -> Y | R51: =IFERROR(_xlfn.XLOOKUP($B51,Raw_Data!$A$3:$A$273,Raw_Data!$Y$3:$Y$273),"") -> N/A | S51: {=_xlfn.LET(_xlpm.s, Raw_Data!W51,_xlpm.strat, _xlfn._xlws.FILTER(REF_Setup!$B$3:$B$40, REF_Setup!$B$3:$B$40<>""),IF(OR(_xlpm.s="",_xlpm.s=0),"Unclassified",IF(SUM(--ISNUMBER(SEARCH(_xlpm.strat, _xlpm.s)))>0, "Y", "N")) )} -> Unclassified | T51: {=_xlfn.LET(_xlpm.s,M51,_xlpm.phil, _xlfn._xlws.FILTER(REF_Setup!$D$3:$D$5, REF_Setup!$D$3:$D$5<>""),IF(OR(_xlpm.s="", _xlpm.s=0),"Unclassified",IF(SUM(--ISNUMBER(SEARCH(_xlpm.phil, _xlpm.s)))>0, "Y", "N")))} -> N | U51: {=IF(M51="", "Unclassified", IF(AND(SUMPRODUCT(--ISNUMBER(SEARCH(REF_Setup!$B$3:$B$40,M51)))>0,SUMPRODUCT(--ISNUMBER(SEARCH(REF_Setup!$F$3:$F$15,M51)))>0),"Mixed",IF(SUMPRODUCT(--ISNUMBER(SEARCH(REF_Setup!$B$3:$B$40,M51)))>0,"Strategic Only",IF(SUMPRODUCT(--ISNUMBER(SEARCH(REF_Setup!$F$3:$F$15,M51)))>0,"VC Only","Unclassified"))))} -> VC Only
B52: =B51+1 -> 50 | C52: =IFERROR(_xlfn.XLOOKUP($B52,Raw_Data!$A$3:$A$273,Raw_Data!$B$3:$B$273),"") -> Clear Energy Hydro | D52: =IFERROR(_xlfn.XLOOKUP($B52,Raw_Data!$A$3:$A$273,Raw_Data!$C$3:$C$273),"") -> Castle Rock, CO | E52: =IFERROR(_xlfn.XLOOKUP($B52,Raw_Data!$A$3:$A$273,Raw_Data!$D$3:$D$273),"") -> 2018 | F52: =IFERROR(_xlfn.XLOOKUP($B52,Raw_Data!$A$3:$A$273,Raw_Data!$F$3:$F$273),"") -> Renewables | G52: =IFERROR(_xlfn.XLOOKUP($B52,Raw_Data!$A$3:$A$273,Raw_Data!$J$3:$J$273),"") -> 44215 | H52: Development capital | I52: =IFERROR(_xlfn.XLOOKUP($B52,Raw_Data!$A$3:$A$273,Raw_Data!$I$3:$I$273),"") -> 0 | J52: =IFERROR(_xlfn.XLOOKUP($B52,Raw_Data!$A$3:$A$273,Raw_Data!$L$3:$L$273),"") -> 0 | K52: =IFERROR(_xlfn.XLOOKUP($B52,Raw_Data!$A$3:$A$273,Raw_Data!$M$3:$M$273),"") -> 0 | L52: =IFERROR(_xlfn.XLOOKUP($B52,Raw_Data!$A$3:$A$273,Raw_Data!$Q$3:$Q$273),"") -> N/A | M52: =IFERROR(_xlfn.XLOOKUP($B52,Raw_Data!$A$3:$A$273,Raw_Data!$R$3:$R$273),"") -> Greenbacker Capital Management | N52: {=IF(M52="",0,COUNTA(_xlfn._xlws.FILTER(_xlfn.TEXTSPLIT(M52,";"), _xlfn.TEXTSPLIT(M52,";")<>"")))} -> 1 | O52: =IF(P52>0,"Y","N") -> N | P52: =IFERROR(_xlfn.XLOOKUP($B52,Raw_Data!$A$3:$A$273,Raw_Data!$V$3:$V$273),"") -> 0 | Q52: =IF(R52>0,"Y","N") -> Y | R52: =IFERROR(_xlfn.XLOOKUP($B52,Raw_Data!$A$3:$A$273,Raw_Data!$Y$3:$Y$273),"") -> 1 | S52: {=_xlfn.LET(_xlpm.s, Raw_Data!W52,_xlpm.strat, _xlfn._xlws.FILTER(REF_Setup!$B$3:$B$40, REF_Setup!$B$3:$B$40<>""),IF(OR(_xlpm.s="",_xlpm.s=0),"Unclassified",IF(SUM(--ISNUMBER(SEARCH(_xlpm.strat, _xlpm.s)))>0, "Y", "N")) )} -> N | T52: {=_xlfn.LET(_xlpm.s,M52,_xlpm.phil, _xlfn._xlws.FILTER(REF_Setup!$D$3:$D$5, REF_Setup!$D$3:$D$5<>""),IF(OR(_xlpm.s="", _xlpm.s=0),"Unclassified",IF(SUM(--ISNUMBER(SEARCH(_xlpm.phil, _xlpm.s)))>0, "Y", "N")))} -> N | U52: {=IF(M52="", "Unclassified", IF(AND(SUMPRODUCT(--ISNUMBER(SEARCH(REF_Setup!$B$3:$B$40,M52)))>0,SUMPRODUCT(--ISNUMBER(SEARCH(REF_Setup!$F$3:$F$15,M52)))>0),"Mixed",IF(SUMPRODUCT(--ISNUMBER(SEARCH(REF_Setup!$B$3:$B$40,M52)))>0,"Strategic Only",IF(SUMPRODUCT(--ISNUMBER(SEARCH(REF_Setup!$F$3:$F$15,M52)))>0,"VC Only","Unclassified"))))} -> VC Only
B53: =B52+1 -> 51 | C53: =IFERROR(_xlfn.XLOOKUP($B53,Raw_Data!$A$3:$A$273,Raw_Data!$B$3:$B$273),"") -> ClearShift | D53: =IFERROR(_xlfn.XLOOKUP($B53,Raw_Data!$A$3:$A$273,Raw_Data!$C$3:$C$273),"") -> Dallas, TX | E53: =IFERROR(_xlfn.XLOOKUP($B53,Raw_Data!$A$3:$A$273,Raw_Data!$D$3:$D$273),"") -> 2017 | F53: =IFERROR(_xlfn.XLOOKUP($B53,Raw_Data!$A$3:$A$273,Raw_Data!$F$3:$F$273),"") -> Industrial Decarbonization | G53: =IFERROR(_xlfn.XLOOKUP($B53,Raw_Data!$A$3:$A$273,Raw_Data!$J$3:$J$273),"") -> 43003 | H53: Development capital | I53: =IFERROR(_xlfn.XLOOKUP($B53,Raw_Data!$A$3:$A$273,Raw_Data!$I$3:$I$273),"") -> 0 | J53: =IFERROR(_xlfn.XLOOKUP($B53,Raw_Data!$A$3:$A$273,Raw_Data!$L$3:$L$273),"") -> 0 | K53: =IFERROR(_xlfn.XLOOKUP($B53,Raw_Data!$A$3:$A$273,Raw_Data!$M$3:$M$273),"") -> 0 | L53: =IFERROR(_xlfn.XLOOKUP($B53,Raw_Data!$A$3:$A$273,Raw_Data!$Q$3:$Q$273),"") -> N/A | M53: =IFERROR(_xlfn.XLOOKUP($B53,Raw_Data!$A$3:$A$273,Raw_Data!$R$3:$R$273),"") -> Castlelake | N53: {=IF(M53="",0,COUNTA(_xlfn._xlws.FILTER(_xlfn.TEXTSPLIT(M53,";"), _xlfn.TEXTSPLIT(M53,";")<>"")))} -> 1 | O53: =IF(P53>0,"Y","N") -> N | P53: =IFERROR(_xlfn.XLOOKUP($B53,Raw_Data!$A$3:$A$273,Raw_Data!$V$3:$V$273),"") -> 0 | Q53: =IF(R53>0,"Y","N") -> Y | R53: =IFERROR(_xlfn.XLOOKUP($B53,Raw_Data!$A$3:$A$273,Raw_Data!$Y$3:$Y$273),"") -> 1 | S53: {=_xlfn.LET(_xlpm.s, Raw_Data!W53,_xlpm.strat, _xlfn._xlws.FILTER(REF_Setup!$B$3:$B$40, REF_Setup!$B$3:$B$40<>""),IF(OR(_xlpm.s="",_xlpm.s=0),"Unclassified",IF(SUM(--ISNUMBER(SEARCH(_xlpm.strat, _xlpm.s)))>0, "Y", "N")) )} -> N | T53: {=_xlfn.LET(_xlpm.s,M53,_xlpm.phil, _xlfn._xlws.FILTER(REF_Setup!$D$3:$D$5, REF_Setup!$D$3:$D$5<>""),IF(OR(_xlpm.s="", _xlpm.s=0),"Unclassified",IF(SUM(--ISNUMBER(SEARCH(_xlpm.phil, _xlpm.s)))>0, "Y", "N")))} -> N | U53: {=IF(M53="", "Unclassified", IF(AND(SUMPRODUCT(--ISNUMBER(SEARCH(REF_Setup!$B$3:$B$40,M53)))>0,SUMPRODUCT(--ISNUMBER(SEARCH(REF_Setup!$F$3:$F$15,M53)))>0),"Mixed",IF(SUMPRODUCT(--ISNUMBER(SEARCH(REF_Setup!$B$3:$B$40,M53)))>0,"Strategic Only",IF(SUMPRODUCT(--ISNUMBER(SEARCH(REF_Setup!$F$3:$F$15,M53)))>0,"VC Only","Unclassified"))))} -> Unclassified
B54: =B53+1 -> 52 | C54: =IFERROR(_xlfn.XLOOKUP($B54,Raw_Data!$A$3:$A$273,Raw_Data!$B$3:$B$273),"") -> Commonwealth Fusion Systems | D54: =IFERROR(_xlfn.XLOOKUP($B54,Raw_Data!$A$3:$A$273,Raw_Data!$C$3:$C$273),"") -> Devens, MA | E54: =IFERROR(_xlfn.XLOOKUP($B54,Raw_Data!$A$3:$A$273,Raw_Data!$D$3:$D$273),"") -> 2018 | F54: =IFERROR(_xlfn.XLOOKUP($B54,Raw_Data!$A$3:$A$273,Raw_Data!$F$3:$F$273),"") -> Renewables | G54: =IFERROR(_xlfn.XLOOKUP($B54,Raw_Data!$A$3:$A$273,Raw_Data!$J$3:$J$273),"") -> 43977 | H54: Series A | I54: =IFERROR(_xlfn.XLOOKUP($B54,Raw_Data!$A$3:$A$273,Raw_Data!$I$3:$I$273),"") -> 199 | J54: =IFERROR(_xlfn.XLOOKUP($B54,Raw_Data!$A$3:$A$273,Raw_Data!$L$3:$L$273),"") -> 84 | K54: =IFERROR(_xlfn.XLOOKUP($B54,Raw_Data!$A$3:$A$273,Raw_Data!$M$3:$M$273),"") -> 0 | L54: =IFERROR(_xlfn.XLOOKUP($B54,Raw_Data!$A$3:$A$273,Raw_Data!$Q$3:$Q$273),"") -> 0 | M54: =IFERROR(_xlfn.XLOOKUP($B54,Raw_Data!$A$3:$A$273,Raw_Data!$R$3:$R$273),"") -> Artfo Holdings; Beni Venture Capital; Breakthrough Energy; Devonshire Investors; Engine Ventures; Equinor Venturses; Futures Ventures; Hostplus Superannuation Fund; Khosla Ventures; Lowercarbon Capital; Moore Strategic Ventures; Prime Movers Lab; Safar Partners; Schooner Capital; Starlight Ventures; Temasek Holdings; Yild Capital Partners | N54: {=IF(M54="",0,COUNTA(_xlfn._xlws.FILTER(_xlfn.TEXTSPLIT(M54,";"), _xlfn.TEXTSPLIT(M54,";")<>"")))} -> 17 | O54: =IF(P54>0,"Y","N") -> Y | P54: =IFERROR(_xlfn.XLOOKUP($B54,Raw_Data!$A$3:$A$273,Raw_Data!$V$3:$V$273),"") -> 0.47058824 | Q54: =IF(R54>0,"Y","N") -> Y | R54: =IFERROR(_xlfn.XLOOKUP($B54,Raw_Data!$A$3:$A$273,Raw_Data!$Y$3:$Y$273),"") -> 0.70588235 | S54: {=_xlfn.LET(_xlpm.s, Raw_Data!W54,_xlpm.strat, _xlfn._xlws.FILTER(REF_Setup!$B$3:$B$40, REF_Setup!$B$3:$B$40<>""),IF(OR(_xlpm.s="",_xlpm.s=0),"Unclassified",IF(SUM(--ISNUMBER(SEARCH(_xlpm.strat, _xlpm.s)))>0, "Y", "N")) )} -> N | T54: {=_xlfn.LET(_xlpm.s,M54,_xlpm.phil, _xlfn._xlws.FILTER(REF_Setup!$D$3:$D$5, REF_Setup!$D$3:$D$5<>""),IF(OR(_xlpm.s="", _xlpm.s=0),"Unclassified",IF(SUM(--ISNUMBER(SEARCH(_xlpm.phil, _xlpm.s)))>0, "Y", "N")))} -> N | U54: {=IF(M54="", "Unclassified", IF(AND(SUMPRODUCT(--ISNUMBER(SEARCH(REF_Setup!$B$3:$B$40,M54)))>0,SUMPRODUCT(--ISNUMBER(SEARCH(REF_Setup!$F$3:$F$15,M54)))>0),"Mixed",IF(SUMPRODUCT(--ISNUMBER(SEARCH(REF_Setup!$B$3:$B$40,M54)))>0,"Strategic Only",IF(SUMPRODUCT(--ISNUMBER(SEARCH(REF_Setup!$F$3:$F$15,M54)))>0,"VC Only","Unclassified"))))} -> VC Only
B55: =B54+1 -> 53 | C55: =IFERROR(_xlfn.XLOOKUP($B55,Raw_Data!$A$3:$A$273,Raw_Data!$B$3:$B$273),"") -> Commonwealth Fusion Systems | D55: =IFERROR(_xlfn.XLOOKUP($B55,Raw_Data!$A$3:$A$273,Raw_Data!$C$3:$C$273),"") -> Devens, MA | E55: =IFERROR(_xlfn.XLOOKUP($B55,Raw_Data!$A$3:$A$273,Raw_Data!$D$3:$D$273),"") -> 2018 | F55: =IFERROR(_xlfn.XLOOKUP($B55,Raw_Data!$A$3:$A$273,Raw_Data!$F$3:$F$273),"") -> Renewables | G55: =IFERROR(_xlfn.XLOOKUP($B55,Raw_Data!$A$3:$A$273,Raw_Data!$J$3:$J$273),"") -> 45834 | H55: Series B | I55: =IFERROR(_xlfn.XLOOKUP($B55,Raw_Data!$A$3:$A$273,Raw_Data!$I$3:$I$273),"") -> 2862 | J55: =IFERROR(_xlfn.XLOOKUP($B55,Raw_Data!$A$3:$A$273,Raw_Data!$L$3:$L$273),"") -> 863 | K55: =IFERROR(_xlfn.XLOOKUP($B55,Raw_Data!$A$3:$A$273,Raw_Data!$M$3:$M$273),"") -> 0 | L55: =IFERROR(_xlfn.XLOOKUP($B55,Raw_Data!$A$3:$A$273,Raw_Data!$Q$3:$Q$273),"") -> 0.11587486 | M55: =IFERROR(_xlfn.XLOOKUP($B55,Raw_Data!$A$3:$A$273,Raw_Data!$R$3:$R$273),"") -> 31Ventures; Breakthrough Energy; Brevan Howard Macro Venture Fund; Eni Next, FFA Private Bank Dubai, NTT Docomo Ventures; Mitsui & Company; Mitsubishi Corporation Urban Development; Development Bank of Japan; Fujikura; Jera; NVentures; Mitsui Fudosan; Nvidia; Mitsui O.S.K. Lines; Kansai Electric Power; K4 Ventures; Woori Financial Group; NTT QONOQ; Planet First Partners; HOF Capital; Evolution VC Partners; Gigascale Capital; NEVA SGR; Standish Spring Investments; Khosla Ventures; Future Ventures; Safar Partners; Starlight Ventures; Lowercarbon Capital; Tiger Global Management; Global Brain; Galaxy Interactive; Gates Frontier; Stanley F. Druckenmiller; Eric Schmidt; Sumitomo Mitsui Trust Bank; Sumitomo Mitsui Banking; JGC Holdings; Brightwing Capital; One Madison Group; Emerson Collective; Google Foundation; Hostplus Superannuation Fund; Ripple Impact Investments; Doorga Capital; Counterpoint Global | N55: {=IF(M55="",0,COUNTA(_xlfn._xlws.FILTER(_xlfn.TEXTSPLIT(M55,";"), _xlfn.TEXTSPLIT(M55,";")<>"")))} -> 45 | O55: =IF(P55>0,"Y","N") -> Y | P55: =IFERROR(_xlfn.XLOOKUP($B55,Raw_Data!$A$3:$A$273,Raw_Data!$V$3:$V$273),"") -> 0.28888889 | Q55: =IF(R55>0,"Y","N") -> Y | R55: =IFERROR(_xlfn.XLOOKUP($B55,Raw_Data!$A$3:$A$273,Raw_Data!$Y$3:$Y$273),"") -> 0.73333333 | S55: {=_xlfn.LET(_xlpm.s, Raw_Data!W55,_xlpm.strat, _xlfn._xlws.FILTER(REF_Setup!$B$3:$B$40, REF_Setup!$B$3:$B$40<>""),IF(OR(_xlpm.s="",_xlpm.s=0),"Unclassified",IF(SUM(--ISNUMBER(SEARCH(_xlpm.strat, _xlpm.s)))>0, "Y", "N")) )} -> Y | T55: {=_xlfn.LET(_xlpm.s,M55,_xlpm.phil, _xlfn._xlws.FILTER(REF_Setup!$D$3:$D$5, REF_Setup!$D$3:$D$5<>""),IF(OR(_xlpm.s="", _xlpm.s=0),"Unclassified",IF(SUM(--ISNUMBER(SEARCH(_xlpm.phil, _xlpm.s)))>0, "Y", "N")))} -> Y | U55: {=IF(M55="", "Unclassified", IF(AND(SUMPRODUCT(--ISNUMBER(SEARCH(REF_Setup!$B$3:$B$40,M55)))>0,SUMPRODUCT(--ISNUMBER(SEARCH(REF_Setup!$F$3:$F$15,M55)))>0),"Mixed",IF(SUMPRODUCT(--ISNUMBER(SEARCH(REF_Setup!$B$3:$B$40,M55)))>0,"Strategic Only",IF(SUMPRODUCT(--ISNUMBER(SEARCH(REF_Setup!$F$3:$F$15,M55)))>0,"VC Only","Unclassified"))))} -> Mixed
B56: =B55+1 -> 54 | C56: =IFERROR(_xlfn.XLOOKUP($B56,Raw_Data!$A$3:$A$273,Raw_Data!$B$3:$B$273),"") -> Conamix | D56: =IFERROR(_xlfn.XLOOKUP($B56,Raw_Data!$A$3:$A$273,Raw_Data!$C$3:$C$273),"") -> Ithaca, NY | E56: =IFERROR(_xlfn.XLOOKUP($B56,Raw_Data!$A$3:$A$273,Raw_Data!$D$3:$D$273),"") -> 2014 | F56: =IFERROR(_xlfn.XLOOKUP($B56,Raw_Data!$A$3:$A$273,Raw_Data!$F$3:$F$273),"") -> LDES | G56: =IFERROR(_xlfn.XLOOKUP($B56,Raw_Data!$A$3:$A$273,Raw_Data!$J$3:$J$273),"") -> 44524 | H56: Series A | I56: =IFERROR(_xlfn.XLOOKUP($B56,Raw_Data!$A$3:$A$273,Raw_Data!$I$3:$I$273),"") -> 10.84 | J56: =IFERROR(_xlfn.XLOOKUP($B56,Raw_Data!$A$3:$A$273,Raw_Data!$L$3:$L$273),"") -> 4 | K56: =IFERROR(_xlfn.XLOOKUP($B56,Raw_Data!$A$3:$A$273,Raw_Data!$M$3:$M$273),"") -> 34 | L56: =IFERROR(_xlfn.XLOOKUP($B56,Raw_Data!$A$3:$A$273,Raw_Data!$Q$3:$Q$273),"") -> 0 | M56: =IFERROR(_xlfn.XLOOKUP($B56,Raw_Data!$A$3:$A$273,Raw_Data!$R$3:$R$273),"") -> Catalus Capital Management (Saif Qazi); Plug and Play Tech Center | N56: {=IF(M56="",0,COUNTA(_xlfn._xlws.FILTER(_xlfn.TEXTSPLIT(M56,";"), _xlfn.TEXTSPLIT(M56,";")<>"")))} -> 2 | O56: =IF(P56>0,"Y","N") -> N | P56: =IFERROR(_xlfn.XLOOKUP($B56,Raw_Data!$A$3:$A$273,Raw_Data!$V$3:$V$273),"") -> 0 | Q56: =IF(R56>0,"Y","N") -> Y | R56: =IFERROR(_xlfn.XLOOKUP($B56,Raw_Data!$A$3:$A$273,Raw_Data!$Y$3:$Y$273),"") -> 1 | S56: {=_xlfn.LET(_xlpm.s, Raw_Data!W56,_xlpm.strat, _xlfn._xlws.FILTER(REF_Setup!$B$3:$B$40, REF_Setup!$B$3:$B$40<>""),IF(OR(_xlpm.s="",_xlpm.s=0),"Unclassified",IF(SUM(--ISNUMBER(SEARCH(_xlpm.strat, _xlpm.s)))>0, "Y", "N")) )} -> N | T56: {=_xlfn.LET(_xlpm.s,M56,_xlpm.phil, _xlfn._xlws.FILTER(REF_Setup!$D$3:$D$5, REF_Setup!$D$3:$D$5<>""),IF(OR(_xlpm.s="", _xlpm.s=0),"Unclassified",IF(SUM(--ISNUMBER(SEARCH(_xlpm.phil, _xlpm.s)))>0, "Y", "N")))} -> N | U56: {=IF(M56="", "Unclassified", IF(AND(SUMPRODUCT(--ISNUMBER(SEARCH(REF_Setup!$B$3:$B$40,M56)))>0,SUMPRODUCT(--ISNUMBER(SEARCH(REF_Setup!$F$3:$F$15,M56)))>0),"Mixed",IF(SUMPRODUCT(--ISNUMBER(SEARCH(REF_Setup!$B$3:$B$40,M56)))>0,"Strategic Only",IF(SUMPRODUCT(--ISNUMBER(SEARCH(REF_Setup!$F$3:$F$15,M56)))>0,"VC Only","Unclassified"))))} -> VC Only
B57: =B56+1 -> 55 | C57: =IFERROR(_xlfn.XLOOKUP($B57,Raw_Data!$A$3:$A$273,Raw_Data!$B$3:$B$273),"") -> Cool Energy | D57: =IFERROR(_xlfn.XLOOKUP($B57,Raw_Data!$A$3:$A$273,Raw_Data!$C$3:$C$273),"") -> Boulder, CO | E57: =IFERROR(_xlfn.XLOOKUP($B57,Raw_Data!$A$3:$A$273,Raw_Data!$D$3:$D$273),"") -> 2006 | F57: =IFERROR(_xlfn.XLOOKUP($B57,Raw_Data!$A$3:$A$273,Raw_Data!$F$3:$F$273),"") -> Industrial Decarbonization | G57: =IFERROR(_xlfn.XLOOKUP($B57,Raw_Data!$A$3:$A$273,Raw_Data!$J$3:$J$273),"") -> 44774 | H57: Development capital | I57: =IFERROR(_xlfn.XLOOKUP($B57,Raw_Data!$A$3:$A$273,Raw_Data!$I$3:$I$273),"") -> 2.47 | J57: =IFERROR(_xlfn.XLOOKUP($B57,Raw_Data!$A$3:$A$273,Raw_Data!$L$3:$L$273),"") -> 0 | K57: =IFERROR(_xlfn.XLOOKUP($B57,Raw_Data!$A$3:$A$273,Raw_Data!$M$3:$M$273),"") -> 0 | L57: =IFERROR(_xlfn.XLOOKUP($B57,Raw_Data!$A$3:$A$273,Raw_Data!$Q$3:$Q$273),"") -> N/A | M57: =IFERROR(_xlfn.XLOOKUP($B57,Raw_Data!$A$3:$A$273,Raw_Data!$R$3:$R$273),"") -> Highland Ventures Group | N57: {=IF(M57="",0,COUNTA(_xlfn._xlws.FILTER(_xlfn.TEXTSPLIT(M57,";"), _xlfn.TEXTSPLIT(M57,";")<>"")))} -> 1 | O57: =IF(P57>0,"Y","N") -> N | P57: =IFERROR(_xlfn.XLOOKUP($B57,Raw_Data!$A$3:$A$273,Raw_Data!$V$3:$V$273),"") -> 0 | Q57: =IF(R57>0,"Y","N") -> Y | R57: =IFERROR(_xlfn.XLOOKUP($B57,Raw_Data!$A$3:$A$273,Raw_Data!$Y$3:$Y$273),"") -> 1 | S57: {=_xlfn.LET(_xlpm.s, Raw_Data!W57,_xlpm.strat, _xlfn._xlws.FILTER(REF_Setup!$B$3:$B$40, REF_Setup!$B$3:$B$40<>""),IF(OR(_xlpm.s="",_xlpm.s=0),"Unclassified",IF(SUM(--ISNUMBER(SEARCH(_xlpm.strat, _xlpm.s)))>0, "Y", "N")) )} -> N | T57: {=_xlfn.LET(_xlpm.s,M57,_xlpm.phil, _xlfn._xlws.FILTER(REF_Setup!$D$3:$D$5, REF_Setup!$D$3:$D$5<>""),IF(OR(_xlpm.s="", _xlpm.s=0),"Unclassified",IF(SUM(--ISNUMBER(SEARCH(_xlpm.phil, _xlpm.s)))>0, "Y", "N")))} -> N | U57: {=IF(M57="", "Unclassified", IF(AND(SUMPRODUCT(--ISNUMBER(SEARCH(REF_Setup!$B$3:$B$40,M57)))>0,SUMPRODUCT(--ISNUMBER(SEARCH(REF_Setup!$F$3:$F$15,M57)))>0),"Mixed",IF(SUMPRODUCT(--ISNUMBER(SEARCH(REF_Setup!$B$3:$B$40,M57)))>0,"Strategic Only",IF(SUMPRODUCT(--ISNUMBER(SEARCH(REF_Setup!$F$3:$F$15,M57)))>0,"VC Only","Unclassified"))))} -> VC Only
B58: =B57+1 -> 56 | C58: =IFERROR(_xlfn.XLOOKUP($B58,Raw_Data!$A$3:$A$273,Raw_Data!$B$3:$B$273),"") -> Dandelion Energy | D58: =IFERROR(_xlfn.XLOOKUP($B58,Raw_Data!$A$3:$A$273,Raw_Data!$C$3:$C$273),"") -> Mount Kisco, NY | E58: =IFERROR(_xlfn.XLOOKUP($B58,Raw_Data!$A$3:$A$273,Raw_Data!$D$3:$D$273),"") -> 2017 | F58: =IFERROR(_xlfn.XLOOKUP($B58,Raw_Data!$A$3:$A$273,Raw_Data!$F$3:$F$273),"") -> Buildings | G58: =IFERROR(_xlfn.XLOOKUP($B58,Raw_Data!$A$3:$A$273,Raw_Data!$J$3:$J$273),"") -> 43845 | H58: Series A | I58: =IFERROR(_xlfn.XLOOKUP($B58,Raw_Data!$A$3:$A$273,Raw_Data!$I$3:$I$273),"") -> 34.96 | J58: =IFERROR(_xlfn.XLOOKUP($B58,Raw_Data!$A$3:$A$273,Raw_Data!$L$3:$L$273),"") -> 12 | K58: =IFERROR(_xlfn.XLOOKUP($B58,Raw_Data!$A$3:$A$273,Raw_Data!$M$3:$M$273),"") -> 109.99 | L58: =IFERROR(_xlfn.XLOOKUP($B58,Raw_Data!$A$3:$A$273,Raw_Data!$Q$3:$Q$273),"") -> 0 | M58: =IFERROR(_xlfn.XLOOKUP($B58,Raw_Data!$A$3:$A$273,Raw_Data!$R$3:$R$273),"") -> Catchlight Ventures; Collaborative Fund; Comcast Ventures; Ground Up Ventures; GV; Lennar Ventures; New Enterprise Associates | N58: {=IF(M58="",0,COUNTA(_xlfn._xlws.FILTER(_xlfn.TEXTSPLIT(M58,";"), _xlfn.TEXTSPLIT(M58,";")<>"")))} -> 7 | O58: =IF(P58>0,"Y","N") -> Y | P58: =IFERROR(_xlfn.XLOOKUP($B58,Raw_Data!$A$3:$A$273,Raw_Data!$V$3:$V$273),"") -> 0.85714286 | Q58: =IF(R58>0,"Y","N") -> Y | R58: =IFERROR(_xlfn.XLOOKUP($B58,Raw_Data!$A$3:$A$273,Raw_Data!$Y$3:$Y$273),"") -> 0.14285714 | S58: {=_xlfn.LET(_xlpm.s, Raw_Data!W58,_xlpm.strat, _xlfn._xlws.FILTER(REF_Setup!$B$3:$B$40, REF_Setup!$B$3:$B$40<>""),IF(OR(_xlpm.s="",_xlpm.s=0),"Unclassified",IF(SUM(--ISNUMBER(SEARCH(_xlpm.strat, _xlpm.s)))>0, "Y", "N")) )} -> N | T58: {=_xlfn.LET(_xlpm.s,M58,_xlpm.phil, _xlfn._xlws.FILTER(REF_Setup!$D$3:$D$5, REF_Setup!$D$3:$D$5<>""),IF(OR(_xlpm.s="", _xlpm.s=0),"Unclassified",IF(SUM(--ISNUMBER(SEARCH(_xlpm.phil, _xlpm.s)))>0, "Y", "N")))} -> N | U58: {=IF(M58="", "Unclassified", IF(AND(SUMPRODUCT(--ISNUMBER(SEARCH(REF_Setup!$B$3:$B$40,M58)))>0,SUMPRODUCT(--ISNUMBER(SEARCH(REF_Setup!$F$3:$F$15,M58)))>0),"Mixed",IF(SUMPRODUCT(--ISNUMBER(SEARCH(REF_Setup!$B$3:$B$40,M58)))>0,"Strategic Only",IF(SUMPRODUCT(--ISNUMBER(SEARCH(REF_Setup!$F$3:$F$15,M58)))>0,"VC Only","Unclassified"))))} -> Mixed
B59: =B58+1 -> 57 | C59: =IFERROR(_xlfn.XLOOKUP($B59,Raw_Data!$A$3:$A$273,Raw_Data!$B$3:$B$273),"") -> Dandelion Energy | D59: =IFERROR(_xlfn.XLOOKUP($B59,Raw_Data!$A$3:$A$273,Raw_Data!$C$3:$C$273),"") -> Mount Kisco, NY | E59: =IFERROR(_xlfn.XLOOKUP($B59,Raw_Data!$A$3:$A$273,Raw_Data!$D$3:$D$273),"") -> 2017 | F59: =IFERROR(_xlfn.XLOOKUP($B59,Raw_Data!$A$3:$A$273,Raw_Data!$F$3:$F$273),"") -> Buildings | G59: =IFERROR(_xlfn.XLOOKUP($B59,Raw_Data!$A$3:$A$273,Raw_Data!$J$3:$J$273),"") -> 44880 | H59: Series B | I59: =IFERROR(_xlfn.XLOOKUP($B59,Raw_Data!$A$3:$A$273,Raw_Data!$I$3:$I$273),"") -> 135.66 | J59: =IFERROR(_xlfn.XLOOKUP($B59,Raw_Data!$A$3:$A$273,Raw_Data!$L$3:$L$273),"") -> 69.7 | K59: =IFERROR(_xlfn.XLOOKUP($B59,Raw_Data!$A$3:$A$273,Raw_Data!$M$3:$M$273),"") -> 299.7 | L59: =IFERROR(_xlfn.XLOOKUP($B59,Raw_Data!$A$3:$A$273,Raw_Data!$Q$3:$Q$273),"") -> 0 | M59: =IFERROR(_xlfn.XLOOKUP($B59,Raw_Data!$A$3:$A$273,Raw_Data!$R$3:$R$273),"") -> Breakthrough Energy; Building Ventures; Collaborative Fund; David Stark; GV; HiJoJo Partners; Lennar Ventures; Michael Sachse; New Enterprise Associates; NGP Energy Capital Management; NGP Energy Technology Partners; OurCrowd; Sam Landman; Tim Krebs; Travis Connors | N59: {=IF(M59="",0,COUNTA(_xlfn._xlws.FILTER(_xlfn.TEXTSPLIT(M59,";"), _xlfn.TEXTSPLIT(M59,";")<>"")))} -> 15 | O59: =IF(P59>0,"Y","N") -> Y | P59: =IFERROR(_xlfn.XLOOKUP($B59,Raw_Data!$A$3:$A$273,Raw_Data!$V$3:$V$273),"") -> 0.4 | Q59: =IF(R59>0,"Y","N") -> Y | R59: =IFERROR(_xlfn.XLOOKUP($B59,Raw_Data!$A$3:$A$273,Raw_Data!$Y$3:$Y$273),"") -> 0.6 | S59: {=_xlfn.LET(_xlpm.s, Raw_Data!W59,_xlpm.strat, _xlfn._xlws.FILTER(REF_Setup!$B$3:$B$40, REF_Setup!$B$3:$B$40<>""),IF(OR(_xlpm.s="",_xlpm.s=0),"Unclassified",IF(SUM(--ISNUMBER(SEARCH(_xlpm.strat, _xlpm.s)))>0, "Y", "N")) )} -> N | T59: {=_xlfn.LET(_xlpm.s,M59,_xlpm.phil, _xlfn._xlws.FILTER(REF_Setup!$D$3:$D$5, REF_Setup!$D$3:$D$5<>""),IF(OR(_xlpm.s="", _xlpm.s=0),"Unclassified",IF(SUM(--ISNUMBER(SEARCH(_xlpm.phil, _xlpm.s)))>0, "Y", "N")))} -> N | U59: {=IF(M59="", "Unclassified", IF(AND(SUMPRODUCT(--ISNUMBER(SEARCH(REF_Setup!$B$3:$B$40,M59)))>0,SUMPRODUCT(--ISNUMBER(SEARCH(REF_Setup!$F$3:$F$15,M59)))>0),"Mixed",IF(SUMPRODUCT(--ISNUMBER(SEARCH(REF_Setup!$B$3:$B$40,M59)))>0,"Strategic Only",IF(SUMPRODUCT(--ISNUMBER(SEARCH(REF_Setup!$F$3:$F$15,M59)))>0,"VC Only","Unclassified"))))} -> Mixed
B60: =B59+1 -> 58 | C60: =IFERROR(_xlfn.XLOOKUP($B60,Raw_Data!$A$3:$A$273,Raw_Data!$B$3:$B$273),"") -> Digital Power Optimization | D60: =IFERROR(_xlfn.XLOOKUP($B60,Raw_Data!$A$3:$A$273,Raw_Data!$C$3:$C$273),"") -> New York, NY | E60: =IFERROR(_xlfn.XLOOKUP($B60,Raw_Data!$A$3:$A$273,Raw_Data!$D$3:$D$273),"") -> 2020 | F60: =IFERROR(_xlfn.XLOOKUP($B60,Raw_Data!$A$3:$A$273,Raw_Data!$F$3:$F$273),"") -> Renewables | G60: =IFERROR(_xlfn.XLOOKUP($B60,Raw_Data!$A$3:$A$273,Raw_Data!$J$3:$J$273),"") -> 44223 | H60: Seed | I60: =IFERROR(_xlfn.XLOOKUP($B60,Raw_Data!$A$3:$A$273,Raw_Data!$I$3:$I$273),"") -> 0.54 | J60: =IFERROR(_xlfn.XLOOKUP($B60,Raw_Data!$A$3:$A$273,Raw_Data!$L$3:$L$273),"") -> 0.44 | K60: =IFERROR(_xlfn.XLOOKUP($B60,Raw_Data!$A$3:$A$273,Raw_Data!$M$3:$M$273),"") -> 4 | L60: =IFERROR(_xlfn.XLOOKUP($B60,Raw_Data!$A$3:$A$273,Raw_Data!$Q$3:$Q$273),"") -> 0 | M60: =IFERROR(_xlfn.XLOOKUP($B60,Raw_Data!$A$3:$A$273,Raw_Data!$R$3:$R$273),"") -> Salutem Capital | N60: {=IF(M60="",0,COUNTA(_xlfn._xlws.FILTER(_xlfn.TEXTSPLIT(M60,";"), _xlfn.TEXTSPLIT(M60,";")<>"")))} -> 1 | O60: =IF(P60>0,"Y","N") -> N | P60: =IFERROR(_xlfn.XLOOKUP($B60,Raw_Data!$A$3:$A$273,Raw_Data!$V$3:$V$273),"") -> 0 | Q60: =IF(R60>0,"Y","N") -> Y | R60: =IFERROR(_xlfn.XLOOKUP($B60,Raw_Data!$A$3:$A$273,Raw_Data!$Y$3:$Y$273),"") -> 1 | S60: {=_xlfn.LET(_xlpm.s, Raw_Data!W60,_xlpm.strat, _xlfn._xlws.FILTER(REF_Setup!$B$3:$B$40, REF_Setup!$B$3:$B$40<>""),IF(OR(_xlpm.s="",_xlpm.s=0),"Unclassified",IF(SUM(--ISNUMBER(SEARCH(_xlpm.strat, _xlpm.s)))>0, "Y", "N")) )} -> N | T60: {=_xlfn.LET(_xlpm.s,M60,_xlpm.phil, _xlfn._xlws.FILTER(REF_Setup!$D$3:$D$5, REF_Setup!$D$3:$D$5<>""),IF(OR(_xlpm.s="", _xlpm.s=0),"Unclassified",IF(SUM(--ISNUMBER(SEARCH(_xlpm.phil, _xlpm.s)))>0, "Y", "N")))} -> N | U60: {=IF(M60="", "Unclassified", IF(AND(SUMPRODUCT(--ISNUMBER(SEARCH(REF_Setup!$B$3:$B$40,M60)))>0,SUMPRODUCT(--ISNUMBER(SEARCH(REF_Setup!$F$3:$F$15,M60)))>0),"Mixed",IF(SUMPRODUCT(--ISNUMBER(SEARCH(REF_Setup!$B$3:$B$40,M60)))>0,"Strategic Only",IF(SUMPRODUCT(--ISNUMBER(SEARCH(REF_Setup!$F$3:$F$15,M60)))>0,"VC Only","Unclassified"))))} -> VC Only
B61: =B60+1 -> 59 | C61: =IFERROR(_xlfn.XLOOKUP($B61,Raw_Data!$A$3:$A$273,Raw_Data!$B$3:$B$273),"") -> Dimensional Energy | D61: =IFERROR(_xlfn.XLOOKUP($B61,Raw_Data!$A$3:$A$273,Raw_Data!$C$3:$C$273),"") -> Ithaca, NY | E61: =IFERROR(_xlfn.XLOOKUP($B61,Raw_Data!$A$3:$A$273,Raw_Data!$D$3:$D$273),"") -> 2014 | F61: =IFERROR(_xlfn.XLOOKUP($B61,Raw_Data!$A$3:$A$273,Raw_Data!$F$3:$F$273),"") -> Mobility | G61: =IFERROR(_xlfn.XLOOKUP($B61,Raw_Data!$A$3:$A$273,Raw_Data!$J$3:$J$273),"") -> 44561 | I61: =IFERROR(_xlfn.XLOOKUP($B61,Raw_Data!$A$3:$A$273,Raw_Data!$I$3:$I$273),"") -> 6.3 | J61: =IFERROR(_xlfn.XLOOKUP($B61,Raw_Data!$A$3:$A$273,Raw_Data!$L$3:$L$273),"") -> 0 | K61: =IFERROR(_xlfn.XLOOKUP($B61,Raw_Data!$A$3:$A$273,Raw_Data!$M$3:$M$273),"") -> 0 | L61: =IFERROR(_xlfn.XLOOKUP($B61,Raw_Data!$A$3:$A$273,Raw_Data!$Q$3:$Q$273),"") -> N/A | M61: =IFERROR(_xlfn.XLOOKUP($B61,Raw_Data!$A$3:$A$273,Raw_Data!$R$3:$R$273),"") -> Beni Venture Capital; Demos Capital; Ithaca Area Economic Development; New Climate Ventures; New York Ventures; United Airlines Ventures | N61: {=IF(M61="",0,COUNTA(_xlfn._xlws.FILTER(_xlfn.TEXTSPLIT(M61,";"), _xlfn.TEXTSPLIT(M61,";")<>"")))} -> 6 | O61: =IF(P61>0,"Y","N") -> Y | P61: =IFERROR(_xlfn.XLOOKUP($B61,Raw_Data!$A$3:$A$273,Raw_Data!$V$3:$V$273),"") -> 0.16666667 | Q61: =IF(R61>0,"Y","N") -> Y | R61: =IFERROR(_xlfn.XLOOKUP($B61,Raw_Data!$A$3:$A$273,Raw_Data!$Y$3:$Y$273),"") -> 0.83333333 | S61: {=_xlfn.LET(_xlpm.s, Raw_Data!W61,_xlpm.strat, _xlfn._xlws.FILTER(REF_Setup!$B$3:$B$40, REF_Setup!$B$3:$B$40<>""),IF(OR(_xlpm.s="",_xlpm.s=0),"Unclassified",IF(SUM(--ISNUMBER(SEARCH(_xlpm.strat, _xlpm.s)))>0, "Y", "N")) )} -> Y | T61: {=_xlfn.LET(_xlpm.s,M61,_xlpm.phil, _xlfn._xlws.FILTER(REF_Setup!$D$3:$D$5, REF_Setup!$D$3:$D$5<>""),IF(OR(_xlpm.s="", _xlpm.s=0),"Unclassified",IF(SUM(--ISNUMBER(SEARCH(_xlpm.phil, _xlpm.s)))>0, "Y", "N")))} -> N | U61: {=IF(M61="", "Unclassified", IF(AND(SUMPRODUCT(--ISNUMBER(SEARCH(REF_Setup!$B$3:$B$40,M61)))>0,SUMPRODUCT(--ISNUMBER(SEARCH(REF_Setup!$F$3:$F$15,M61)))>0),"Mixed",IF(SUMPRODUCT(--ISNUMBER(SEARCH(REF_Setup!$B$3:$B$40,M61)))>0,"Strategic Only",IF(SUMPRODUCT(--ISNUMBER(SEARCH(REF_Setup!$F$3:$F$15,M61)))>0,"VC Only","Unclassified"))))} -> Mixed
B62: =B61+1 -> 60 | C62: =IFERROR(_xlfn.XLOOKUP($B62,Raw_Data!$A$3:$A$273,Raw_Data!$B$3:$B$273),"") -> Disa Technologies | D62: =IFERROR(_xlfn.XLOOKUP($B62,Raw_Data!$A$3:$A$273,Raw_Data!$C$3:$C$273),"") -> Casper, WY | E62: =IFERROR(_xlfn.XLOOKUP($B62,Raw_Data!$A$3:$A$273,Raw_Data!$D$3:$D$273),"") -> 0 | F62: =IFERROR(_xlfn.XLOOKUP($B62,Raw_Data!$A$3:$A$273,Raw_Data!$F$3:$F$273),"") -> Industrial Decarbonization | G62: =IFERROR(_xlfn.XLOOKUP($B62,Raw_Data!$A$3:$A$273,Raw_Data!$J$3:$J$273),"") -> 45845 | H62: Series A | I62: =IFERROR(_xlfn.XLOOKUP($B62,Raw_Data!$A$3:$A$273,Raw_Data!$I$3:$I$273),"") -> 49.53 | J62: =IFERROR(_xlfn.XLOOKUP($B62,Raw_Data!$A$3:$A$273,Raw_Data!$L$3:$L$273),"") -> 30 | K62: =IFERROR(_xlfn.XLOOKUP($B62,Raw_Data!$A$3:$A$273,Raw_Data!$M$3:$M$273),"") -> 149 | L62: =IFERROR(_xlfn.XLOOKUP($B62,Raw_Data!$A$3:$A$273,Raw_Data!$Q$3:$Q$273),"") -> 0 | M62: =IFERROR(_xlfn.XLOOKUP($B62,Raw_Data!$A$3:$A$273,Raw_Data!$R$3:$R$273),"") -> Bacchus Venture Capital; Constellation Technology Ventures; Evok Innovations; Halliburton Labs; The Think & Act Differently; Valor Equity Partners; Veriten | N62: {=IF(M62="",0,COUNTA(_xlfn._xlws.FILTER(_xlfn.TEXTSPLIT(M62,";"), _xlfn.TEXTSPLIT(M62,";")<>"")))} -> 7 | O62: =IF(P62>0,"Y","N") -> Y | P62: =IFERROR(_xlfn.XLOOKUP($B62,Raw_Data!$A$3:$A$273,Raw_Data!$V$3:$V$273),"") -> 0.28571429 | Q62: =IF(R62>0,"Y","N") -> Y | R62: =IFERROR(_xlfn.XLOOKUP($B62,Raw_Data!$A$3:$A$273,Raw_Data!$Y$3:$Y$273),"") -> 0.85714286 | S62: {=_xlfn.LET(_xlpm.s, Raw_Data!W62,_xlpm.strat, _xlfn._xlws.FILTER(REF_Setup!$B$3:$B$40, REF_Setup!$B$3:$B$40<>""),IF(OR(_xlpm.s="",_xlpm.s=0),"Unclassified",IF(SUM(--ISNUMBER(SEARCH(_xlpm.strat, _xlpm.s)))>0, "Y", "N")) )} -> N | T62: {=_xlfn.LET(_xlpm.s,M62,_xlpm.phil, _xlfn._xlws.FILTER(REF_Setup!$D$3:$D$5, REF_Setup!$D$3:$D$5<>""),IF(OR(_xlpm.s="", _xlpm.s=0),"Unclassified",IF(SUM(--ISNUMBER(SEARCH(_xlpm.phil, _xlpm.s)))>0, "Y", "N")))} -> N | U62: {=IF(M62="", "Unclassified", IF(AND(SUMPRODUCT(--ISNUMBER(SEARCH(REF_Setup!$B$3:$B$40,M62)))>0,SUMPRODUCT(--ISNUMBER(SEARCH(REF_Setup!$F$3:$F$15,M62)))>0),"Mixed",IF(SUMPRODUCT(--ISNUMBER(SEARCH(REF_Setup!$B$3:$B$40,M62)))>0,"Strategic Only",IF(SUMPRODUCT(--ISNUMBER(SEARCH(REF_Setup!$F$3:$F$15,M62)))>0,"VC Only","Unclassified"))))} -> VC Only
B63: =B62+1 -> 61 | C63: =IFERROR(_xlfn.XLOOKUP($B63,Raw_Data!$A$3:$A$273,Raw_Data!$B$3:$B$273),"") -> DTG Recycle | D63: =IFERROR(_xlfn.XLOOKUP($B63,Raw_Data!$A$3:$A$273,Raw_Data!$C$3:$C$273),"") -> Bothell, WA | E63: =IFERROR(_xlfn.XLOOKUP($B63,Raw_Data!$A$3:$A$273,Raw_Data!$D$3:$D$273),"") -> 1999 | F63: =IFERROR(_xlfn.XLOOKUP($B63,Raw_Data!$A$3:$A$273,Raw_Data!$F$3:$F$273),"") -> Industrial Decarbonization | G63: =IFERROR(_xlfn.XLOOKUP($B63,Raw_Data!$A$3:$A$273,Raw_Data!$J$3:$J$273),"") -> 43850 | H63: Development capital | I63: =IFERROR(_xlfn.XLOOKUP($B63,Raw_Data!$A$3:$A$273,Raw_Data!$I$3:$I$273),"") -> 32 | J63: =IFERROR(_xlfn.XLOOKUP($B63,Raw_Data!$A$3:$A$273,Raw_Data!$L$3:$L$273),"") -> 32 | K63: =IFERROR(_xlfn.XLOOKUP($B63,Raw_Data!$A$3:$A$273,Raw_Data!$M$3:$M$273),"") -> 0 | L63: =IFERROR(_xlfn.XLOOKUP($B63,Raw_Data!$A$3:$A$273,Raw_Data!$Q$3:$Q$273),"") -> 0 | M63: =IFERROR(_xlfn.XLOOKUP($B63,Raw_Data!$A$3:$A$273,Raw_Data!$R$3:$R$273),"") -> Clair-vest Group | N63: {=IF(M63="",0,COUNTA(_xlfn._xlws.FILTER(_xlfn.TEXTSPLIT(M63,";"), _xlfn.TEXTSPLIT(M63,";")<>"")))} -> 1 | O63: =IF(P63>0,"Y","N") -> N | P63: =IFERROR(_xlfn.XLOOKUP($B63,Raw_Data!$A$3:$A$273,Raw_Data!$V$3:$V$273),"") -> 0 | Q63: =IF(R63>0,"Y","N") -> Y | R63: =IFERROR(_xlfn.XLOOKUP($B63,Raw_Data!$A$3:$A$273,Raw_Data!$Y$3:$Y$273),"") -> 1 | S63: {=_xlfn.LET(_xlpm.s, Raw_Data!W63,_xlpm.strat, _xlfn._xlws.FILTER(REF_Setup!$B$3:$B$40, REF_Setup!$B$3:$B$40<>""),IF(OR(_xlpm.s="",_xlpm.s=0),"Unclassified",IF(SUM(--ISNUMBER(SEARCH(_xlpm.strat, _xlpm.s)))>0, "Y", "N")) )} -> N | T63: {=_xlfn.LET(_xlpm.s,M63,_xlpm.phil, _xlfn._xlws.FILTER(REF_Setup!$D$3:$D$5, REF_Setup!$D$3:$D$5<>""),IF(OR(_xlpm.s="", _xlpm.s=0),"Unclassified",IF(SUM(--ISNUMBER(SEARCH(_xlpm.phil, _xlpm.s)))>0, "Y", "N")))} -> N | U63: {=IF(M63="", "Unclassified", IF(AND(SUMPRODUCT(--ISNUMBER(SEARCH(REF_Setup!$B$3:$B$40,M63)))>0,SUMPRODUCT(--ISNUMBER(SEARCH(REF_Setup!$F$3:$F$15,M63)))>0),"Mixed",IF(SUMPRODUCT(--ISNUMBER(SEARCH(REF_Setup!$B$3:$B$40,M63)))>0,"Strategic Only",IF(SUMPRODUCT(--ISNUMBER(SEARCH(REF_Setup!$F$3:$F$15,M63)))>0,"VC Only","Unclassified"))))} -> VC Only
B64: =B63+1 -> 62 | C64: =IFERROR(_xlfn.XLOOKUP($B64,Raw_Data!$A$3:$A$273,Raw_Data!$B$3:$B$273),"") -> Dynami | D64: =IFERROR(_xlfn.XLOOKUP($B64,Raw_Data!$A$3:$A$273,Raw_Data!$C$3:$C$273),"") -> Binghamton, NY | E64: =IFERROR(_xlfn.XLOOKUP($B64,Raw_Data!$A$3:$A$273,Raw_Data!$D$3:$D$273),"") -> 2019 | F64: =IFERROR(_xlfn.XLOOKUP($B64,Raw_Data!$A$3:$A$273,Raw_Data!$F$3:$F$273),"") -> LDES | G64: =IFERROR(_xlfn.XLOOKUP($B64,Raw_Data!$A$3:$A$273,Raw_Data!$J$3:$J$273),"") -> 44769 | H64: Seed | I64: =IFERROR(_xlfn.XLOOKUP($B64,Raw_Data!$A$3:$A$273,Raw_Data!$I$3:$I$273),"") -> 1.16 | J64: =IFERROR(_xlfn.XLOOKUP($B64,Raw_Data!$A$3:$A$273,Raw_Data!$L$3:$L$273),"") -> 1 | K64: =IFERROR(_xlfn.XLOOKUP($B64,Raw_Data!$A$3:$A$273,Raw_Data!$M$3:$M$273),"") -> 5.5 | L64: =IFERROR(_xlfn.XLOOKUP($B64,Raw_Data!$A$3:$A$273,Raw_Data!$Q$3:$Q$273),"") -> 0 | M64: =IFERROR(_xlfn.XLOOKUP($B64,Raw_Data!$A$3:$A$273,Raw_Data!$R$3:$R$273),"") -> Beresford Ventures; Draper Cygnus; Ecosphere Ventures; Globalive Capital; Murchison Capital Partners; Murchison Ventures; Threshold Impact; William Tunstall-Pedoe | N64: {=IF(M64="",0,COUNTA(_xlfn._xlws.FILTER(_xlfn.TEXTSPLIT(M64,";"), _xlfn.TEXTSPLIT(M64,";")<>"")))} -> 8 | O64: =IF(P64>0,"Y","N") -> Y | P64: =IFERROR(_xlfn.XLOOKUP($B64,Raw_Data!$A$3:$A$273,Raw_Data!$V$3:$V$273),"") -> 0.125 | Q64: =IF(R64>0,"Y","N") -> Y | R64: =IFERROR(_xlfn.XLOOKUP($B64,Raw_Data!$A$3:$A$273,Raw_Data!$Y$3:$Y$273),"") -> 0.875 | S64: {=_xlfn.LET(_xlpm.s, Raw_Data!W64,_xlpm.strat, _xlfn._xlws.FILTER(REF_Setup!$B$3:$B$40, REF_Setup!$B$3:$B$40<>""),IF(OR(_xlpm.s="",_xlpm.s=0),"Unclassified",IF(SUM(--ISNUMBER(SEARCH(_xlpm.strat, _xlpm.s)))>0, "Y", "N")) )} -> N | T64: {=_xlfn.LET(_xlpm.s,M64,_xlpm.phil, _xlfn._xlws.FILTER(REF_Setup!$D$3:$D$5, REF_Setup!$D$3:$D$5<>""),IF(OR(_xlpm.s="", _xlpm.s=0),"Unclassified",IF(SUM(--ISNUMBER(SEARCH(_xlpm.phil, _xlpm.s)))>0, "Y", "N")))} -> N | U64: {=IF(M64="", "Unclassified", IF(AND(SUMPRODUCT(--ISNUMBER(SEARCH(REF_Setup!$B$3:$B$40,M64)))>0,SUMPRODUCT(--ISNUMBER(SEARCH(REF_Setup!$F$3:$F$15,M64)))>0),"Mixed",IF(SUMPRODUCT(--ISNUMBER(SEARCH(REF_Setup!$B$3:$B$40,M64)))>0,"Strategic Only",IF(SUMPRODUCT(--ISNUMBER(SEARCH(REF_Setup!$F$3:$F$15,M64)))>0,"VC Only","Unclassified"))))} -> VC Only
B65: =B64+1 -> 63 | C65: =IFERROR(_xlfn.XLOOKUP($B65,Raw_Data!$A$3:$A$273,Raw_Data!$B$3:$B$273),"") -> e-Zinc | D65: =IFERROR(_xlfn.XLOOKUP($B65,Raw_Data!$A$3:$A$273,Raw_Data!$C$3:$C$273),"") -> Mississauga, Canada | E65: =IFERROR(_xlfn.XLOOKUP($B65,Raw_Data!$A$3:$A$273,Raw_Data!$D$3:$D$273),"") -> 2012 | F65: =IFERROR(_xlfn.XLOOKUP($B65,Raw_Data!$A$3:$A$273,Raw_Data!$F$3:$F$273),"") -> LDES | G65: =IFERROR(_xlfn.XLOOKUP($B65,Raw_Data!$A$3:$A$273,Raw_Data!$J$3:$J$273),"") -> 44974 | H65: Series A | I65: =IFERROR(_xlfn.XLOOKUP($B65,Raw_Data!$A$3:$A$273,Raw_Data!$I$3:$I$273),"") -> 27.73 | J65: =IFERROR(_xlfn.XLOOKUP($B65,Raw_Data!$A$3:$A$273,Raw_Data!$L$3:$L$273),"") -> 10 | K65: =IFERROR(_xlfn.XLOOKUP($B65,Raw_Data!$A$3:$A$273,Raw_Data!$M$3:$M$273),"") -> 0 | L65: =IFERROR(_xlfn.XLOOKUP($B65,Raw_Data!$A$3:$A$273,Raw_Data!$Q$3:$Q$273),"") -> 0 | M65: =IFERROR(_xlfn.XLOOKUP($B65,Raw_Data!$A$3:$A$273,Raw_Data!$R$3:$R$273),"") -> EDC Investments; Evok Innovations; Graphite Ventures; Mitsubishi Heavy Industries; Ultratech Capital Partners | N65: {=IF(M65="",0,COUNTA(_xlfn._xlws.FILTER(_xlfn.TEXTSPLIT(M65,";"), _xlfn.TEXTSPLIT(M65,";")<>"")))} -> 5 | O65: =IF(P65>0,"Y","N") -> N | P65: =IFERROR(_xlfn.XLOOKUP($B65,Raw_Data!$A$3:$A$273,Raw_Data!$V$3:$V$273),"") -> 0 | Q65: =IF(R65>0,"Y","N") -> Y | R65: =IFERROR(_xlfn.XLOOKUP($B65,Raw_Data!$A$3:$A$273,Raw_Data!$Y$3:$Y$273),"") -> 1 | S65: {=_xlfn.LET(_xlpm.s, Raw_Data!W65,_xlpm.strat, _xlfn._xlws.FILTER(REF_Setup!$B$3:$B$40, REF_Setup!$B$3:$B$40<>""),IF(OR(_xlpm.s="",_xlpm.s=0),"Unclassified",IF(SUM(--ISNUMBER(SEARCH(_xlpm.strat, _xlpm.s)))>0, "Y", "N")) )} -> Y | T65: {=_xlfn.LET(_xlpm.s,M65,_xlpm.phil, _xlfn._xlws.FILTER(REF_Setup!$D$3:$D$5, REF_Setup!$D$3:$D$5<>""),IF(OR(_xlpm.s="", _xlpm.s=0),"Unclassified",IF(SUM(--ISNUMBER(SEARCH(_xlpm.phil, _xlpm.s)))>0, "Y", "N")))} -> N | U65: {=IF(M65="", "Unclassified", IF(AND(SUMPRODUCT(--ISNUMBER(SEARCH(REF_Setup!$B$3:$B$40,M65)))>0,SUMPRODUCT(--ISNUMBER(SEARCH(REF_Setup!$F$3:$F$15,M65)))>0),"Mixed",IF(SUMPRODUCT(--ISNUMBER(SEARCH(REF_Setup!$B$3:$B$40,M65)))>0,"Strategic Only",IF(SUMPRODUCT(--ISNUMBER(SEARCH(REF_Setup!$F$3:$F$15,M65)))>0,"VC Only","Unclassified"))))} -> Mixed
B66: =B65+1 -> 64 | C66: =IFERROR(_xlfn.XLOOKUP($B66,Raw_Data!$A$3:$A$273,Raw_Data!$B$3:$B$273),"") -> EarthGrid | D66: =IFERROR(_xlfn.XLOOKUP($B66,Raw_Data!$A$3:$A$273,Raw_Data!$C$3:$C$273),"") -> Richmond, CA | E66: =IFERROR(_xlfn.XLOOKUP($B66,Raw_Data!$A$3:$A$273,Raw_Data!$D$3:$D$273),"") -> 2016 | F66: =IFERROR(_xlfn.XLOOKUP($B66,Raw_Data!$A$3:$A$273,Raw_Data!$F$3:$F$273),"") -> Renewables | G66: =IFERROR(_xlfn.XLOOKUP($B66,Raw_Data!$A$3:$A$273,Raw_Data!$J$3:$J$273),"") -> 44196 | I66: =IFERROR(_xlfn.XLOOKUP($B66,Raw_Data!$A$3:$A$273,Raw_Data!$I$3:$I$273),"") -> 63 | J66: =IFERROR(_xlfn.XLOOKUP($B66,Raw_Data!$A$3:$A$273,Raw_Data!$L$3:$L$273),"") -> 63 | K66: =IFERROR(_xlfn.XLOOKUP($B66,Raw_Data!$A$3:$A$273,Raw_Data!$M$3:$M$273),"") -> 90 | L66: =IFERROR(_xlfn.XLOOKUP($B66,Raw_Data!$A$3:$A$273,Raw_Data!$Q$3:$Q$273),"") -> 0 | M66: =IFERROR(_xlfn.XLOOKUP($B66,Raw_Data!$A$3:$A$273,Raw_Data!$R$3:$R$273),"") -> Green Reach | N66: {=IF(M66="",0,COUNTA(_xlfn._xlws.FILTER(_xlfn.TEXTSPLIT(M66,";"), _xlfn.TEXTSPLIT(M66,";")<>"")))} -> 1 | O66: =IF(P66>0,"Y","N") -> N | P66: =IFERROR(_xlfn.XLOOKUP($B66,Raw_Data!$A$3:$A$273,Raw_Data!$V$3:$V$273),"") -> 0 | Q66: =IF(R66>0,"Y","N") -> Y | R66: =IFERROR(_xlfn.XLOOKUP($B66,Raw_Data!$A$3:$A$273,Raw_Data!$Y$3:$Y$273),"") -> 1 | S66: {=_xlfn.LET(_xlpm.s, Raw_Data!W66,_xlpm.strat, _xlfn._xlws.FILTER(REF_Setup!$B$3:$B$40, REF_Setup!$B$3:$B$40<>""),IF(OR(_xlpm.s="",_xlpm.s=0),"Unclassified",IF(SUM(--ISNUMBER(SEARCH(_xlpm.strat, _xlpm.s)))>0, "Y", "N")) )} -> N | T66: {=_xlfn.LET(_xlpm.s,M66,_xlpm.phil, _xlfn._xlws.FILTER(REF_Setup!$D$3:$D$5, REF_Setup!$D$3:$D$5<>""),IF(OR(_xlpm.s="", _xlpm.s=0),"Unclassified",IF(SUM(--ISNUMBER(SEARCH(_xlpm.phil, _xlpm.s)))>0, "Y", "N")))} -> N | U66: {=IF(M66="", "Unclassified", IF(AND(SUMPRODUCT(--ISNUMBER(SEARCH(REF_Setup!$B$3:$B$40,M66)))>0,SUMPRODUCT(--ISNUMBER(SEARCH(REF_Setup!$F$3:$F$15,M66)))>0),"Mixed",IF(SUMPRODUCT(--ISNUMBER(SEARCH(REF_Setup!$B$3:$B$40,M66)))>0,"Strategic Only",IF(SUMPRODUCT(--ISNUMBER(SEARCH(REF_Setup!$F$3:$F$15,M66)))>0,"VC Only","Unclassified"))))} -> Unclassified
B67: =B66+1 -> 65 | C67: =IFERROR(_xlfn.XLOOKUP($B67,Raw_Data!$A$3:$A$273,Raw_Data!$B$3:$B$273),"") -> Ebb Carbon | D67: =IFERROR(_xlfn.XLOOKUP($B67,Raw_Data!$A$3:$A$273,Raw_Data!$C$3:$C$273),"") -> South San Francisco, CA | E67: =IFERROR(_xlfn.XLOOKUP($B67,Raw_Data!$A$3:$A$273,Raw_Data!$D$3:$D$273),"") -> 2021 | F67: =IFERROR(_xlfn.XLOOKUP($B67,Raw_Data!$A$3:$A$273,Raw_Data!$F$3:$F$273),"") -> CDR | G67: =IFERROR(_xlfn.XLOOKUP($B67,Raw_Data!$A$3:$A$273,Raw_Data!$J$3:$J$273),"") -> 45595 | H67: Series A | I67: =IFERROR(_xlfn.XLOOKUP($B67,Raw_Data!$A$3:$A$273,Raw_Data!$I$3:$I$273),"") -> 24.75 | J67: =IFERROR(_xlfn.XLOOKUP($B67,Raw_Data!$A$3:$A$273,Raw_Data!$L$3:$L$273),"") -> 11 | K67: =IFERROR(_xlfn.XLOOKUP($B67,Raw_Data!$A$3:$A$273,Raw_Data!$M$3:$M$273),"") -> 85 | L67: =IFERROR(_xlfn.XLOOKUP($B67,Raw_Data!$A$3:$A$273,Raw_Data!$Q$3:$Q$273),"") -> 0 | M67: =IFERROR(_xlfn.XLOOKUP($B67,Raw_Data!$A$3:$A$273,Raw_Data!$R$3:$R$273),"") -> Chan Zuckerberg Initiative; Cisco Foundation; Congruent Ventures; Course Correction Capital; Elemental Impact; Evok Innovations; Neglected Climate Opportunities; Prelude Ventures; PRIME Coalition; Propeller; The Grantham Foundation | N67: {=IF(M67="",0,COUNTA(_xlfn._xlws.FILTER(_xlfn.TEXTSPLIT(M67,";"), _xlfn.TEXTSPLIT(M67,";")<>"")))} -> 11 | O67: =IF(P67>0,"Y","N") -> Y | P67: =IFERROR(_xlfn.XLOOKUP($B67,Raw_Data!$A$3:$A$273,Raw_Data!$V$3:$V$273),"") -> 0.45454545 | Q67: =IF(R67>0,"Y","N") -> Y | R67: =IFERROR(_xlfn.XLOOKUP($B67,Raw_Data!$A$3:$A$273,Raw_Data!$Y$3:$Y$273),"") -> 0.63636364 | S67: {=_xlfn.LET(_xlpm.s, Raw_Data!W67,_xlpm.strat, _xlfn._xlws.FILTER(REF_Setup!$B$3:$B$40, REF_Setup!$B$3:$B$40<>""),IF(OR(_xlpm.s="",_xlpm.s=0),"Unclassified",IF(SUM(--ISNUMBER(SEARCH(_xlpm.strat, _xlpm.s)))>0, "Y", "N")) )} -> N | T67: {=_xlfn.LET(_xlpm.s,M67,_xlpm.phil, _xlfn._xlws.FILTER(REF_Setup!$D$3:$D$5, REF_Setup!$D$3:$D$5<>""),IF(OR(_xlpm.s="", _xlpm.s=0),"Unclassified",IF(SUM(--ISNUMBER(SEARCH(_xlpm.phil, _xlpm.s)))>0, "Y", "N")))} -> Y | U67: {=IF(M67="", "Unclassified", IF(AND(SUMPRODUCT(--ISNUMBER(SEARCH(REF_Setup!$B$3:$B$40,M67)))>0,SUMPRODUCT(--ISNUMBER(SEARCH(REF_Setup!$F$3:$F$15,M67)))>0),"Mixed",IF(SUMPRODUCT(--ISNUMBER(SEARCH(REF_Setup!$B$3:$B$40,M67)))>0,"Strategic Only",IF(SUMPRODUCT(--ISNUMBER(SEARCH(REF_Setup!$F$3:$F$15,M67)))>0,"VC Only","Unclassified"))))} -> VC Only
B68: =B67+1 -> 66 | C68: =IFERROR(_xlfn.XLOOKUP($B68,Raw_Data!$A$3:$A$273,Raw_Data!$B$3:$B$273),"") -> Eco Carbon | D68: =IFERROR(_xlfn.XLOOKUP($B68,Raw_Data!$A$3:$A$273,Raw_Data!$C$3:$C$273),"") -> Bala Cynwyd, PA | E68: =IFERROR(_xlfn.XLOOKUP($B68,Raw_Data!$A$3:$A$273,Raw_Data!$D$3:$D$273),"") -> 2022 | F68: =IFERROR(_xlfn.XLOOKUP($B68,Raw_Data!$A$3:$A$273,Raw_Data!$F$3:$F$273),"") -> Industrial Decarbonization | G68: =IFERROR(_xlfn.XLOOKUP($B68,Raw_Data!$A$3:$A$273,Raw_Data!$J$3:$J$273),"") -> 45292 | H68: Angel | I68: =IFERROR(_xlfn.XLOOKUP($B68,Raw_Data!$A$3:$A$273,Raw_Data!$I$3:$I$273),"") -> 1.32 | J68: =IFERROR(_xlfn.XLOOKUP($B68,Raw_Data!$A$3:$A$273,Raw_Data!$L$3:$L$273),"") -> 1.32 | K68: =IFERROR(_xlfn.XLOOKUP($B68,Raw_Data!$A$3:$A$273,Raw_Data!$M$3:$M$273),"") -> 10 | L68: =IFERROR(_xlfn.XLOOKUP($B68,Raw_Data!$A$3:$A$273,Raw_Data!$Q$3:$Q$273),"") -> 0 | N68: {=IF(M68="",0,COUNTA(_xlfn._xlws.FILTER(_xlfn.TEXTSPLIT(M68,";"), _xlfn.TEXTSPLIT(M68,";")<>"")))} -> 0 | O68: =IF(P68>0,"Y","N") -> Y | P68: =IFERROR(_xlfn.XLOOKUP($B68,Raw_Data!$A$3:$A$273,Raw_Data!$V$3:$V$273),"") -> N/A | Q68: =IF(R68>0,"Y","N") -> Y | R68: =IFERROR(_xlfn.XLOOKUP($B68,Raw_Data!$A$3:$A$273,Raw_Data!$Y$3:$Y$273),"") -> N/A | S68: {=_xlfn.LET(_xlpm.s, Raw_Data!W68,_xlpm.strat, _xlfn._xlws.FILTER(REF_Setup!$B$3:$B$40, REF_Setup!$B$3:$B$40<>""),IF(OR(_xlpm.s="",_xlpm.s=0),"Unclassified",IF(SUM(--ISNUMBER(SEARCH(_xlpm.strat, _xlpm.s)))>0, "Y", "N")) )} -> Unclassified | T68: {=_xlfn.LET(_xlpm.s,M68,_xlpm.phil, _xlfn._xlws.FILTER(REF_Setup!$D$3:$D$5, REF_Setup!$D$3:$D$5<>""),IF(OR(_xlpm.s="", _xlpm.s=0),"Unclassified",IF(SUM(--ISNUMBER(SEARCH(_xlpm.phil, _xlpm.s)))>0, "Y", "N")))} -> Unclassified | U68: {=IF(M68="", "Unclassified", IF(AND(SUMPRODUCT(--ISNUMBER(SEARCH(REF_Setup!$B$3:$B$40,M68)))>0,SUMPRODUCT(--ISNUMBER(SEARCH(REF_Setup!$F$3:$F$15,M68)))>0),"Mixed",IF(SUMPRODUCT(--ISNUMBER(SEARCH(REF_Setup!$B$3:$B$40,M68)))>0,"Strategic Only",IF(SUMPRODUCT(--ISNUMBER(SEARCH(REF_Setup!$F$3:$F$15,M68)))>0,"VC Only","Unclassified"))))} -> Unclassified
B69: =B68+1 -> 67 | C69: =IFERROR(_xlfn.XLOOKUP($B69,Raw_Data!$A$3:$A$273,Raw_Data!$B$3:$B$273),"") -> EGI Battery | D69: =IFERROR(_xlfn.XLOOKUP($B69,Raw_Data!$A$3:$A$273,Raw_Data!$C$3:$C$273),"") -> Ann Arbor, MI | E69: =IFERROR(_xlfn.XLOOKUP($B69,Raw_Data!$A$3:$A$273,Raw_Data!$D$3:$D$273),"") -> 2012 | F69: =IFERROR(_xlfn.XLOOKUP($B69,Raw_Data!$A$3:$A$273,Raw_Data!$F$3:$F$273),"") -> LDES | G69: =IFERROR(_xlfn.XLOOKUP($B69,Raw_Data!$A$3:$A$273,Raw_Data!$J$3:$J$273),"") -> 44749 | H69: Series A | I69: =IFERROR(_xlfn.XLOOKUP($B69,Raw_Data!$A$3:$A$273,Raw_Data!$I$3:$I$273),"") -> 50.72 | J69: =IFERROR(_xlfn.XLOOKUP($B69,Raw_Data!$A$3:$A$273,Raw_Data!$L$3:$L$273),"") -> 35 | K69: =IFERROR(_xlfn.XLOOKUP($B69,Raw_Data!$A$3:$A$273,Raw_Data!$M$3:$M$273),"") -> 0 | L69: =IFERROR(_xlfn.XLOOKUP($B69,Raw_Data!$A$3:$A$273,Raw_Data!$Q$3:$Q$273),"") -> 0 | M69: =IFERROR(_xlfn.XLOOKUP($B69,Raw_Data!$A$3:$A$273,Raw_Data!$R$3:$R$273),"") -> Borun Capital (Xiamen); BR Capital; Dayone Capital; GAC Capital; Hongshan Capital Group; Niuli Venture; Tianqi Capital; Unreasonable Impact | N69: {=IF(M69="",0,COUNTA(_xlfn._xlws.FILTER(_xlfn.TEXTSPLIT(M69,";"), _xlfn.TEXTSPLIT(M69,";")<>"")))} -> 8 | O69: =IF(P69>0,"Y","N") -> Y | P69: =IFERROR(_xlfn.XLOOKUP($B69,Raw_Data!$A$3:$A$273,Raw_Data!$V$3:$V$273),"") -> 0.125 | Q69: =IF(R69>0,"Y","N") -> Y | R69: =IFERROR(_xlfn.XLOOKUP($B69,Raw_Data!$A$3:$A$273,Raw_Data!$Y$3:$Y$273),"") -> 1 | S69: {=_xlfn.LET(_xlpm.s, Raw_Data!W69,_xlpm.strat, _xlfn._xlws.FILTER(REF_Setup!$B$3:$B$40, REF_Setup!$B$3:$B$40<>""),IF(OR(_xlpm.s="",_xlpm.s=0),"Unclassified",IF(SUM(--ISNUMBER(SEARCH(_xlpm.strat, _xlpm.s)))>0, "Y", "N")) )} -> N | T69: {=_xlfn.LET(_xlpm.s,M69,_xlpm.phil, _xlfn._xlws.FILTER(REF_Setup!$D$3:$D$5, REF_Setup!$D$3:$D$5<>""),IF(OR(_xlpm.s="", _xlpm.s=0),"Unclassified",IF(SUM(--ISNUMBER(SEARCH(_xlpm.phil, _xlpm.s)))>0, "Y", "N")))} -> N | U69: {=IF(M69="", "Unclassified", IF(AND(SUMPRODUCT(--ISNUMBER(SEARCH(REF_Setup!$B$3:$B$40,M69)))>0,SUMPRODUCT(--ISNUMBER(SEARCH(REF_Setup!$F$3:$F$15,M69)))>0),"Mixed",IF(SUMPRODUCT(--ISNUMBER(SEARCH(REF_Setup!$B$3:$B$40,M69)))>0,"Strategic Only",IF(SUMPRODUCT(--ISNUMBER(SEARCH(REF_Setup!$F$3:$F$15,M69)))>0,"VC Only","Unclassified"))))} -> VC Only
B70: =B69+1 -> 68 | C70: =IFERROR(_xlfn.XLOOKUP($B70,Raw_Data!$A$3:$A$273,Raw_Data!$B$3:$B$273),"") -> Emission Free Generators | D70: =IFERROR(_xlfn.XLOOKUP($B70,Raw_Data!$A$3:$A$273,Raw_Data!$C$3:$C$273),"") -> San Diego, CA | E70: =IFERROR(_xlfn.XLOOKUP($B70,Raw_Data!$A$3:$A$273,Raw_Data!$D$3:$D$273),"") -> 2022 | F70: =IFERROR(_xlfn.XLOOKUP($B70,Raw_Data!$A$3:$A$273,Raw_Data!$F$3:$F$273),"") -> Hydrogen | G70: =IFERROR(_xlfn.XLOOKUP($B70,Raw_Data!$A$3:$A$273,Raw_Data!$J$3:$J$273),"") -> 45473 | H70: Seed | I70: =IFERROR(_xlfn.XLOOKUP($B70,Raw_Data!$A$3:$A$273,Raw_Data!$I$3:$I$273),"") -> 0.43 | J70: =IFERROR(_xlfn.XLOOKUP($B70,Raw_Data!$A$3:$A$273,Raw_Data!$L$3:$L$273),"") -> 0.18 | K70: =IFERROR(_xlfn.XLOOKUP($B70,Raw_Data!$A$3:$A$273,Raw_Data!$M$3:$M$273),"") -> 0 | L70: =IFERROR(_xlfn.XLOOKUP($B70,Raw_Data!$A$3:$A$273,Raw_Data!$Q$3:$Q$273),"") -> 0 | N70: {=IF(M70="",0,COUNTA(_xlfn._xlws.FILTER(_xlfn.TEXTSPLIT(M70,";"), _xlfn.TEXTSPLIT(M70,";")<>"")))} -> 0 | O70: =IF(P70>0,"Y","N") -> Y | P70: =IFERROR(_xlfn.XLOOKUP($B70,Raw_Data!$A$3:$A$273,Raw_Data!$V$3:$V$273),"") -> N/A | Q70: =IF(R70>0,"Y","N") -> Y | R70: =IFERROR(_xlfn.XLOOKUP($B70,Raw_Data!$A$3:$A$273,Raw_Data!$Y$3:$Y$273),"") -> N/A | S70: {=_xlfn.LET(_xlpm.s, Raw_Data!W70,_xlpm.strat, _xlfn._xlws.FILTER(REF_Setup!$B$3:$B$40, REF_Setup!$B$3:$B$40<>""),IF(OR(_xlpm.s="",_xlpm.s=0),"Unclassified",IF(SUM(--ISNUMBER(SEARCH(_xlpm.strat, _xlpm.s)))>0, "Y", "N")) )} -> Unclassified | T70: {=_xlfn.LET(_xlpm.s,M70,_xlpm.phil, _xlfn._xlws.FILTER(REF_Setup!$D$3:$D$5, REF_Setup!$D$3:$D$5<>""),IF(OR(_xlpm.s="", _xlpm.s=0),"Unclassified",IF(SUM(--ISNUMBER(SEARCH(_xlpm.phil, _xlpm.s)))>0, "Y", "N")))} -> Unclassified | U70: {=IF(M70="", "Unclassified", IF(AND(SUMPRODUCT(--ISNUMBER(SEARCH(REF_Setup!$B$3:$B$40,M70)))>0,SUMPRODUCT(--ISNUMBER(SEARCH(REF_Setup!$F$3:$F$15,M70)))>0),"Mixed",IF(SUMPRODUCT(--ISNUMBER(SEARCH(REF_Setup!$B$3:$B$40,M70)))>0,"Strategic Only",IF(SUMPRODUCT(--ISNUMBER(SEARCH(REF_Setup!$F$3:$F$15,M70)))>0,"VC Only","Unclassified"))))} -> Unclassified
B71: =B70+1 -> 69 | C71: =IFERROR(_xlfn.XLOOKUP($B71,Raw_Data!$A$3:$A$273,Raw_Data!$B$3:$B$273),"") -> Emrgy | D71: =IFERROR(_xlfn.XLOOKUP($B71,Raw_Data!$A$3:$A$273,Raw_Data!$C$3:$C$273),"") -> Atlanta, GA | E71: =IFERROR(_xlfn.XLOOKUP($B71,Raw_Data!$A$3:$A$273,Raw_Data!$D$3:$D$273),"") -> 2014 | F71: =IFERROR(_xlfn.XLOOKUP($B71,Raw_Data!$A$3:$A$273,Raw_Data!$F$3:$F$273),"") -> Renewables | G71: =IFERROR(_xlfn.XLOOKUP($B71,Raw_Data!$A$3:$A$273,Raw_Data!$J$3:$J$273),"") -> 45261 | H71: Development capital | I71: =IFERROR(_xlfn.XLOOKUP($B71,Raw_Data!$A$3:$A$273,Raw_Data!$I$3:$I$273),"") -> 36.67 | J71: =IFERROR(_xlfn.XLOOKUP($B71,Raw_Data!$A$3:$A$273,Raw_Data!$L$3:$L$273),"") -> 0 | K71: =IFERROR(_xlfn.XLOOKUP($B71,Raw_Data!$A$3:$A$273,Raw_Data!$M$3:$M$273),"") -> 0 | L71: =IFERROR(_xlfn.XLOOKUP($B71,Raw_Data!$A$3:$A$273,Raw_Data!$Q$3:$Q$273),"") -> N/A | M71: =IFERROR(_xlfn.XLOOKUP($B71,Raw_Data!$A$3:$A$273,Raw_Data!$R$3:$R$273),"") -> KRF capital | N71: {=IF(M71="",0,COUNTA(_xlfn._xlws.FILTER(_xlfn.TEXTSPLIT(M71,";"), _xlfn.TEXTSPLIT(M71,";")<>"")))} -> 1 | O71: =IF(P71>0,"Y","N") -> N | P71: =IFERROR(_xlfn.XLOOKUP($B71,Raw_Data!$A$3:$A$273,Raw_Data!$V$3:$V$273),"") -> 0 | Q71: =IF(R71>0,"Y","N") -> Y | R71: =IFERROR(_xlfn.XLOOKUP($B71,Raw_Data!$A$3:$A$273,Raw_Data!$Y$3:$Y$273),"") -> 1 | S71: {=_xlfn.LET(_xlpm.s, Raw_Data!W71,_xlpm.strat, _xlfn._xlws.FILTER(REF_Setup!$B$3:$B$40, REF_Setup!$B$3:$B$40<>""),IF(OR(_xlpm.s="",_xlpm.s=0),"Unclassified",IF(SUM(--ISNUMBER(SEARCH(_xlpm.strat, _xlpm.s)))>0, "Y", "N")) )} -> N | T71: {=_xlfn.LET(_xlpm.s,M71,_xlpm.phil, _xlfn._xlws.FILTER(REF_Setup!$D$3:$D$5, REF_Setup!$D$3:$D$5<>""),IF(OR(_xlpm.s="", _xlpm.s=0),"Unclassified",IF(SUM(--ISNUMBER(SEARCH(_xlpm.phil, _xlpm.s)))>0, "Y", "N")))} -> N | U71: {=IF(M71="", "Unclassified", IF(AND(SUMPRODUCT(--ISNUMBER(SEARCH(REF_Setup!$B$3:$B$40,M71)))>0,SUMPRODUCT(--ISNUMBER(SEARCH(REF_Setup!$F$3:$F$15,M71)))>0),"Mixed",IF(SUMPRODUCT(--ISNUMBER(SEARCH(REF_Setup!$B$3:$B$40,M71)))>0,"Strategic Only",IF(SUMPRODUCT(--ISNUMBER(SEARCH(REF_Setup!$F$3:$F$15,M71)))>0,"VC Only","Unclassified"))))} -> VC Only
B72: =B71+1 -> 70 | C72: =IFERROR(_xlfn.XLOOKUP($B72,Raw_Data!$A$3:$A$273,Raw_Data!$B$3:$B$273),"") -> Emrgy | D72: =IFERROR(_xlfn.XLOOKUP($B72,Raw_Data!$A$3:$A$273,Raw_Data!$C$3:$C$273),"") -> Atlanta, GA | E72: =IFERROR(_xlfn.XLOOKUP($B72,Raw_Data!$A$3:$A$273,Raw_Data!$D$3:$D$273),"") -> 2014 | F72: =IFERROR(_xlfn.XLOOKUP($B72,Raw_Data!$A$3:$A$273,Raw_Data!$F$3:$F$273),"") -> Renewables | G72: =IFERROR(_xlfn.XLOOKUP($B72,Raw_Data!$A$3:$A$273,Raw_Data!$J$3:$J$273),"") -> 45657 | H72: Development capital | I72: =IFERROR(_xlfn.XLOOKUP($B72,Raw_Data!$A$3:$A$273,Raw_Data!$I$3:$I$273),"") -> 3771 | J72: =IFERROR(_xlfn.XLOOKUP($B72,Raw_Data!$A$3:$A$273,Raw_Data!$L$3:$L$273),"") -> 1.04 | K72: =IFERROR(_xlfn.XLOOKUP($B72,Raw_Data!$A$3:$A$273,Raw_Data!$M$3:$M$273),"") -> 0 | L72: =IFERROR(_xlfn.XLOOKUP($B72,Raw_Data!$A$3:$A$273,Raw_Data!$Q$3:$Q$273),"") -> 0 | M72: =IFERROR(_xlfn.XLOOKUP($B72,Raw_Data!$A$3:$A$273,Raw_Data!$R$3:$R$273),"") -> Treehouse Investments | N72: {=IF(M72="",0,COUNTA(_xlfn._xlws.FILTER(_xlfn.TEXTSPLIT(M72,";"), _xlfn.TEXTSPLIT(M72,";")<>"")))} -> 1 | O72: =IF(P72>0,"Y","N") -> N | P72: =IFERROR(_xlfn.XLOOKUP($B72,Raw_Data!$A$3:$A$273,Raw_Data!$V$3:$V$273),"") -> 0 | Q72: =IF(R72>0,"Y","N") -> Y | R72: =IFERROR(_xlfn.XLOOKUP($B72,Raw_Data!$A$3:$A$273,Raw_Data!$Y$3:$Y$273),"") -> 1 | S72: {=_xlfn.LET(_xlpm.s, Raw_Data!W72,_xlpm.strat, _xlfn._xlws.FILTER(REF_Setup!$B$3:$B$40, REF_Setup!$B$3:$B$40<>""),IF(OR(_xlpm.s="",_xlpm.s=0),"Unclassified",IF(SUM(--ISNUMBER(SEARCH(_xlpm.strat, _xlpm.s)))>0, "Y", "N")) )} -> N | T72: {=_xlfn.LET(_xlpm.s,M72,_xlpm.phil, _xlfn._xlws.FILTER(REF_Setup!$D$3:$D$5, REF_Setup!$D$3:$D$5<>""),IF(OR(_xlpm.s="", _xlpm.s=0),"Unclassified",IF(SUM(--ISNUMBER(SEARCH(_xlpm.phil, _xlpm.s)))>0, "Y", "N")))} -> N | U72: {=IF(M72="", "Unclassified", IF(AND(SUMPRODUCT(--ISNUMBER(SEARCH(REF_Setup!$B$3:$B$40,M72)))>0,SUMPRODUCT(--ISNUMBER(SEARCH(REF_Setup!$F$3:$F$15,M72)))>0),"Mixed",IF(SUMPRODUCT(--ISNUMBER(SEARCH(REF_Setup!$B$3:$B$40,M72)))>0,"Strategic Only",IF(SUMPRODUCT(--ISNUMBER(SEARCH(REF_Setup!$F$3:$F$15,M72)))>0,"VC Only","Unclassified"))))} -> Unclassified
B73: =B72+1 -> 71 | C73: =IFERROR(_xlfn.XLOOKUP($B73,Raw_Data!$A$3:$A$273,Raw_Data!$B$3:$B$273),"") -> Energy Dome | D73: =IFERROR(_xlfn.XLOOKUP($B73,Raw_Data!$A$3:$A$273,Raw_Data!$C$3:$C$273),"") -> Milan, Italy | E73: =IFERROR(_xlfn.XLOOKUP($B73,Raw_Data!$A$3:$A$273,Raw_Data!$D$3:$D$273),"") -> 2019 | F73: =IFERROR(_xlfn.XLOOKUP($B73,Raw_Data!$A$3:$A$273,Raw_Data!$F$3:$F$273),"") -> LDES | G73: =IFERROR(_xlfn.XLOOKUP($B73,Raw_Data!$A$3:$A$273,Raw_Data!$J$3:$J$273),"") -> 45866 | I73: =IFERROR(_xlfn.XLOOKUP($B73,Raw_Data!$A$3:$A$273,Raw_Data!$I$3:$I$273),"") -> 120.86 | J73: =IFERROR(_xlfn.XLOOKUP($B73,Raw_Data!$A$3:$A$273,Raw_Data!$L$3:$L$273),"") -> 0 | K73: =IFERROR(_xlfn.XLOOKUP($B73,Raw_Data!$A$3:$A$273,Raw_Data!$M$3:$M$273),"") -> 0 | L73: =IFERROR(_xlfn.XLOOKUP($B73,Raw_Data!$A$3:$A$273,Raw_Data!$Q$3:$Q$273),"") -> N/A | M73: =IFERROR(_xlfn.XLOOKUP($B73,Raw_Data!$A$3:$A$273,Raw_Data!$R$3:$R$273),"") -> Alphabet | N73: {=IF(M73="",0,COUNTA(_xlfn._xlws.FILTER(_xlfn.TEXTSPLIT(M73,";"), _xlfn.TEXTSPLIT(M73,";")<>"")))} -> 1 | O73: =IF(P73>0,"Y","N") -> N | P73: =IFERROR(_xlfn.XLOOKUP($B73,Raw_Data!$A$3:$A$273,Raw_Data!$V$3:$V$273),"") -> 0 | Q73: =IF(R73>0,"Y","N") -> Y | R73: =IFERROR(_xlfn.XLOOKUP($B73,Raw_Data!$A$3:$A$273,Raw_Data!$Y$3:$Y$273),"") -> 1 | S73: {=_xlfn.LET(_xlpm.s, Raw_Data!W73,_xlpm.strat, _xlfn._xlws.FILTER(REF_Setup!$B$3:$B$40, REF_Setup!$B$3:$B$40<>""),IF(OR(_xlpm.s="",_xlpm.s=0),"Unclassified",IF(SUM(--ISNUMBER(SEARCH(_xlpm.strat, _xlpm.s)))>0, "Y", "N")) )} -> Y | T73: {=_xlfn.LET(_xlpm.s,M73,_xlpm.phil, _xlfn._xlws.FILTER(REF_Setup!$D$3:$D$5, REF_Setup!$D$3:$D$5<>""),IF(OR(_xlpm.s="", _xlpm.s=0),"Unclassified",IF(SUM(--ISNUMBER(SEARCH(_xlpm.phil, _xlpm.s)))>0, "Y", "N")))} -> N | U73: {=IF(M73="", "Unclassified", IF(AND(SUMPRODUCT(--ISNUMBER(SEARCH(REF_Setup!$B$3:$B$40,M73)))>0,SUMPRODUCT(--ISNUMBER(SEARCH(REF_Setup!$F$3:$F$15,M73)))>0),"Mixed",IF(SUMPRODUCT(--ISNUMBER(SEARCH(REF_Setup!$B$3:$B$40,M73)))>0,"Strategic Only",IF(SUMPRODUCT(--ISNUMBER(SEARCH(REF_Setup!$F$3:$F$15,M73)))>0,"VC Only","Unclassified"))))} -> Strategic Only
B74: =B73+1 -> 72 | C74: =IFERROR(_xlfn.XLOOKUP($B74,Raw_Data!$A$3:$A$273,Raw_Data!$B$3:$B$273),"") -> EnGoPIanet Energy Solutions | D74: =IFERROR(_xlfn.XLOOKUP($B74,Raw_Data!$A$3:$A$273,Raw_Data!$C$3:$C$273),"") -> Houston, TX | E74: =IFERROR(_xlfn.XLOOKUP($B74,Raw_Data!$A$3:$A$273,Raw_Data!$D$3:$D$273),"") -> 2019 | F74: =IFERROR(_xlfn.XLOOKUP($B74,Raw_Data!$A$3:$A$273,Raw_Data!$F$3:$F$273),"") -> Renewables | G74: =IFERROR(_xlfn.XLOOKUP($B74,Raw_Data!$A$3:$A$273,Raw_Data!$J$3:$J$273),"") -> 45536 | H74: Development capital | I74: =IFERROR(_xlfn.XLOOKUP($B74,Raw_Data!$A$3:$A$273,Raw_Data!$I$3:$I$273),"") -> 0 | J74: =IFERROR(_xlfn.XLOOKUP($B74,Raw_Data!$A$3:$A$273,Raw_Data!$L$3:$L$273),"") -> 0 | K74: =IFERROR(_xlfn.XLOOKUP($B74,Raw_Data!$A$3:$A$273,Raw_Data!$M$3:$M$273),"") -> 0 | L74: =IFERROR(_xlfn.XLOOKUP($B74,Raw_Data!$A$3:$A$273,Raw_Data!$Q$3:$Q$273),"") -> N/A | M74: =IFERROR(_xlfn.XLOOKUP($B74,Raw_Data!$A$3:$A$273,Raw_Data!$R$3:$R$273),"") -> Longmont Capital | N74: {=IF(M74="",0,COUNTA(_xlfn._xlws.FILTER(_xlfn.TEXTSPLIT(M74,";"), _xlfn.TEXTSPLIT(M74,";")<>"")))} -> 1 | O74: =IF(P74>0,"Y","N") -> N | P74: =IFERROR(_xlfn.XLOOKUP($B74,Raw_Data!$A$3:$A$273,Raw_Data!$V$3:$V$273),"") -> 0 | Q74: =IF(R74>0,"Y","N") -> Y | R74: =IFERROR(_xlfn.XLOOKUP($B74,Raw_Data!$A$3:$A$273,Raw_Data!$Y$3:$Y$273),"") -> 1 | S74: {=_xlfn.LET(_xlpm.s, Raw_Data!W74,_xlpm.strat, _xlfn._xlws.FILTER(REF_Setup!$B$3:$B$40, REF_Setup!$B$3:$B$40<>""),IF(OR(_xlpm.s="",_xlpm.s=0),"Unclassified",IF(SUM(--ISNUMBER(SEARCH(_xlpm.strat, _xlpm.s)))>0, "Y", "N")) )} -> N | T74: {=_xlfn.LET(_xlpm.s,M74,_xlpm.phil, _xlfn._xlws.FILTER(REF_Setup!$D$3:$D$5, REF_Setup!$D$3:$D$5<>""),IF(OR(_xlpm.s="", _xlpm.s=0),"Unclassified",IF(SUM(--ISNUMBER(SEARCH(_xlpm.phil, _xlpm.s)))>0, "Y", "N")))} -> N | U74: {=IF(M74="", "Unclassified", IF(AND(SUMPRODUCT(--ISNUMBER(SEARCH(REF_Setup!$B$3:$B$40,M74)))>0,SUMPRODUCT(--ISNUMBER(SEARCH(REF_Setup!$F$3:$F$15,M74)))>0),"Mixed",IF(SUMPRODUCT(--ISNUMBER(SEARCH(REF_Setup!$B$3:$B$40,M74)))>0,"Strategic Only",IF(SUMPRODUCT(--ISNUMBER(SEARCH(REF_Setup!$F$3:$F$15,M74)))>0,"VC Only","Unclassified"))))} -> VC Only
B75: =B74+1 -> 73 | C75: =IFERROR(_xlfn.XLOOKUP($B75,Raw_Data!$A$3:$A$273,Raw_Data!$B$3:$B$273),"") -> Envocore | D75: =IFERROR(_xlfn.XLOOKUP($B75,Raw_Data!$A$3:$A$273,Raw_Data!$C$3:$C$273),"") -> Gambrills, MD | E75: =IFERROR(_xlfn.XLOOKUP($B75,Raw_Data!$A$3:$A$273,Raw_Data!$D$3:$D$273),"") -> 1993 | F75: =IFERROR(_xlfn.XLOOKUP($B75,Raw_Data!$A$3:$A$273,Raw_Data!$F$3:$F$273),"") -> Buildings | G75: =IFERROR(_xlfn.XLOOKUP($B75,Raw_Data!$A$3:$A$273,Raw_Data!$J$3:$J$273),"") -> 42641 | H75: Development capital | I75: =IFERROR(_xlfn.XLOOKUP($B75,Raw_Data!$A$3:$A$273,Raw_Data!$I$3:$I$273),"") -> 24 | J75: =IFERROR(_xlfn.XLOOKUP($B75,Raw_Data!$A$3:$A$273,Raw_Data!$L$3:$L$273),"") -> 0 | K75: =IFERROR(_xlfn.XLOOKUP($B75,Raw_Data!$A$3:$A$273,Raw_Data!$M$3:$M$273),"") -> 0 | L75: =IFERROR(_xlfn.XLOOKUP($B75,Raw_Data!$A$3:$A$273,Raw_Data!$Q$3:$Q$273),"") -> N/A | M75: =IFERROR(_xlfn.XLOOKUP($B75,Raw_Data!$A$3:$A$273,Raw_Data!$R$3:$R$273),"") -> Arborview Capital; Capital Southwest; DFW Capital Partners | N75: {=IF(M75="",0,COUNTA(_xlfn._xlws.FILTER(_xlfn.TEXTSPLIT(M75,";"), _xlfn.TEXTSPLIT(M75,";")<>"")))} -> 3 | O75: =IF(P75>0,"Y","N") -> Y | P75: =IFERROR(_xlfn.XLOOKUP($B75,Raw_Data!$A$3:$A$273,Raw_Data!$V$3:$V$273),"") -> 0.33333333 | Q75: =IF(R75>0,"Y","N") -> Y | R75: =IFERROR(_xlfn.XLOOKUP($B75,Raw_Data!$A$3:$A$273,Raw_Data!$Y$3:$Y$273),"") -> 0.66666667 | S75: {=_xlfn.LET(_xlpm.s, Raw_Data!W75,_xlpm.strat, _xlfn._xlws.FILTER(REF_Setup!$B$3:$B$40, REF_Setup!$B$3:$B$40<>""),IF(OR(_xlpm.s="",_xlpm.s=0),"Unclassified",IF(SUM(--ISNUMBER(SEARCH(_xlpm.strat, _xlpm.s)))>0, "Y", "N")) )} -> N | T75: {=_xlfn.LET(_xlpm.s,M75,_xlpm.phil, _xlfn._xlws.FILTER(REF_Setup!$D$3:$D$5, REF_Setup!$D$3:$D$5<>""),IF(OR(_xlpm.s="", _xlpm.s=0),"Unclassified",IF(SUM(--ISNUMBER(SEARCH(_xlpm.phil, _xlpm.s)))>0, "Y", "N")))} -> N | U75: {=IF(M75="", "Unclassified", IF(AND(SUMPRODUCT(--ISNUMBER(SEARCH(REF_Setup!$B$3:$B$40,M75)))>0,SUMPRODUCT(--ISNUMBER(SEARCH(REF_Setup!$F$3:$F$15,M75)))>0),"Mixed",IF(SUMPRODUCT(--ISNUMBER(SEARCH(REF_Setup!$B$3:$B$40,M75)))>0,"Strategic Only",IF(SUMPRODUCT(--ISNUMBER(SEARCH(REF_Setup!$F$3:$F$15,M75)))>0,"VC Only","Unclassified"))))} -> VC Only
B76: =B75+1 -> 74 | C76: =IFERROR(_xlfn.XLOOKUP($B76,Raw_Data!$A$3:$A$273,Raw_Data!$B$3:$B$273),"") -> Envocore | D76: =IFERROR(_xlfn.XLOOKUP($B76,Raw_Data!$A$3:$A$273,Raw_Data!$C$3:$C$273),"") -> Gambrills, MD | E76: =IFERROR(_xlfn.XLOOKUP($B76,Raw_Data!$A$3:$A$273,Raw_Data!$D$3:$D$273),"") -> 1993 | F76: =IFERROR(_xlfn.XLOOKUP($B76,Raw_Data!$A$3:$A$273,Raw_Data!$F$3:$F$273),"") -> Buildings | G76: =IFERROR(_xlfn.XLOOKUP($B76,Raw_Data!$A$3:$A$273,Raw_Data!$J$3:$J$273),"") -> 43368 | H76: Development capital | I76: =IFERROR(_xlfn.XLOOKUP($B76,Raw_Data!$A$3:$A$273,Raw_Data!$I$3:$I$273),"") -> 83.33 | J76: =IFERROR(_xlfn.XLOOKUP($B76,Raw_Data!$A$3:$A$273,Raw_Data!$L$3:$L$273),"") -> 8 | K76: =IFERROR(_xlfn.XLOOKUP($B76,Raw_Data!$A$3:$A$273,Raw_Data!$M$3:$M$273),"") -> 0 | L76: =IFERROR(_xlfn.XLOOKUP($B76,Raw_Data!$A$3:$A$273,Raw_Data!$Q$3:$Q$273),"") -> 0.485 | M76: =IFERROR(_xlfn.XLOOKUP($B76,Raw_Data!$A$3:$A$273,Raw_Data!$R$3:$R$273),"") -> Capital Southwest | N76: {=IF(M76="",0,COUNTA(_xlfn._xlws.FILTER(_xlfn.TEXTSPLIT(M76,";"), _xlfn.TEXTSPLIT(M76,";")<>"")))} -> 1 | O76: =IF(P76>0,"Y","N") -> Y | P76: =IFERROR(_xlfn.XLOOKUP($B76,Raw_Data!$A$3:$A$273,Raw_Data!$V$3:$V$273),"") -> 1 | Q76: =IF(R76>0,"Y","N") -> Y | R76: =IFERROR(_xlfn.XLOOKUP($B76,Raw_Data!$A$3:$A$273,Raw_Data!$Y$3:$Y$273),"") -> N/A | S76: {=_xlfn.LET(_xlpm.s, Raw_Data!W76,_xlpm.strat, _xlfn._xlws.FILTER(REF_Setup!$B$3:$B$40, REF_Setup!$B$3:$B$40<>""),IF(OR(_xlpm.s="",_xlpm.s=0),"Unclassified",IF(SUM(--ISNUMBER(SEARCH(_xlpm.strat, _xlpm.s)))>0, "Y", "N")) )} -> Unclassified | T76: {=_xlfn.LET(_xlpm.s,M76,_xlpm.phil, _xlfn._xlws.FILTER(REF_Setup!$D$3:$D$5, REF_Setup!$D$3:$D$5<>""),IF(OR(_xlpm.s="", _xlpm.s=0),"Unclassified",IF(SUM(--ISNUMBER(SEARCH(_xlpm.phil, _xlpm.s)))>0, "Y", "N")))} -> N | U76: {=IF(M76="", "Unclassified", IF(AND(SUMPRODUCT(--ISNUMBER(SEARCH(REF_Setup!$B$3:$B$40,M76)))>0,SUMPRODUCT(--ISNUMBER(SEARCH(REF_Setup!$F$3:$F$15,M76)))>0),"Mixed",IF(SUMPRODUCT(--ISNUMBER(SEARCH(REF_Setup!$B$3:$B$40,M76)))>0,"Strategic Only",IF(SUMPRODUCT(--ISNUMBER(SEARCH(REF_Setup!$F$3:$F$15,M76)))>0,"VC Only","Unclassified"))))} -> VC Only
B77: =B76+1 -> 75 | C77: =IFERROR(_xlfn.XLOOKUP($B77,Raw_Data!$A$3:$A$273,Raw_Data!$B$3:$B$273),"") -> EPC Power | D77: =IFERROR(_xlfn.XLOOKUP($B77,Raw_Data!$A$3:$A$273,Raw_Data!$C$3:$C$273),"") -> Poway, CA | E77: =IFERROR(_xlfn.XLOOKUP($B77,Raw_Data!$A$3:$A$273,Raw_Data!$D$3:$D$273),"") -> 2010 | F77: =IFERROR(_xlfn.XLOOKUP($B77,Raw_Data!$A$3:$A$273,Raw_Data!$F$3:$F$273),"") -> Renewables | G77: =IFERROR(_xlfn.XLOOKUP($B77,Raw_Data!$A$3:$A$273,Raw_Data!$J$3:$J$273),"") -> 44197 | H77: Development capital | I77: =IFERROR(_xlfn.XLOOKUP($B77,Raw_Data!$A$3:$A$273,Raw_Data!$I$3:$I$273),"") -> 4 | J77: =IFERROR(_xlfn.XLOOKUP($B77,Raw_Data!$A$3:$A$273,Raw_Data!$L$3:$L$273),"") -> 0 | K77: =IFERROR(_xlfn.XLOOKUP($B77,Raw_Data!$A$3:$A$273,Raw_Data!$M$3:$M$273),"") -> 0 | L77: =IFERROR(_xlfn.XLOOKUP($B77,Raw_Data!$A$3:$A$273,Raw_Data!$Q$3:$Q$273),"") -> N/A | M77: =IFERROR(_xlfn.XLOOKUP($B77,Raw_Data!$A$3:$A$273,Raw_Data!$R$3:$R$273),"") -> 13Capital; Cleanhill Partners; Goldman Sachs Asset Management | N77: {=IF(M77="",0,COUNTA(_xlfn._xlws.FILTER(_xlfn.TEXTSPLIT(M77,";"), _xlfn.TEXTSPLIT(M77,";")<>"")))} -> 3 | O77: =IF(P77>0,"Y","N") -> N | P77: =IFERROR(_xlfn.XLOOKUP($B77,Raw_Data!$A$3:$A$273,Raw_Data!$V$3:$V$273),"") -> 0 | Q77: =IF(R77>0,"Y","N") -> Y | R77: =IFERROR(_xlfn.XLOOKUP($B77,Raw_Data!$A$3:$A$273,Raw_Data!$Y$3:$Y$273),"") -> 1 | S77: {=_xlfn.LET(_xlpm.s, Raw_Data!W77,_xlpm.strat, _xlfn._xlws.FILTER(REF_Setup!$B$3:$B$40, REF_Setup!$B$3:$B$40<>""),IF(OR(_xlpm.s="",_xlpm.s=0),"Unclassified",IF(SUM(--ISNUMBER(SEARCH(_xlpm.strat, _xlpm.s)))>0, "Y", "N")) )} -> N | T77: {=_xlfn.LET(_xlpm.s,M77,_xlpm.phil, _xlfn._xlws.FILTER(REF_Setup!$D$3:$D$5, REF_Setup!$D$3:$D$5<>""),IF(OR(_xlpm.s="", _xlpm.s=0),"Unclassified",IF(SUM(--ISNUMBER(SEARCH(_xlpm.phil, _xlpm.s)))>0, "Y", "N")))} -> N | U77: {=IF(M77="", "Unclassified", IF(AND(SUMPRODUCT(--ISNUMBER(SEARCH(REF_Setup!$B$3:$B$40,M77)))>0,SUMPRODUCT(--ISNUMBER(SEARCH(REF_Setup!$F$3:$F$15,M77)))>0),"Mixed",IF(SUMPRODUCT(--ISNUMBER(SEARCH(REF_Setup!$B$3:$B$40,M77)))>0,"Strategic Only",IF(SUMPRODUCT(--ISNUMBER(SEARCH(REF_Setup!$F$3:$F$15,M77)))>0,"VC Only","Unclassified"))))} -> VC Only
B78: =B77+1 -> 76 | C78: =IFERROR(_xlfn.XLOOKUP($B78,Raw_Data!$A$3:$A$273,Raw_Data!$B$3:$B$273),"") -> Evergreen (Other Commercial Products) | D78: =IFERROR(_xlfn.XLOOKUP($B78,Raw_Data!$A$3:$A$273,Raw_Data!$C$3:$C$273),"") -> Albany, NY | E78: =IFERROR(_xlfn.XLOOKUP($B78,Raw_Data!$A$3:$A$273,Raw_Data!$D$3:$D$273),"") -> 1998 | F78: =IFERROR(_xlfn.XLOOKUP($B78,Raw_Data!$A$3:$A$273,Raw_Data!$F$3:$F$273),"") -> Industrial Decarbonization | G78: =IFERROR(_xlfn.XLOOKUP($B78,Raw_Data!$A$3:$A$273,Raw_Data!$J$3:$J$273),"") -> 44621 | H78: Development capital | I78: =IFERROR(_xlfn.XLOOKUP($B78,Raw_Data!$A$3:$A$273,Raw_Data!$I$3:$I$273),"") -> 5 | J78: =IFERROR(_xlfn.XLOOKUP($B78,Raw_Data!$A$3:$A$273,Raw_Data!$L$3:$L$273),"") -> 0 | K78: =IFERROR(_xlfn.XLOOKUP($B78,Raw_Data!$A$3:$A$273,Raw_Data!$M$3:$M$273),"") -> 0 | L78: =IFERROR(_xlfn.XLOOKUP($B78,Raw_Data!$A$3:$A$273,Raw_Data!$Q$3:$Q$273),"") -> N/A | M78: =IFERROR(_xlfn.XLOOKUP($B78,Raw_Data!$A$3:$A$273,Raw_Data!$R$3:$R$273),"") -> The Sterling Group | N78: {=IF(M78="",0,COUNTA(_xlfn._xlws.FILTER(_xlfn.TEXTSPLIT(M78,";"), _xlfn.TEXTSPLIT(M78,";")<>"")))} -> 1 | O78: =IF(P78>0,"Y","N") -> N | P78: =IFERROR(_xlfn.XLOOKUP($B78,Raw_Data!$A$3:$A$273,Raw_Data!$V$3:$V$273),"") -> 0 | Q78: =IF(R78>0,"Y","N") -> Y | R78: =IFERROR(_xlfn.XLOOKUP($B78,Raw_Data!$A$3:$A$273,Raw_Data!$Y$3:$Y$273),"") -> 1 | S78: {=_xlfn.LET(_xlpm.s, Raw_Data!W78,_xlpm.strat, _xlfn._xlws.FILTER(REF_Setup!$B$3:$B$40, REF_Setup!$B$3:$B$40<>""),IF(OR(_xlpm.s="",_xlpm.s=0),"Unclassified",IF(SUM(--ISNUMBER(SEARCH(_xlpm.strat, _xlpm.s)))>0, "Y", "N")) )} -> N | T78: {=_xlfn.LET(_xlpm.s,M78,_xlpm.phil, _xlfn._xlws.FILTER(REF_Setup!$D$3:$D$5, REF_Setup!$D$3:$D$5<>""),IF(OR(_xlpm.s="", _xlpm.s=0),"Unclassified",IF(SUM(--ISNUMBER(SEARCH(_xlpm.phil, _xlpm.s)))>0, "Y", "N")))} -> N | U78: {=IF(M78="", "Unclassified", IF(AND(SUMPRODUCT(--ISNUMBER(SEARCH(REF_Setup!$B$3:$B$40,M78)))>0,SUMPRODUCT(--ISNUMBER(SEARCH(REF_Setup!$F$3:$F$15,M78)))>0),"Mixed",IF(SUMPRODUCT(--ISNUMBER(SEARCH(REF_Setup!$B$3:$B$40,M78)))>0,"Strategic Only",IF(SUMPRODUCT(--ISNUMBER(SEARCH(REF_Setup!$F$3:$F$15,M78)))>0,"VC Only","Unclassified"))))} -> VC Only
B79: =B78+1 -> 77 | C79: =IFERROR(_xlfn.XLOOKUP($B79,Raw_Data!$A$3:$A$273,Raw_Data!$B$3:$B$273),"") -> Exowatt | D79: =IFERROR(_xlfn.XLOOKUP($B79,Raw_Data!$A$3:$A$273,Raw_Data!$C$3:$C$273),"") -> Miami, FL | E79: =IFERROR(_xlfn.XLOOKUP($B79,Raw_Data!$A$3:$A$273,Raw_Data!$D$3:$D$273),"") -> 2023 | F79: =IFERROR(_xlfn.XLOOKUP($B79,Raw_Data!$A$3:$A$273,Raw_Data!$F$3:$F$273),"") -> LDES | G79: =IFERROR(_xlfn.XLOOKUP($B79,Raw_Data!$A$3:$A$273,Raw_Data!$J$3:$J$273),"") -> 45974 | H79: Series A | I79: =IFERROR(_xlfn.XLOOKUP($B79,Raw_Data!$A$3:$A$273,Raw_Data!$I$3:$I$273),"") -> 140 | J79: =IFERROR(_xlfn.XLOOKUP($B79,Raw_Data!$A$3:$A$273,Raw_Data!$L$3:$L$273),"") -> 120 | K79: =IFERROR(_xlfn.XLOOKUP($B79,Raw_Data!$A$3:$A$273,Raw_Data!$M$3:$M$273),"") -> 0 | L79: =IFERROR(_xlfn.XLOOKUP($B79,Raw_Data!$A$3:$A$273,Raw_Data!$Q$3:$Q$273),"") -> 0 | M79: =IFERROR(_xlfn.XLOOKUP($B79,Raw_Data!$A$3:$A$273,Raw_Data!$R$3:$R$273),"") -> 8090 Industries; Felicis; MVP Ventures; Atomic; Dragon Global; New Atlas Capital; Brex Asset Management; Bay Bridge Ventures; Florida Opportunity Fund; Andreessen Horowitz; Deepwork Capital; Protagonist; Overmatch; MCJ; Thrive Capital; Goat Ventures; Massive Capital Partners; Leonardo DiCaprio; Upsher Management Company; Alpen Capital; StepStone Group; Starwood Capital Group | N79: {=IF(M79="",0,COUNTA(_xlfn._xlws.FILTER(_xlfn.TEXTSPLIT(M79,";"), _xlfn.TEXTSPLIT(M79,";")<>"")))} -> 22 | O79: =IF(P79>0,"Y","N") -> Y | P79: =IFERROR(_xlfn.XLOOKUP($B79,Raw_Data!$A$3:$A$273,Raw_Data!$V$3:$V$273),"") -> 0.45454545 | Q79: =IF(R79>0,"Y","N") -> Y | R79: =IFERROR(_xlfn.XLOOKUP($B79,Raw_Data!$A$3:$A$273,Raw_Data!$Y$3:$Y$273),"") -> 0.59090909 | S79: {=_xlfn.LET(_xlpm.s, Raw_Data!W79,_xlpm.strat, _xlfn._xlws.FILTER(REF_Setup!$B$3:$B$40, REF_Setup!$B$3:$B$40<>""),IF(OR(_xlpm.s="",_xlpm.s=0),"Unclassified",IF(SUM(--ISNUMBER(SEARCH(_xlpm.strat, _xlpm.s)))>0, "Y", "N")) )} -> N | T79: {=_xlfn.LET(_xlpm.s,M79,_xlpm.phil, _xlfn._xlws.FILTER(REF_Setup!$D$3:$D$5, REF_Setup!$D$3:$D$5<>""),IF(OR(_xlpm.s="", _xlpm.s=0),"Unclassified",IF(SUM(--ISNUMBER(SEARCH(_xlpm.phil, _xlpm.s)))>0, "Y", "N")))} -> N | U79: {=IF(M79="", "Unclassified", IF(AND(SUMPRODUCT(--ISNUMBER(SEARCH(REF_Setup!$B$3:$B$40,M79)))>0,SUMPRODUCT(--ISNUMBER(SEARCH(REF_Setup!$F$3:$F$15,M79)))>0),"Mixed",IF(SUMPRODUCT(--ISNUMBER(SEARCH(REF_Setup!$B$3:$B$40,M79)))>0,"Strategic Only",IF(SUMPRODUCT(--ISNUMBER(SEARCH(REF_Setup!$F$3:$F$15,M79)))>0,"VC Only","Unclassified"))))} -> VC Only
B80: =B79+1 -> 78 | C80: =IFERROR(_xlfn.XLOOKUP($B80,Raw_Data!$A$3:$A$273,Raw_Data!$B$3:$B$273),"") -> Faraday Future Intelligent Electric (NAS: FFAI) | D80: =IFERROR(_xlfn.XLOOKUP($B80,Raw_Data!$A$3:$A$273,Raw_Data!$C$3:$C$273),"") -> Gardena, CA | E80: =IFERROR(_xlfn.XLOOKUP($B80,Raw_Data!$A$3:$A$273,Raw_Data!$D$3:$D$273),"") -> 2014 | F80: =IFERROR(_xlfn.XLOOKUP($B80,Raw_Data!$A$3:$A$273,Raw_Data!$F$3:$F$273),"") -> Mobility | G80: =IFERROR(_xlfn.XLOOKUP($B80,Raw_Data!$A$3:$A$273,Raw_Data!$J$3:$J$273),"") -> 43584 | H80: Series B | I80: =IFERROR(_xlfn.XLOOKUP($B80,Raw_Data!$A$3:$A$273,Raw_Data!$I$3:$I$273),"") -> 4361 | J80: =IFERROR(_xlfn.XLOOKUP($B80,Raw_Data!$A$3:$A$273,Raw_Data!$L$3:$L$273),"") -> 1250 | K80: =IFERROR(_xlfn.XLOOKUP($B80,Raw_Data!$A$3:$A$273,Raw_Data!$M$3:$M$273),"") -> 0 | L80: =IFERROR(_xlfn.XLOOKUP($B80,Raw_Data!$A$3:$A$273,Raw_Data!$Q$3:$Q$273),"") -> 0.18 | N80: {=IF(M80="",0,COUNTA(_xlfn._xlws.FILTER(_xlfn.TEXTSPLIT(M80,";"), _xlfn.TEXTSPLIT(M80,";")<>"")))} -> 0 | O80: =IF(P80>0,"Y","N") -> Y | P80: =IFERROR(_xlfn.XLOOKUP($B80,Raw_Data!$A$3:$A$273,Raw_Data!$V$3:$V$273),"") -> N/A | Q80: =IF(R80>0,"Y","N") -> Y | R80: =IFERROR(_xlfn.XLOOKUP($B80,Raw_Data!$A$3:$A$273,Raw_Data!$Y$3:$Y$273),"") -> N/A | S80: {=_xlfn.LET(_xlpm.s, Raw_Data!W80,_xlpm.strat, _xlfn._xlws.FILTER(REF_Setup!$B$3:$B$40, REF_Setup!$B$3:$B$40<>""),IF(OR(_xlpm.s="",_xlpm.s=0),"Unclassified",IF(SUM(--ISNUMBER(SEARCH(_xlpm.strat, _xlpm.s)))>0, "Y", "N")) )} -> Unclassified | T80: {=_xlfn.LET(_xlpm.s,M80,_xlpm.phil, _xlfn._xlws.FILTER(REF_Setup!$D$3:$D$5, REF_Setup!$D$3:$D$5<>""),IF(OR(_xlpm.s="", _xlpm.s=0),"Unclassified",IF(SUM(--ISNUMBER(SEARCH(_xlpm.phil, _xlpm.s)))>0, "Y", "N")))} -> Unclassified | U80: {=IF(M80="", "Unclassified", IF(AND(SUMPRODUCT(--ISNUMBER(SEARCH(REF_Setup!$B$3:$B$40,M80)))>0,SUMPRODUCT(--ISNUMBER(SEARCH(REF_Setup!$F$3:$F$15,M80)))>0),"Mixed",IF(SUMPRODUCT(--ISNUMBER(SEARCH(REF_Setup!$B$3:$B$40,M80)))>0,"Strategic Only",IF(SUMPRODUCT(--ISNUMBER(SEARCH(REF_Setup!$F$3:$F$15,M80)))>0,"VC Only","Unclassified"))))} -> Unclassified
B81: =B80+1 -> 79 | C81: =IFERROR(_xlfn.XLOOKUP($B81,Raw_Data!$A$3:$A$273,Raw_Data!$B$3:$B$273),"") -> Fermata Energy | D81: =IFERROR(_xlfn.XLOOKUP($B81,Raw_Data!$A$3:$A$273,Raw_Data!$C$3:$C$273),"") -> Charlottesville, VA | E81: =IFERROR(_xlfn.XLOOKUP($B81,Raw_Data!$A$3:$A$273,Raw_Data!$D$3:$D$273),"") -> 2010 | F81: =IFERROR(_xlfn.XLOOKUP($B81,Raw_Data!$A$3:$A$273,Raw_Data!$F$3:$F$273),"") -> Mobility | G81: =IFERROR(_xlfn.XLOOKUP($B81,Raw_Data!$A$3:$A$273,Raw_Data!$J$3:$J$273),"") -> 43069 | H81: Series A | I81: =IFERROR(_xlfn.XLOOKUP($B81,Raw_Data!$A$3:$A$273,Raw_Data!$I$3:$I$273),"") -> 7.92 | J81: =IFERROR(_xlfn.XLOOKUP($B81,Raw_Data!$A$3:$A$273,Raw_Data!$L$3:$L$273),"") -> 3.92 | K81: =IFERROR(_xlfn.XLOOKUP($B81,Raw_Data!$A$3:$A$273,Raw_Data!$M$3:$M$273),"") -> 0 | L81: =IFERROR(_xlfn.XLOOKUP($B81,Raw_Data!$A$3:$A$273,Raw_Data!$Q$3:$Q$273),"") -> 0 | N81: {=IF(M81="",0,COUNTA(_xlfn._xlws.FILTER(_xlfn.TEXTSPLIT(M81,";"), _xlfn.TEXTSPLIT(M81,";")<>"")))} -> 0 | O81: =IF(P81>0,"Y","N") -> Y | P81: =IFERROR(_xlfn.XLOOKUP($B81,Raw_Data!$A$3:$A$273,Raw_Data!$V$3:$V$273),"") -> N/A | Q81: =IF(R81>0,"Y","N") -> Y | R81: =IFERROR(_xlfn.XLOOKUP($B81,Raw_Data!$A$3:$A$273,Raw_Data!$Y$3:$Y$273),"") -> N/A | S81: {=_xlfn.LET(_xlpm.s, Raw_Data!W81,_xlpm.strat, _xlfn._xlws.FILTER(REF_Setup!$B$3:$B$40, REF_Setup!$B$3:$B$40<>""),IF(OR(_xlpm.s="",_xlpm.s=0),"Unclassified",IF(SUM(--ISNUMBER(SEARCH(_xlpm.strat, _xlpm.s)))>0, "Y", "N")) )} -> Unclassified | T81: {=_xlfn.LET(_xlpm.s,M81,_xlpm.phil, _xlfn._xlws.FILTER(REF_Setup!$D$3:$D$5, REF_Setup!$D$3:$D$5<>""),IF(OR(_xlpm.s="", _xlpm.s=0),"Unclassified",IF(SUM(--ISNUMBER(SEARCH(_xlpm.phil, _xlpm.s)))>0, "Y", "N")))} -> Unclassified | U81: {=IF(M81="", "Unclassified", IF(AND(SUMPRODUCT(--ISNUMBER(SEARCH(REF_Setup!$B$3:$B$40,M81)))>0,SUMPRODUCT(--ISNUMBER(SEARCH(REF_Setup!$F$3:$F$15,M81)))>0),"Mixed",IF(SUMPRODUCT(--ISNUMBER(SEARCH(REF_Setup!$B$3:$B$40,M81)))>0,"Strategic Only",IF(SUMPRODUCT(--ISNUMBER(SEARCH(REF_Setup!$F$3:$F$15,M81)))>0,"VC Only","Unclassified"))))} -> Unclassified
B82: =B81+1 -> 80 | C82: =IFERROR(_xlfn.XLOOKUP($B82,Raw_Data!$A$3:$A$273,Raw_Data!$B$3:$B$273),"") -> Fervo Energy | D82: =IFERROR(_xlfn.XLOOKUP($B82,Raw_Data!$A$3:$A$273,Raw_Data!$C$3:$C$273),"") -> Houston, TX | E82: =IFERROR(_xlfn.XLOOKUP($B82,Raw_Data!$A$3:$A$273,Raw_Data!$D$3:$D$273),"") -> 2017 | F82: =IFERROR(_xlfn.XLOOKUP($B82,Raw_Data!$A$3:$A$273,Raw_Data!$F$3:$F$273),"") -> Renewables | G82: =IFERROR(_xlfn.XLOOKUP($B82,Raw_Data!$A$3:$A$273,Raw_Data!$J$3:$J$273),"") -> 45545 | H82: Debt | I82: =IFERROR(_xlfn.XLOOKUP($B82,Raw_Data!$A$3:$A$273,Raw_Data!$I$3:$I$273),"") -> 521.47 | J82: =IFERROR(_xlfn.XLOOKUP($B82,Raw_Data!$A$3:$A$273,Raw_Data!$L$3:$L$273),"") -> 100 | K82: =IFERROR(_xlfn.XLOOKUP($B82,Raw_Data!$A$3:$A$273,Raw_Data!$M$3:$M$273),"") -> 0 | L82: =IFERROR(_xlfn.XLOOKUP($B82,Raw_Data!$A$3:$A$273,Raw_Data!$Q$3:$Q$273),"") -> 1 | N82: {=IF(M82="",0,COUNTA(_xlfn._xlws.FILTER(_xlfn.TEXTSPLIT(M82,";"), _xlfn.TEXTSPLIT(M82,";")<>"")))} -> 0 | O82: =IF(P82>0,"Y","N") -> Y | P82: =IFERROR(_xlfn.XLOOKUP($B82,Raw_Data!$A$3:$A$273,Raw_Data!$V$3:$V$273),"") -> N/A | Q82: =IF(R82>0,"Y","N") -> Y | R82: =IFERROR(_xlfn.XLOOKUP($B82,Raw_Data!$A$3:$A$273,Raw_Data!$Y$3:$Y$273),"") -> N/A | S82: {=_xlfn.LET(_xlpm.s, Raw_Data!W82,_xlpm.strat, _xlfn._xlws.FILTER(REF_Setup!$B$3:$B$40, REF_Setup!$B$3:$B$40<>""),IF(OR(_xlpm.s="",_xlpm.s=0),"Unclassified",IF(SUM(--ISNUMBER(SEARCH(_xlpm.strat, _xlpm.s)))>0, "Y", "N")) )} -> Unclassified | T82: {=_xlfn.LET(_xlpm.s,M82,_xlpm.phil, _xlfn._xlws.FILTER(REF_Setup!$D$3:$D$5, REF_Setup!$D$3:$D$5<>""),IF(OR(_xlpm.s="", _xlpm.s=0),"Unclassified",IF(SUM(--ISNUMBER(SEARCH(_xlpm.phil, _xlpm.s)))>0, "Y", "N")))} -> Unclassified | U82: {=IF(M82="", "Unclassified", IF(AND(SUMPRODUCT(--ISNUMBER(SEARCH(REF_Setup!$B$3:$B$40,M82)))>0,SUMPRODUCT(--ISNUMBER(SEARCH(REF_Setup!$F$3:$F$15,M82)))>0),"Mixed",IF(SUMPRODUCT(--ISNUMBER(SEARCH(REF_Setup!$B$3:$B$40,M82)))>0,"Strategic Only",IF(SUMPRODUCT(--ISNUMBER(SEARCH(REF_Setup!$F$3:$F$15,M82)))>0,"VC Only","Unclassified"))))} -> Unclassified
B83: =B82+1 -> 81 | C83: =IFERROR(_xlfn.XLOOKUP($B83,Raw_Data!$A$3:$A$273,Raw_Data!$B$3:$B$273),"") -> Finless Foods | D83: =IFERROR(_xlfn.XLOOKUP($B83,Raw_Data!$A$3:$A$273,Raw_Data!$C$3:$C$273),"") -> San Francisco,CA | E83: =IFERROR(_xlfn.XLOOKUP($B83,Raw_Data!$A$3:$A$273,Raw_Data!$D$3:$D$273),"") -> 2017 | F83: =IFERROR(_xlfn.XLOOKUP($B83,Raw_Data!$A$3:$A$273,Raw_Data!$F$3:$F$273),"") -> Food & Ag | G83: =IFERROR(_xlfn.XLOOKUP($B83,Raw_Data!$A$3:$A$273,Raw_Data!$J$3:$J$273),"") -> 44085 | H83: Series A | I83: =IFERROR(_xlfn.XLOOKUP($B83,Raw_Data!$A$3:$A$273,Raw_Data!$I$3:$I$273),"") -> 14 | J83: =IFERROR(_xlfn.XLOOKUP($B83,Raw_Data!$A$3:$A$273,Raw_Data!$L$3:$L$273),"") -> 10.23 | K83: =IFERROR(_xlfn.XLOOKUP($B83,Raw_Data!$A$3:$A$273,Raw_Data!$M$3:$M$273),"") -> 30.23 | L83: =IFERROR(_xlfn.XLOOKUP($B83,Raw_Data!$A$3:$A$273,Raw_Data!$Q$3:$Q$273),"") -> 0 | M83: =IFERROR(_xlfn.XLOOKUP($B83,Raw_Data!$A$3:$A$273,Raw_Data!$R$3:$R$273),"") -> AiiM Partners; Alecla7; At One Ventures; Cognic Capital; Draper Associates; Emergence Industries; Endurance28; Gaingels; Good Seed Ventures; Hemisphere Ventures; JKS Ventures; Joyance Partners; Magic Hour; Rise Together; Seabird Ventures; Samsarik Capital; SOSV; Synergeticl VU enture Partners | N83: {=IF(M83="",0,COUNTA(_xlfn._xlws.FILTER(_xlfn.TEXTSPLIT(M83,";"), _xlfn.TEXTSPLIT(M83,";")<>"")))} -> 18 | O83: =IF(P83>0,"Y","N") -> Y | P83: =IFERROR(_xlfn.XLOOKUP($B83,Raw_Data!$A$3:$A$273,Raw_Data!$V$3:$V$273),"") -> 0.16666667 | Q83: =IF(R83>0,"Y","N") -> Y | R83: =IFERROR(_xlfn.XLOOKUP($B83,Raw_Data!$A$3:$A$273,Raw_Data!$Y$3:$Y$273),"") -> 0.88888889 | S83: {=_xlfn.LET(_xlpm.s, Raw_Data!W83,_xlpm.strat, _xlfn._xlws.FILTER(REF_Setup!$B$3:$B$40, REF_Setup!$B$3:$B$40<>""),IF(OR(_xlpm.s="",_xlpm.s=0),"Unclassified",IF(SUM(--ISNUMBER(SEARCH(_xlpm.strat, _xlpm.s)))>0, "Y", "N")) )} -> N | T83: {=_xlfn.LET(_xlpm.s,M83,_xlpm.phil, _xlfn._xlws.FILTER(REF_Setup!$D$3:$D$5, REF_Setup!$D$3:$D$5<>""),IF(OR(_xlpm.s="", _xlpm.s=0),"Unclassified",IF(SUM(--ISNUMBER(SEARCH(_xlpm.phil, _xlpm.s)))>0, "Y", "N")))} -> N | U83: {=IF(M83="", "Unclassified", IF(AND(SUMPRODUCT(--ISNUMBER(SEARCH(REF_Setup!$B$3:$B$40,M83)))>0,SUMPRODUCT(--ISNUMBER(SEARCH(REF_Setup!$F$3:$F$15,M83)))>0),"Mixed",IF(SUMPRODUCT(--ISNUMBER(SEARCH(REF_Setup!$B$3:$B$40,M83)))>0,"Strategic Only",IF(SUMPRODUCT(--ISNUMBER(SEARCH(REF_Setup!$F$3:$F$15,M83)))>0,"VC Only","Unclassified"))))} -> VC Only
B84: =B83+1 -> 82 | C84: =IFERROR(_xlfn.XLOOKUP($B84,Raw_Data!$A$3:$A$273,Raw_Data!$B$3:$B$273),"") -> Finless Foods | D84: =IFERROR(_xlfn.XLOOKUP($B84,Raw_Data!$A$3:$A$273,Raw_Data!$C$3:$C$273),"") -> San Francisco, CA | E84: =IFERROR(_xlfn.XLOOKUP($B84,Raw_Data!$A$3:$A$273,Raw_Data!$D$3:$D$273),"") -> 2017 | F84: =IFERROR(_xlfn.XLOOKUP($B84,Raw_Data!$A$3:$A$273,Raw_Data!$F$3:$F$273),"") -> Food & Ag | G84: =IFERROR(_xlfn.XLOOKUP($B84,Raw_Data!$A$3:$A$273,Raw_Data!$J$3:$J$273),"") -> 44505 | H84: Series B | I84: =IFERROR(_xlfn.XLOOKUP($B84,Raw_Data!$A$3:$A$273,Raw_Data!$I$3:$I$273),"") -> 14 | J84: =IFERROR(_xlfn.XLOOKUP($B84,Raw_Data!$A$3:$A$273,Raw_Data!$L$3:$L$273),"") -> 0 | K84: =IFERROR(_xlfn.XLOOKUP($B84,Raw_Data!$A$3:$A$273,Raw_Data!$M$3:$M$273),"") -> 0 | L84: =IFERROR(_xlfn.XLOOKUP($B84,Raw_Data!$A$3:$A$273,Raw_Data!$Q$3:$Q$273),"") -> N/A | M84: =IFERROR(_xlfn.XLOOKUP($B84,Raw_Data!$A$3:$A$273,Raw_Data!$R$3:$R$273),"") -> Draper Associates | N84: {=IF(M84="",0,COUNTA(_xlfn._xlws.FILTER(_xlfn.TEXTSPLIT(M84,";"), _xlfn.TEXTSPLIT(M84,";")<>"")))} -> 1 | O84: =IF(P84>0,"Y","N") -> Y | P84: =IFERROR(_xlfn.XLOOKUP($B84,Raw_Data!$A$3:$A$273,Raw_Data!$V$3:$V$273),"") -> 1 | Q84: =IF(R84>0,"Y","N") -> Y | R84: =IFERROR(_xlfn.XLOOKUP($B84,Raw_Data!$A$3:$A$273,Raw_Data!$Y$3:$Y$273),"") -> N/A | S84: {=_xlfn.LET(_xlpm.s, Raw_Data!W84,_xlpm.strat, _xlfn._xlws.FILTER(REF_Setup!$B$3:$B$40, REF_Setup!$B$3:$B$40<>""),IF(OR(_xlpm.s="",_xlpm.s=0),"Unclassified",IF(SUM(--ISNUMBER(SEARCH(_xlpm.strat, _xlpm.s)))>0, "Y", "N")) )} -> Unclassified | T84: {=_xlfn.LET(_xlpm.s,M84,_xlpm.phil, _xlfn._xlws.FILTER(REF_Setup!$D$3:$D$5, REF_Setup!$D$3:$D$5<>""),IF(OR(_xlpm.s="", _xlpm.s=0),"Unclassified",IF(SUM(--ISNUMBER(SEARCH(_xlpm.phil, _xlpm.s)))>0, "Y", "N")))} -> N | U84: {=IF(M84="", "Unclassified", IF(AND(SUMPRODUCT(--ISNUMBER(SEARCH(REF_Setup!$B$3:$B$40,M84)))>0,SUMPRODUCT(--ISNUMBER(SEARCH(REF_Setup!$F$3:$F$15,M84)))>0),"Mixed",IF(SUMPRODUCT(--ISNUMBER(SEARCH(REF_Setup!$B$3:$B$40,M84)))>0,"Strategic Only",IF(SUMPRODUCT(--ISNUMBER(SEARCH(REF_Setup!$F$3:$F$15,M84)))>0,"VC Only","Unclassified"))))} -> Unclassified
B85: =B84+1 -> 83 | C85: =IFERROR(_xlfn.XLOOKUP($B85,Raw_Data!$A$3:$A$273,Raw_Data!$B$3:$B$273),"") -> Flow Environmental Systems | D85: =IFERROR(_xlfn.XLOOKUP($B85,Raw_Data!$A$3:$A$273,Raw_Data!$C$3:$C$273),"") -> Rogers, MN | E85: =IFERROR(_xlfn.XLOOKUP($B85,Raw_Data!$A$3:$A$273,Raw_Data!$D$3:$D$273),"") -> 2021 | F85: =IFERROR(_xlfn.XLOOKUP($B85,Raw_Data!$A$3:$A$273,Raw_Data!$F$3:$F$273),"") -> Buildings | G85: =IFERROR(_xlfn.XLOOKUP($B85,Raw_Data!$A$3:$A$273,Raw_Data!$J$3:$J$273),"") -> 45961 | H85: Seed | I85: =IFERROR(_xlfn.XLOOKUP($B85,Raw_Data!$A$3:$A$273,Raw_Data!$I$3:$I$273),"") -> 3.1 | J85: =IFERROR(_xlfn.XLOOKUP($B85,Raw_Data!$A$3:$A$273,Raw_Data!$L$3:$L$273),"") -> 3.1 | K85: =IFERROR(_xlfn.XLOOKUP($B85,Raw_Data!$A$3:$A$273,Raw_Data!$M$3:$M$273),"") -> 0 | L85: =IFERROR(_xlfn.XLOOKUP($B85,Raw_Data!$A$3:$A$273,Raw_Data!$Q$3:$Q$273),"") -> 0 | N85: {=IF(M85="",0,COUNTA(_xlfn._xlws.FILTER(_xlfn.TEXTSPLIT(M85,";"), _xlfn.TEXTSPLIT(M85,";")<>"")))} -> 0 | O85: =IF(P85>0,"Y","N") -> Y | P85: =IFERROR(_xlfn.XLOOKUP($B85,Raw_Data!$A$3:$A$273,Raw_Data!$V$3:$V$273),"") -> N/A | Q85: =IF(R85>0,"Y","N") -> Y | R85: =IFERROR(_xlfn.XLOOKUP($B85,Raw_Data!$A$3:$A$273,Raw_Data!$Y$3:$Y$273),"") -> N/A | S85: {=_xlfn.LET(_xlpm.s, Raw_Data!W85,_xlpm.strat, _xlfn._xlws.FILTER(REF_Setup!$B$3:$B$40, REF_Setup!$B$3:$B$40<>""),IF(OR(_xlpm.s="",_xlpm.s=0),"Unclassified",IF(SUM(--ISNUMBER(SEARCH(_xlpm.strat, _xlpm.s)))>0, "Y", "N")) )} -> Unclassified | T85: {=_xlfn.LET(_xlpm.s,M85,_xlpm.phil, _xlfn._xlws.FILTER(REF_Setup!$D$3:$D$5, REF_Setup!$D$3:$D$5<>""),IF(OR(_xlpm.s="", _xlpm.s=0),"Unclassified",IF(SUM(--ISNUMBER(SEARCH(_xlpm.phil, _xlpm.s)))>0, "Y", "N")))} -> Unclassified | U85: {=IF(M85="", "Unclassified", IF(AND(SUMPRODUCT(--ISNUMBER(SEARCH(REF_Setup!$B$3:$B$40,M85)))>0,SUMPRODUCT(--ISNUMBER(SEARCH(REF_Setup!$F$3:$F$15,M85)))>0),"Mixed",IF(SUMPRODUCT(--ISNUMBER(SEARCH(REF_Setup!$B$3:$B$40,M85)))>0,"Strategic Only",IF(SUMPRODUCT(--ISNUMBER(SEARCH(REF_Setup!$F$3:$F$15,M85)))>0,"VC Only","Unclassified"))))} -> Unclassified
B86: =B85+1 -> 84 | C86: =IFERROR(_xlfn.XLOOKUP($B86,Raw_Data!$A$3:$A$273,Raw_Data!$B$3:$B$273),"") -> Footprint Power | D86: =IFERROR(_xlfn.XLOOKUP($B86,Raw_Data!$A$3:$A$273,Raw_Data!$C$3:$C$273),"") -> Bridgewater , NJ | E86: =IFERROR(_xlfn.XLOOKUP($B86,Raw_Data!$A$3:$A$273,Raw_Data!$D$3:$D$273),"") -> 2009 | F86: =IFERROR(_xlfn.XLOOKUP($B86,Raw_Data!$A$3:$A$273,Raw_Data!$F$3:$F$273),"") -> Renewables | G86: =IFERROR(_xlfn.XLOOKUP($B86,Raw_Data!$A$3:$A$273,Raw_Data!$J$3:$J$273),"") -> 42013 | H86: Development capital | I86: =IFERROR(_xlfn.XLOOKUP($B86,Raw_Data!$A$3:$A$273,Raw_Data!$I$3:$I$273),"") -> 337 | J86: =IFERROR(_xlfn.XLOOKUP($B86,Raw_Data!$A$3:$A$273,Raw_Data!$L$3:$L$273),"") -> 337 | K86: =IFERROR(_xlfn.XLOOKUP($B86,Raw_Data!$A$3:$A$273,Raw_Data!$M$3:$M$273),"") -> 0 | L86: =IFERROR(_xlfn.XLOOKUP($B86,Raw_Data!$A$3:$A$273,Raw_Data!$Q$3:$Q$273),"") -> 0 | M86: =IFERROR(_xlfn.XLOOKUP($B86,Raw_Data!$A$3:$A$273,Raw_Data!$R$3:$R$273),"") -> Oaktree Capital Management; Toyota Tsusho | N86: {=IF(M86="",0,COUNTA(_xlfn._xlws.FILTER(_xlfn.TEXTSPLIT(M86,";"), _xlfn.TEXTSPLIT(M86,";")<>"")))} -> 2 | O86: =IF(P86>0,"Y","N") -> N | P86: =IFERROR(_xlfn.XLOOKUP($B86,Raw_Data!$A$3:$A$273,Raw_Data!$V$3:$V$273),"") -> 0 | Q86: =IF(R86>0,"Y","N") -> Y | R86: =IFERROR(_xlfn.XLOOKUP($B86,Raw_Data!$A$3:$A$273,Raw_Data!$Y$3:$Y$273),"") -> 1 | S86: {=_xlfn.LET(_xlpm.s, Raw_Data!W86,_xlpm.strat, _xlfn._xlws.FILTER(REF_Setup!$B$3:$B$40, REF_Setup!$B$3:$B$40<>""),IF(OR(_xlpm.s="",_xlpm.s=0),"Unclassified",IF(SUM(--ISNUMBER(SEARCH(_xlpm.strat, _xlpm.s)))>0, "Y", "N")) )} -> Y | T86: {=_xlfn.LET(_xlpm.s,M86,_xlpm.phil, _xlfn._xlws.FILTER(REF_Setup!$D$3:$D$5, REF_Setup!$D$3:$D$5<>""),IF(OR(_xlpm.s="", _xlpm.s=0),"Unclassified",IF(SUM(--ISNUMBER(SEARCH(_xlpm.phil, _xlpm.s)))>0, "Y", "N")))} -> N | U86: {=IF(M86="", "Unclassified", IF(AND(SUMPRODUCT(--ISNUMBER(SEARCH(REF_Setup!$B$3:$B$40,M86)))>0,SUMPRODUCT(--ISNUMBER(SEARCH(REF_Setup!$F$3:$F$15,M86)))>0),"Mixed",IF(SUMPRODUCT(--ISNUMBER(SEARCH(REF_Setup!$B$3:$B$40,M86)))>0,"Strategic Only",IF(SUMPRODUCT(--ISNUMBER(SEARCH(REF_Setup!$F$3:$F$15,M86)))>0,"VC Only","Unclassified"))))} -> Mixed
B87: =B86+1 -> 85 | C87: =IFERROR(_xlfn.XLOOKUP($B87,Raw_Data!$A$3:$A$273,Raw_Data!$B$3:$B$273),"") -> Forever Oceans | D87: =IFERROR(_xlfn.XLOOKUP($B87,Raw_Data!$A$3:$A$273,Raw_Data!$C$3:$C$273),"") -> Bethesda, MD | E87: =IFERROR(_xlfn.XLOOKUP($B87,Raw_Data!$A$3:$A$273,Raw_Data!$D$3:$D$273),"") -> 2014 | F87: =IFERROR(_xlfn.XLOOKUP($B87,Raw_Data!$A$3:$A$273,Raw_Data!$F$3:$F$273),"") -> Food & Ag | G87: =IFERROR(_xlfn.XLOOKUP($B87,Raw_Data!$A$3:$A$273,Raw_Data!$J$3:$J$273),"") -> 43279 | H87: Series A | I87: =IFERROR(_xlfn.XLOOKUP($B87,Raw_Data!$A$3:$A$273,Raw_Data!$I$3:$I$273),"") -> 9.99 | J87: =IFERROR(_xlfn.XLOOKUP($B87,Raw_Data!$A$3:$A$273,Raw_Data!$L$3:$L$273),"") -> 9.89 | K87: =IFERROR(_xlfn.XLOOKUP($B87,Raw_Data!$A$3:$A$273,Raw_Data!$M$3:$M$273),"") -> 38.9 | L87: =IFERROR(_xlfn.XLOOKUP($B87,Raw_Data!$A$3:$A$273,Raw_Data!$Q$3:$Q$273),"") -> 0 | M87: =IFERROR(_xlfn.XLOOKUP($B87,Raw_Data!$A$3:$A$273,Raw_Data!$R$3:$R$273),"") -> Bessemer Venture Partners; Lockheed Martin Ventures; Palapa Ventures; StartX | N87: {=IF(M87="",0,COUNTA(_xlfn._xlws.FILTER(_xlfn.TEXTSPLIT(M87,";"), _xlfn.TEXTSPLIT(M87,";")<>"")))} -> 4 | O87: =IF(P87>0,"Y","N") -> Y | P87: =IFERROR(_xlfn.XLOOKUP($B87,Raw_Data!$A$3:$A$273,Raw_Data!$V$3:$V$273),"") -> 0.5 | Q87: =IF(R87>0,"Y","N") -> Y | R87: =IFERROR(_xlfn.XLOOKUP($B87,Raw_Data!$A$3:$A$273,Raw_Data!$Y$3:$Y$273),"") -> 0.5 | S87: {=_xlfn.LET(_xlpm.s, Raw_Data!W87,_xlpm.strat, _xlfn._xlws.FILTER(REF_Setup!$B$3:$B$40, REF_Setup!$B$3:$B$40<>""),IF(OR(_xlpm.s="",_xlpm.s=0),"Unclassified",IF(SUM(--ISNUMBER(SEARCH(_xlpm.strat, _xlpm.s)))>0, "Y", "N")) )} -> N | T87: {=_xlfn.LET(_xlpm.s,M87,_xlpm.phil, _xlfn._xlws.FILTER(REF_Setup!$D$3:$D$5, REF_Setup!$D$3:$D$5<>""),IF(OR(_xlpm.s="", _xlpm.s=0),"Unclassified",IF(SUM(--ISNUMBER(SEARCH(_xlpm.phil, _xlpm.s)))>0, "Y", "N")))} -> N | U87: {=IF(M87="", "Unclassified", IF(AND(SUMPRODUCT(--ISNUMBER(SEARCH(REF_Setup!$B$3:$B$40,M87)))>0,SUMPRODUCT(--ISNUMBER(SEARCH(REF_Setup!$F$3:$F$15,M87)))>0),"Mixed",IF(SUMPRODUCT(--ISNUMBER(SEARCH(REF_Setup!$B$3:$B$40,M87)))>0,"Strategic Only",IF(SUMPRODUCT(--ISNUMBER(SEARCH(REF_Setup!$F$3:$F$15,M87)))>0,"VC Only","Unclassified"))))} -> VC Only
B88: =B87+1 -> 86 | C88: =IFERROR(_xlfn.XLOOKUP($B88,Raw_Data!$A$3:$A$273,Raw_Data!$B$3:$B$273),"") -> Form Energy | D88: =IFERROR(_xlfn.XLOOKUP($B88,Raw_Data!$A$3:$A$273,Raw_Data!$C$3:$C$273),"") -> Weirton, V'W | E88: =IFERROR(_xlfn.XLOOKUP($B88,Raw_Data!$A$3:$A$273,Raw_Data!$D$3:$D$273),"") -> 2017 | F88: =IFERROR(_xlfn.XLOOKUP($B88,Raw_Data!$A$3:$A$273,Raw_Data!$F$3:$F$273),"") -> LDES | G88: =IFERROR(_xlfn.XLOOKUP($B88,Raw_Data!$A$3:$A$273,Raw_Data!$J$3:$J$273),"") -> 45642 | H88: Debt | I88: =IFERROR(_xlfn.XLOOKUP($B88,Raw_Data!$A$3:$A$273,Raw_Data!$I$3:$I$273),"") -> 1433 | J88: =IFERROR(_xlfn.XLOOKUP($B88,Raw_Data!$A$3:$A$273,Raw_Data!$L$3:$L$273),"") -> 50 | K88: =IFERROR(_xlfn.XLOOKUP($B88,Raw_Data!$A$3:$A$273,Raw_Data!$M$3:$M$273),"") -> 0 | L88: =IFERROR(_xlfn.XLOOKUP($B88,Raw_Data!$A$3:$A$273,Raw_Data!$Q$3:$Q$273),"") -> 1 | N88: {=IF(M88="",0,COUNTA(_xlfn._xlws.FILTER(_xlfn.TEXTSPLIT(M88,";"), _xlfn.TEXTSPLIT(M88,";")<>"")))} -> 0 | O88: =IF(P88>0,"Y","N") -> Y | P88: =IFERROR(_xlfn.XLOOKUP($B88,Raw_Data!$A$3:$A$273,Raw_Data!$V$3:$V$273),"") -> N/A | Q88: =IF(R88>0,"Y","N") -> Y | R88: =IFERROR(_xlfn.XLOOKUP($B88,Raw_Data!$A$3:$A$273,Raw_Data!$Y$3:$Y$273),"") -> N/A | S88: {=_xlfn.LET(_xlpm.s, Raw_Data!W88,_xlpm.strat, _xlfn._xlws.FILTER(REF_Setup!$B$3:$B$40, REF_Setup!$B$3:$B$40<>""),IF(OR(_xlpm.s="",_xlpm.s=0),"Unclassified",IF(SUM(--ISNUMBER(SEARCH(_xlpm.strat, _xlpm.s)))>0, "Y", "N")) )} -> Unclassified | T88: {=_xlfn.LET(_xlpm.s,M88,_xlpm.phil, _xlfn._xlws.FILTER(REF_Setup!$D$3:$D$5, REF_Setup!$D$3:$D$5<>""),IF(OR(_xlpm.s="", _xlpm.s=0),"Unclassified",IF(SUM(--ISNUMBER(SEARCH(_xlpm.phil, _xlpm.s)))>0, "Y", "N")))} -> Unclassified | U88: {=IF(M88="", "Unclassified", IF(AND(SUMPRODUCT(--ISNUMBER(SEARCH(REF_Setup!$B$3:$B$40,M88)))>0,SUMPRODUCT(--ISNUMBER(SEARCH(REF_Setup!$F$3:$F$15,M88)))>0),"Mixed",IF(SUMPRODUCT(--ISNUMBER(SEARCH(REF_Setup!$B$3:$B$40,M88)))>0,"Strategic Only",IF(SUMPRODUCT(--ISNUMBER(SEARCH(REF_Setup!$F$3:$F$15,M88)))>0,"VC Only","Unclassified"))))} -> Unclassified
